Workbook
Name __xlnm.Print_Area: #REF!
Name Add_Budget_Selection: #REF!
Name Analysis_End_Date: #REF!
Name Analysis_End_Month: #REF!
Name Analysis_Length_Months: #REF!
Name Analysis_Length_Years: #REF!
Name Analysis_Start_Date: #REF!
Name Analysis_Start_Month: #REF!
Name Category_1: #REF!
Name Category_2: #REF!
Name Category_3: #REF!
Name Category_4: #REF!
Name Category_5: #REF!
Name Category_6: #REF!
Name Category_7: #REF!
Name Const_End_Date: #REF!
Name Const_End_Month: #REF!
Name Const_Start_Date: #REF!
Name Construction_Int_Rate: #REF!
Name Construction_Length: #REF!
Name Construction_Loan_Amount: #REF!
Name Construction_Module_On?: #REF!
Name Equity_Contribution: #REF!
Name Equity_Share_LP: #REF!
Name Equity_Share_LP_Monthly: #REF!
Name Equity_Share_Sponsor: #REF!
Name Equity_Share_Sponsor_Monthly: #REF!
Name Financing_Module_On: #REF!
Name GL_Module_On?: #REF!
Name Ground_Lease_Years_Remaining: #REF!
Name Growth_Begin_Month: #REF!
Name Investment_Name: #REF!
Name Investment_Period_Months: #REF!
Name IRR_Type: #REF!
Name Jr_Funding_Month: #REF!
Name Label_SF_M2: #REF!
Name Label_Unit_Type: #REF!
Name Label_Unit_Type_Singular: #REF!
Name List_Location: OFFSET(#REF!,0,0,93-COUNTIF(#REF!,""),1)
Name List_Property_Type: OFFSET(#REF!,0,0,1,10-COUNTIF(#REF!,""))
Name Location: #REF!
Name LTC_Actual: #REF!
Name Manager_Salary_Per_Month: #N/A
Name Managersalaryper: #N/A
Name Managersalarypermonth: #N/A
Name MF_1st_Stab_Month: #REF!
Name MF_Module_On: #REF!
Name MF_Units: #REF!
Name MF_Untrended?: #REF!
Name NRA: #REF!
Name Operation_Period_Months: #REF!
Name Operations_Begin_Date: #REF!
Name Operations_Begin_Month: #REF!
Name ORI_1st_Stab_Month: #REF!
Name ORI_Module_On: #REF!
Name ORI_Untrended?: #REF!
Name Per_Unit_Type: #REF!
Name Perm_Debt_Funding: #REF!
Name PermDebt_Funding_Date: #REF!
Name PermDebt_Funding_Month: MAX(#REF!,1)

Sheet Cover Page
N3: =+Dashboard!$E$10
N4: =+Dashboard!$E$12&", "&Dashboard!$E$13
N6: =TODAY()

Sheet Dashboard
C3: Model Dashboard
C5: Assumptions
C7: Transaction Summary | G7: Sources & Uses | L7: Operating Assumptions | Y7: Returns Summary
C9: Transaction Overview | G9: Sources | I9: $ | J9: % | L9: Broader Model General Assumptions | R9: Utility Expenses | U9: Cost / Unit | V9: Year 1 Cost | Y9: Return Summary (Gross)
C10: Investment Name | E10: […] | G10: Total Debt | I10: =+D49 | J10: =+I10/$I$12 | L10: Vacancy | P10: 0.05 | R10: Electric | U10: =+V10/$E$16 | Y10: Scenario 1
C11: Address | E11: […] | G11: Total Equity | I11: =+I12-I10 | J11: =+I11/$I$12 | L11: Rent Increase | P11: 0.03 | R11: Electric - Vacant | U11: =+V11/$E$16 | AA11: Unlevered | AB11: Levered
C12: City | E12: […] | G12: Total Sources | I12: =+I17 | J12: =SUM(J10:J11) | L12: Utility Expense | P12: 0.03 | R12: Water & Sewer | U12: =+V12/$E$16 | Y12: IRR | AA12: =+'Scenario 1'!$E$122 | AB12: =+'Scenario 1'!$E$134
C13: State | E13: […] | L13: Move Outs Per Year | P13: =+O13/E16 | R13: Gas | U13: =+V13/$E$16 | Y13: MOIC | AA13: =+'Scenario 1'!$E$123 | AB13: =+'Scenario 1'!$E$135
C14: Zipcode | E14: […] | G14: Uses | I14: $ | J14: % | L14: Other Income | P14: 0.025 | R14: Cable | U14: =+V14/$E$16 | Y14: Profit ($m) | AA14: =+('Scenario 1'!$J$119+'Scenario 1'!$E$119)/1000000 | AB14: =+('Scenario 1'!$J$131+'Scenario 1'!$E$131)/1000000
C15: Property Type | E15: […] | G15: Purchase Price | I15: =+E32 | J15: =+I15/$I$17 | L15: Inflation Increase | P15: 0.03 | R15: Trash/Garbage | U15: =+V15/$E$16
C16: Units | E16: 72 | G16: Closing and Financing Costs | I16: =+SUM(E34:E40) | J16: =+I16/$I$17 | L16: Insurance Increase | P16: 0.2 | Y16: Return Summary (Gross)
C17: Buildings | E17: […] | G17: Total Uses | I17: =SUM(I15:I16) | J17: =SUM(J15:J16) | Y17: Scenario 2
C18: Year Built | E18: […] | AA18: Unlevered | AB18: Levered
C19: Initial TCCP End Date | E19: […] | G19: Deal Scenario Summary and Stats | L19: Admin Expenses | N19: Growth Rate | O19: Cost / Unit | P19: Yr. 1 Cost | R19: Operating & Maint. | U19: Cost / Unit | V19: Year 1 Cost | Y19: IRR | AA19: =+'Scenario 2'!$E$122 | AB19: =+'Scenario 2'!$E$134
C20: Final Year of LIHTC Restrictions | E20: […] | G20: Unit Occupancy Statistics | I20: # of Units | J20: % | L20: Bad Debt Expense | N20: 0.015 | O20: =+P20/E16 | R20: In-House R&M (per unit) | U20: 0 | V20: =+U20*E16 | Y20: MOIC | AA20: =+'Scenario 2'!$E$123 | AB20: =+'Scenario 2'!$E$135
C21: Total Rentable SF | E21: =+'Rent Roll'!N4 | G21: Occupied Units | I21: ='Rent Roll'!C4 | J21: =+J23-J22 | L21: Replacement Reserves (cost per unit) | N21: 0 | O21: 300 | P21: =+O21*E16 | R21: Turnover (assumed cost per move out) | U21: 700 | V21: =+U21*O13 | Y21: Profit ($m) | AA21: =+('Scenario 2'!$J$119+'Scenario 2'!$E$119)/1000000 | AB21: =+('Scenario 2'!$J$131+'Scenario 2'!$E$131)/1000000
C22: SF / Unit | E22: =+E21/E16 | G22: Vacant Units | I22: ='Rent Roll'!C5 | J22: =I22/I23 | L22: Compliance Fee | N22: 0 | O22: 0 | P22: 0 | R22: Supplies | U22: =+V22/$E$16 | V22: =+(V23*P13)+(V24*E16)*V25
C23: Total Cost / SF | E23: =+I17/E21 | G23: Total Units | I23: =+E16 | J23: =+I23/$I$23 | L23: COVID Late fee (years 1-2) | P23: 0 | R23: Turnover Supplies / Year | V23: 3600 | Y23: Return Summary (Gross)
C24: Total Cost / Unit | E24: =+E22*E23 | R24: Supplies / Unit / Year | V24: 150 | Y24: Scenario 3
C25: TTM Occupancy (insert month / year) | E25: […] | G25: ='Rent Roll'!$J$3 | I25: # of Units | J25: % | L25: Employee Work Schedule Assumptions | R25: Supplies Overage Multiplier | V25: 1.2 | AA25: Unlevered | AB25: Levered
C26: TTM NOI (insert month / year) | E26: […] | G26: ='Rent Roll'!J4 | I26: ='Rent Roll'!K4 | J26: =+I26/$I$31 | L26: Hours per Week | P26: 40 | R26: Appliance/Electrical | U26: 175 | V26: =+(E16/6)*U26 | Y26: IRR | AA26: =+'Scenario 3'!$E$122 | AB26: =+'Scenario 3'!$E$134
G27: ='Rent Roll'!J5 | I27: ='Rent Roll'!K5 | J27: =+I27/$I$31 | L27: Weeks per Year | P27: 52 | R27: HVAC & Plumbing | U27: =+V27/$E$16 | V27: 0 | Y27: MOIC | AA27: =+'Scenario 3'!$E$123 | AB27: =+'Scenario 3'!$E$135
C28: Transaction Assumptions and Statistics | E28: Total Cost | G28: ='Rent Roll'!J6 | I28: ='Rent Roll'!K6 | J28: =+I28/$I$31 | R28: Rent Concessions | U28: 0 | V28: =+U28*$E$16 | Y28: Profit ($m) | AA28: =+('Scenario 3'!$J$119+'Scenario 3'!$E$119)/1000000 | AB28: =+('Scenario 3'!$J$131+'Scenario 3'!$E$131)/1000000
C29: Asking Price | E29: 4300000 | G29: ='Rent Roll'!J7 | I29: ='Rent Roll'!K7 | J29: =+I29/$I$31
C30: Asking Cap Rate (Year 0) | E30: =+'Scenario 0'!E89/Dashboard!E29 | G30: ='Rent Roll'!J8 | I30: ='Rent Roll'!K8 | J30: =+I30/$I$31 | L30: Employee Work Schedule Expenses | M30: Include? | N30: Hourly | O30: Monthly | P30: Yearly | R30: Contract Expenses | V30: Total $
C31: Cost Per Unit (Asking Price) | E31: =+E29/E16 | G31: Total Units | I31: =SUM(I26:I30) | J31: =SUM(J26:J30) | L31: Regional Manager Salary | M31: Yes | N31: =+P31/P26/P27 | O31: 1200 | P31: =++IF(M31="Yes",O31*12,0) | R31: Landscaping/Grounds Contract
C32: Purchase Price | E32: =E29 | L32: Property Manager Salary | M32: Yes | N32: 27 | O32: =+P32/12 | P32: =+IF(M32="Yes",N32*$P$26*$P$27,0) | R32: Fire & Safety System
C33: Cost Per Unit (Purchase Price) | E33: =+E32/$E$16 | G33: ='Rent Roll'!$F$3 | I33: # of Units | J33: % | L33: Assistant Property Manager Salary | M33: No | N33: 20 | O33: =+P33/12 | P33: =+IF(M33="Yes",N33*$P$26*$P$27,0) | R33: Security
C34: Closing Costs | D34: 0.02 | E34: =+$D$34*$E$32 | G34: ='Rent Roll'!F4 | I34: ='Rent Roll'!G4 | J34: =+I34/$I$31 | L34: Commissions / Bonuses | M34: No | N34: 0 | O34: =+P34/12 | P34: =+IF(M34="Yes",N34*$P$26*$P$27,0) | R34: Pest Control
C35: Broker Fees | D35: 0 | E35: =+E32*D35 | G35: ='Rent Roll'!F5 | I35: ='Rent Roll'!G5 | J35: =+I35/$I$31 | L35: Maintenance Salary | M35: Yes | N35: 27 | O35: =+P35/12 | P35: =+IF(M35="Yes",N35*$P$26*$P$27,0) | R35: Misc. Contracts
C36: Rehabilitation Costs | D36: 1000 | E36: =+D36*E16 | G36: ='Rent Roll'!F6 | I36: ='Rent Roll'!G6 | J36: =+I36/$I$31 | L36: Maintenance Assistant Salary | M36: No | N36: 0 | O36: =+P36/12 | P36: =+IF(M36="Yes",N36*$P$26*$P$27,0) | R36: Elevator Costs
C37: Legal Fees | E37: 35000 | G37: ='Rent Roll'!F7 | I37: ='Rent Roll'!G7 | J37: =+I37/$I$31 | L37: Labor Increase % | N37: 0.03 | R37: Snow
C38: Developer Fees | E38: 100000 | G38: ='Rent Roll'!F8 | I38: ='Rent Roll'!G8 | J38: =+I38/$I$31 | R38: Misc. Operating & Maint.
C39: Due Diligence Fees | E39: 25000 | G39: ='Rent Roll'!F9 | I39: ='Rent Roll'!G9 | J39: =+I39/$I$31
C40: Taxes / Title Insurance | E40: 0 | G40: Total Units | I40: =SUM(I34:I39) | J40: =SUM(J34:J39) | L40: Admin Expenses | O40: Cost / Unit | P40: Yr. 1 Cost | R40: Real Estate Taxes and Insurance | V40: Total $
L41: Management Fee (% of Net Rental Income) | P41: 0.05 | R41: Market Value | V41: =+E32*U41
C42: GP / LP Initial Equity Investment | G42: Additional Unit Statistics | L42: Legal Expense | O42: =+P42/$E$16 | P42: 6000 | R42: Less: Taxable Value | V42: =+V41*U42
C43: GP Equity Investment | D43: 0.1 | E43: =+(I17-I10)*D43 | G43: Average Gross Rent | J43: ='Rent Roll'!O4 | L43: Office Expense (Per Unit) | O43: 150 | P43: =+O43*$E$16 | R43: RE Taxes | T43: Prop. Tax Rate (Milage) -> | V43: =+V42*U43/10
C44: LP Equity Investment | D44: =1-D43 | E44: =+(I17-I10)*D44 | G44: Average Effective Rent | J44: ='Rent Roll'!P4 | L44: Travel Cost | O44: =+P44/$E$16 | P44: 6000 | R44: Stormwater Fees
G45: % of Gross Rent | J45: =+J44/J43 | L45: Audit Expense | O45: =+P45/$E$16 | P45: 6500 | R45: Less Discounts | V45: =+V43*U45
C46: Financing Assumptions | L46: Advertising | O46: =+P46/$E$16 | P46: 0 | R46: Total RE Taxes | U46: =+U43 | V46: =+V43+V44-V45
C47: Lender | E47: TBD | G47: Timeline and Exit Assumptions | L47: Training Charge | O47: =+P47/$E$16 | P47: 0
C48: Loan to Value (w/ out addt'l costs) | E48: =+D49/I17 | G48: Timeline Assumptions | L48: Bank Charges | O48: =+P48/$E$16 | P48: 0 | R48: Property & Liability Insurance | U48: 450 | V48: =+U48*E16
C49: Loan to Value (w/ addt'l costs) | D49: =+E49*E32 | E49: 0.65 | G49: Entry Date | J49: 44408 | L49: Bookkeeping | O49: =+P49/$E$16 | P49: 2000 | R49: Workmens Comp | U49: 0.02 | V49: =+SUM($P$32:$P$33,$P$35)*U49
C50: Interest Rate | E50: 0.065 | G50: Investment Period | J50: 60 | L50: Payroll Service | O50: =+P50/$E$16 | P50: 0 | R50: Health Insurance & Other Benefits | U50: 0.03 | V50: =+SUM($P$32:$P$33,$P$35)*U50
C51: Loan Constant | E51: =E50/(1-(1/((1+(E50/12))^(30*12)))) | G51: Exit Date | J51: =+EOMONTH(J49,J50) | L51: Manager Unit | O51: =+P51/$E$16 | P51: 0 | R51: Payroll Tax | U51: 0.1 | V51: =+SUM($P$32:$P$33,$P$35)*U51
C52: Fully Amort / Yr | E52: =+E51*I10 | L52: Misc. Admin Expenses | O52: =+P52/$E$16 | P52: 0 | R52: Misc Taxes, Licenses, Etc.
C53: Interest Only Loan Pmt | E53: =+$I$10*$E$50 | G53: Exit Assumptions
C54: Principal Portion | E54: =+E52-E53 | G54: Cap Rate at Exit | J54: 0.06
C55: Loan Term | E55: 30 | G55: Broker Commission | J55: 0.015
C56: Interest Only Period | E56: 8
C57: DSCR Check | D57: >1.25x? --> | E57: =+'Scenario 0'!$F$81/Dashboard!E52 | G57: GP / LP Split
G58: GP Proceeds | J58: 0.25
G59: LP Proceeds | J59: =1-J58

Sheet Models -->

Sheet Scenario 0
C1: Underwriting Model Scenario 0
D3: Year | E3: 2024 | F3: =+E3+1 | G3: =+F3+1 | H3: =+G3+1 | I3: =+H3+1 | J3: =+I3+1 | K3: =+J3+1 | L3: =+K3+1 | M3: =+L3+1 | ... O3: =+N3+1
C4: Scenario 0 (No Change to Asset)
C6: Income Statement | E6: T12 | F6: 1 | G6: =+F6+1 | H6: =+G6+1 | I6: =+H6+1 | J6: =+I6+1 | K6: =+J6+1 | L6: =+K6+1 | M6: =+L6+1 | N6: =+M6+1 | O6: =+N6+1
A7: GPI | C7: Gross Potential Income | E7: =1561954 | F7: ='Unit Mix'!N26 | G7: ='Unit Mix'!N49 | H7: ='Unit Mix'!N72 | I7: ='Unit Mix'!N95 | J7: =+'Unit Mix'!N118 | K7: =+'Unit Mix'!N141 | L7: =+'Unit Mix'!N164 | M7: =+'Unit Mix'!N187 | N7: =+'Unit Mix'!N210 | O7: ='Unit Mix'!N233
A8: VC | C8: Vacancy Factor | D8: =+Dashboard!$P$10 | E8: 48058 | F8: =+F7*$D$8 | G8: =+G7*$D$8 | H8: =+H7*$D$8 | I8: =+I7*$D$8 | J8: =+J7*$D$8 | K8: =+K7*$D$8 | L8: =+L7*$D$8 | M8: =+M7*$D$8 | ... O8: =+O7*$D$8
C9: Net Rental Income | E9: =+E7-E8 | F9: =+F7-F8 | G9: =+G7-G8 | H9: =+H7-H8 | I9: =+I7-I8 | J9: =+J7-J8 | K9: =+K7-K8 | L9: =+L7-L8 | ... O9: =+O7-O8
A11: OI | C11: Laundry and Other Income | D11: =+Dashboard!$P$14 | E11: 33716 | F11: =+Dashboard!$O$14 | G11: =+F11*(1+$D11) | H11: =+G11*(1+$D11) | I11: =+H11*(1+$D11) | J11: =+I11*(1+$D11) | K11: =+J11*(1+$D11) | L11: =+K11*(1+$D11) | M11: =+L11*(1+$D11) | N11: =+M11*(1+$D11) | O11: =+N11*(1+$D11)
C12: Total Gross Income | E12: =+SUM(E9:E11) | F12: =+SUM(F9:F11) | G12: =+SUM(G9:G11) | H12: =+SUM(H9:H11) | I12: =+SUM(I9:I11) | J12: =+SUM(J9:J11) | K12: =+SUM(K9:K11) | L12: =+SUM(L9:L11) | ... O12: =+SUM(O9:O11)
C13: Gross Income Growth | E13: -- | F13: =+F12/E12-1 | G13: =+G12/F12-1 | H13: =+H12/G12-1 | I13: =+I12/H12-1 | J13: =+J12/I12-1 | K13: =+K12/J12-1 | L13: =+L12/K12-1 | M13: =+M12/L12-1 | ... O13: =+O12/N12-1
C15: Opertating Expenses
A17: BAD | C17: Bad Debt | D17: =+Dashboard!$N$20 | F17: =+Dashboard!P20 | G17: =+F17*(1+$D17) | H17: =+G17*(1+$D17) | I17: =+H17*(1+$D17) | J17: =+I17*(1+$D17) | K17: =+J17*(1+$D17) | L17: =+K17*(1+$D17) | M17: =+L17*(1+$D17) | N17: =+M17*(1+$D17) | O17: =+N17*(1+$D17)
C18: Bad Debt | E18: =+SUM(E17) | F18: =+SUM(F17) | G18: =+SUM(G17) | H18: =+SUM(H17) | I18: =+SUM(I17) | J18: =+SUM(J17) | K18: =+SUM(K17) | L18: =+SUM(L17) | ... O18: =+SUM(O17)
A20: RES | C20: Replacement Reserves | D20: =+Dashboard!$N$21 | E20: =+F20 | F20: =+Dashboard!P21 | G20: =+F20*(1+$D20) | H20: =+G20*(1+$D20) | I20: =+H20*(1+$D20) | J20: =+I20*(1+$D20) | K20: =+J20*(1+$D20) | L20: =+K20*(1+$D20) | M20: =+L20*(1+$D20) | N20: =+M20*(1+$D20) | O20: =+N20*(1+$D20)
A21: COM | C21: Compliance Fee | D21: =+Dashboard!$N$22 | E21: 0 | F21: =+Dashboard!P22 | G21: =+F21*(1+$D21) | H21: =+G21*(1+$D21) | I21: =+H21*(1+$D21) | J21: =+I21*(1+$D21) | K21: =+J21*(1+$D21) | L21: =+K21*(1+$D21) | M21: =+L21*(1+$D21) | N21: =+M21*(1+$D21) | O21: =+N21*(1+$D21)
C22: Total Replacement Reserves | E22: =SUM(E20:E21) | F22: =SUM(F20:F21) | G22: =SUM(G20:G21) | H22: =SUM(H20:H21) | I22: =SUM(I20:I21) | J22: =SUM(J20:J21) | K22: =SUM(K20:K21) | L22: =SUM(L20:L21) | ... O22: =SUM(O20:O21)
A24: REG | C24: Regional Manager Salary | D24: =+Dashboard!$N$37 | F24: =+Dashboard!P31 | G24: =+F24*(1+$D24) | H24: =+G24*(1+$D24) | I24: =+H24*(1+$D24) | J24: =+I24*(1+$D24) | K24: =+J24*(1+$D24) | L24: =+K24*(1+$D24) | M24: =+L24*(1+$D24) | N24: =+M24*(1+$D24) | O24: =+N24*(1+$D24)
A25: MAN | C25: Property Manager Salary | D25: =+Dashboard!$N$37 | F25: =+Dashboard!P32 | G25: =+F25*(1+$D25) | H25: =+G25*(1+$D25) | I25: =+H25*(1+$D25) | J25: =+I25*(1+$D25) | K25: =+J25*(1+$D25) | L25: =+K25*(1+$D25) | M25: =+L25*(1+$D25) | N25: =+M25*(1+$D25) | O25: =+N25*(1+$D25)
A26: ASS | C26: Assistant Manager (over 160 units) | D26: =+Dashboard!$N$37 | F26: =+Dashboard!P33 | G26: =+F26*(1+$D26) | H26: =+G26*(1+$D26) | I26: =+H26*(1+$D26) | J26: =+I26*(1+$D26) | K26: =+J26*(1+$D26) | L26: =+K26*(1+$D26) | M26: =+L26*(1+$D26) | N26: =+M26*(1+$D26) | O26: =+N26*(1+$D26)
A27: PAY | C27: Commissions/Bonuses | D27: =+Dashboard!$N$37 | F27: =+Dashboard!P34 | G27: =+F27*(1+$D27) | H27: =+G27*(1+$D27) | I27: =+H27*(1+$D27) | J27: =+I27*(1+$D27) | K27: =+J27*(1+$D27) | L27: =+K27*(1+$D27) | M27: =+L27*(1+$D27) | N27: =+M27*(1+$D27) | O27: =+N27*(1+$D27)
A28: MAIT | C28: Maintenance Salary | D28: =+Dashboard!$N$37 | F28: =+Dashboard!P35+Dashboard!P36 | G28: =+F28*(1+$D28) | H28: =+G28*(1+$D28) | I28: =+H28*(1+$D28) | J28: =+I28*(1+$D28) | K28: =+J28*(1+$D28) | L28: =+K28*(1+$D28) | M28: =+L28*(1+$D28) | N28: =+M28*(1+$D28) | O28: =+N28*(1+$D28)
C29: Payroll | E29: =SUM(E24:E28) | F29: =SUM(F24:F28) | G29: =SUM(G24:G28) | H29: =SUM(H24:H28) | I29: =SUM(I24:I28) | J29: =SUM(J24:J28) | K29: =SUM(K24:K28) | L29: =SUM(L24:L28) | ... O29: =SUM(O24:O28)
A31: MGMT | C31: Management Fee | D31: =+Dashboard!$P$41 | F31: =+F9*$D$31 | G31: =+G9*$D$31 | H31: =+H9*$D$31 | I31: =+I9*$D$31 | J31: =+J9*$D$31 | K31: =+K9*$D$31 | L31: =+L9*$D$31 | M31: =+M9*$D$31 | ... O31: =+O9*$D$31
A32: LEGAL | C32: Legal Expense | D32: =+Dashboard!$P$15 | F32: =Dashboard!P42 | G32: =+F32*(1+$D32) | H32: =+G32*(1+$D32) | I32: =+H32*(1+$D32) | J32: =+I32*(1+$D32) | K32: =+J32*(1+$D32) | L32: =+K32*(1+$D32) | M32: =+L32*(1+$D32) | N32: =+M32*(1+$D32) | O32: =+N32*(1+$D32)
A33: OFF | C33: Office Expense | D33: =+Dashboard!$P$15 | F33: =Dashboard!P43 | G33: =+F33*(1+$D33) | H33: =+G33*(1+$D33) | I33: =+H33*(1+$D33) | J33: =+I33*(1+$D33) | K33: =+J33*(1+$D33) | L33: =+K33*(1+$D33) | M33: =+L33*(1+$D33) | N33: =+M33*(1+$D33) | O33: =+N33*(1+$D33)
A34: TRAVEL | C34: Travel Cost | D34: =+Dashboard!$P$15 | F34: =Dashboard!P44 | G34: =+F34*(1+$D34) | H34: =+G34*(1+$D34) | I34: =+H34*(1+$D34) | J34: =+I34*(1+$D34) | K34: =+J34*(1+$D34) | L34: =+K34*(1+$D34) | M34: =+L34*(1+$D34) | N34: =+M34*(1+$D34) | O34: =+N34*(1+$D34)
A35: AUD | C35: Audit Expense | D35: =+Dashboard!$P$15 | F35: =Dashboard!P45 | G35: =+F35*(1+$D35) | H35: =+G35*(1+$D35) | I35: =+H35*(1+$D35) | J35: =+I35*(1+$D35) | K35: =+J35*(1+$D35) | L35: =+K35*(1+$D35) | M35: =+L35*(1+$D35) | N35: =+M35*(1+$D35) | O35: =+N35*(1+$D35)
A36: ADV | C36: Advertising | D36: =+Dashboard!$P$15 | F36: =Dashboard!P46 | G36: =+F36*(1+$D36) | H36: =+G36*(1+$D36) | I36: =+H36*(1+$D36) | J36: =+I36*(1+$D36) | K36: =+J36*(1+$D36) | L36: =+K36*(1+$D36) | M36: =+L36*(1+$D36) | N36: =+M36*(1+$D36) | O36: =+N36*(1+$D36)
A37: TRAIN | C37: Training Charge | D37: =+Dashboard!$P$15 | F37: =Dashboard!P47 | G37: =+F37*(1+$D37) | H37: =+G37*(1+$D37) | I37: =+H37*(1+$D37) | J37: =+I37*(1+$D37) | K37: =+J37*(1+$D37) | L37: =+K37*(1+$D37) | M37: =+L37*(1+$D37) | N37: =+M37*(1+$D37) | O37: =+N37*(1+$D37)
A38: BANK | C38: Bank Charges | D38: =+Dashboard!$P$15 | F38: =Dashboard!P48 | G38: =+F38*(1+$D38) | H38: =+G38*(1+$D38) | I38: =+H38*(1+$D38) | J38: =+I38*(1+$D38) | K38: =+J38*(1+$D38) | L38: =+K38*(1+$D38) | M38: =+L38*(1+$D38) | N38: =+M38*(1+$D38) | O38: =+N38*(1+$D38)
A39: BOOK | C39: Bookkeeping | D39: =+Dashboard!$P$15 | F39: =Dashboard!P49 | G39: =+F39*(1+$D39) | H39: =+G39*(1+$D39) | I39: =+H39*(1+$D39) | J39: =+I39*(1+$D39) | K39: =+J39*(1+$D39) | L39: =+K39*(1+$D39) | M39: =+L39*(1+$D39) | N39: =+M39*(1+$D39) | O39: =+N39*(1+$D39)
A40: PAYSERV | C40: Payroll Service | D40: =+Dashboard!$P$15 | F40: =Dashboard!P50 | G40: =+F40*(1+$D40) | H40: =+G40*(1+$D40) | I40: =+H40*(1+$D40) | J40: =+I40*(1+$D40) | K40: =+J40*(1+$D40) | L40: =+K40*(1+$D40) | M40: =+L40*(1+$D40) | N40: =+M40*(1+$D40) | O40: =+N40*(1+$D40)
A41: UNIT | C41: Manager Unit | D41: =+Dashboard!$P$15 | F41: =Dashboard!P51 | G41: =+F41*(1+$D41) | H41: =+G41*(1+$D41) | I41: =+H41*(1+$D41) | J41: =+I41*(1+$D41) | K41: =+J41*(1+$D41) | L41: =+K41*(1+$D41) | M41: =+L41*(1+$D41) | N41: =+M41*(1+$D41) | O41: =+N41*(1+$D41)
A42: MISCAD | C42: Misc. Admin Expenses | D42: =+Dashboard!$P$15 | E42: 0 | F42: =Dashboard!P52 | G42: =+F42*(1+$D42) | H42: =+G42*(1+$D42) | I42: =+H42*(1+$D42) | J42: =+I42*(1+$D42) | K42: =+J42*(1+$D42) | L42: =+K42*(1+$D42) | M42: =+L42*(1+$D42) | N42: =+M42*(1+$D42) | O42: =+N42*(1+$D42)
C43: Admin Expenses | E43: =SUM(E31:E42) | F43: =SUM(F31:F42) | G43: =SUM(G31:G42) | H43: =SUM(H31:H42) | I43: =SUM(I31:I42) | J43: =SUM(J31:J42) | K43: =SUM(K31:K42) | L43: =SUM(L31:L42) | ... O43: =SUM(O31:O42)
A45: ELEC | C45: Electric | D45: =+Dashboard!$P$15 | F45: =+Dashboard!V10 | G45: =+F45*(1+$D45) | H45: =+G45*(1+$D45) | I45: =+H45*(1+$D45) | J45: =+I45*(1+$D45) | K45: =+J45*(1+$D45) | L45: =+K45*(1+$D45) | M45: =+L45*(1+$D45) | N45: =+M45*(1+$D45) | O45: =+N45*(1+$D45)
A46: VAC | C46: Electric - Vacant | D46: =+Dashboard!$P$15 | F46: =+Dashboard!V11 | G46: =+F46*(1+$D46) | H46: =+G46*(1+$D46) | I46: =+H46*(1+$D46) | J46: =+I46*(1+$D46) | K46: =+J46*(1+$D46) | L46: =+K46*(1+$D46) | M46: =+L46*(1+$D46) | N46: =+M46*(1+$D46) | O46: =+N46*(1+$D46)
A47: WS | C47: Water & Sewer | D47: =+Dashboard!$P$15 | F47: =+Dashboard!V12 | G47: =+F47*(1+$D47) | H47: =+G47*(1+$D47) | I47: =+H47*(1+$D47) | J47: =+I47*(1+$D47) | K47: =+J47*(1+$D47) | L47: =+K47*(1+$D47) | M47: =+L47*(1+$D47) | N47: =+M47*(1+$D47) | O47: =+N47*(1+$D47)
A48: GAS | C48: Gas | D48: =+Dashboard!$P$15 | F48: =+Dashboard!V13 | G48: =+F48*(1+$D48) | H48: =+G48*(1+$D48) | I48: =+H48*(1+$D48) | J48: =+I48*(1+$D48) | K48: =+J48*(1+$D48) | L48: =+K48*(1+$D48) | M48: =+L48*(1+$D48) | N48: =+M48*(1+$D48) | O48: =+N48*(1+$D48)
A49: CABLE | C49: Cable | D49: =+Dashboard!$P$15 | F49: =+Dashboard!V14 | G49: =+F49*(1+$D49) | H49: =+G49*(1+$D49) | I49: =+H49*(1+$D49) | J49: =+I49*(1+$D49) | K49: =+J49*(1+$D49) | L49: =+K49*(1+$D49) | M49: =+L49*(1+$D49) | N49: =+M49*(1+$D49) | O49: =+N49*(1+$D49)
A50: TRASH | C50: Trash/Garbage | D50: =+Dashboard!$P$15 | F50: =+Dashboard!V15 | G50: =+F50*(1+$D50) | H50: =+G50*(1+$D50) | I50: =+H50*(1+$D50) | J50: =+I50*(1+$D50) | K50: =+J50*(1+$D50) | L50: =+K50*(1+$D50) | M50: =+L50*(1+$D50) | N50: =+M50*(1+$D50) | O50: =+N50*(1+$D50)
C51: Utility Expenses | E51: =SUM(E45:E50) | F51: =SUM(F45:F50) | G51: =SUM(G45:G50) | H51: =SUM(H45:H50) | I51: =SUM(I45:I50) | J51: =SUM(J45:J50) | K51: =SUM(K45:K50) | L51: =SUM(L45:L50) | ... O51: =SUM(O45:O50)
A53: RM | C53: In-House R&M | D53: =+Dashboard!$P$15 | F53: =+Dashboard!V20 | G53: =+F53*(1+$D53) | H53: =+G53*(1+$D53) | I53: =+H53*(1+$D53) | J53: =+I53*(1+$D53) | K53: =+J53*(1+$D53) | L53: =+K53*(1+$D53) | M53: =+L53*(1+$D53) | N53: =+M53*(1+$D53) | O53: =+N53*(1+$D53)
A54: TURN | C54: Turnover | D54: =+Dashboard!$P$15 | F54: =+Dashboard!V21 | G54: =+F54*(1+$D54) | H54: =+G54*(1+$D54) | I54: =+H54*(1+$D54) | J54: =+I54*(1+$D54) | K54: =+J54*(1+$D54) | L54: =+K54*(1+$D54) | M54: =+L54*(1+$D54) | N54: =+M54*(1+$D54) | O54: =+N54*(1+$D54)
A55: SUPP | C55: Supplies | D55: =+Dashboard!$P$15 | F55: =+Dashboard!V22 | G55: =+F55*(1+$D55) | H55: =+G55*(1+$D55) | I55: =+H55*(1+$D55) | J55: =+I55*(1+$D55) | K55: =+J55*(1+$D55) | L55: =+K55*(1+$D55) | M55: =+L55*(1+$D55) | N55: =+M55*(1+$D55) | O55: =+N55*(1+$D55)
A56: APP | C56: Appliance/Electrical | D56: =+Dashboard!$P$15 | F56: =+Dashboard!V26 | G56: =+F56*(1+$D56) | H56: =+G56*(1+$D56) | I56: =+H56*(1+$D56) | J56: =+I56*(1+$D56) | K56: =+J56*(1+$D56) | L56: =+K56*(1+$D56) | M56: =+L56*(1+$D56) | N56: =+M56*(1+$D56) | O56: =+N56*(1+$D56)
A57: HP | C57: HVAC & Plumbing | D57: =+Dashboard!$P$15 | E57: 0 | F57: =+Dashboard!V27 | G57: =+F57*(1+$D57) | H57: =+G57*(1+$D57) | I57: =+H57*(1+$D57) | J57: =+I57*(1+$D57) | K57: =+J57*(1+$D57) | L57: =+K57*(1+$D57) | M57: =+L57*(1+$D57) | N57: =+M57*(1+$D57) | O57: =+N57*(1+$D57)
A58: CONC | C58: Rent Concessions | D58: =+Dashboard!$P$15 | E58: 0 | F58: =+Dashboard!V28 | G58: =+F58*(1+$D58) | H58: =+G58*(1+$D58) | I58: =+H58*(1+$D58) | J58: =+I58*(1+$D58) | K58: =+J58*(1+$D58) | L58: =+K58*(1+$D58) | M58: =+L58*(1+$D58) | N58: =+M58*(1+$D58) | O58: =+N58*(1+$D58)
C59: Operating and Maint. | E59: =SUM(E53:E58) | F59: =SUM(F53:F58) | G59: =SUM(G53:G58) | H59: =SUM(H53:H58) | I59: =SUM(I53:I58) | J59: =SUM(J53:J58) | K59: =SUM(K53:K58) | L59: =SUM(L53:L58) | ... O59: =SUM(O53:O58)
A61: LAND | C61: Landscaping/Grounds Contract | D61: =+Dashboard!$P$15 | F61: =+Dashboard!V31 | G61: =+F61*(1+$D61) | H61: =+G61*(1+$D61) | I61: =+H61*(1+$D61) | J61: =+I61*(1+$D61) | K61: =+J61*(1+$D61) | L61: =+K61*(1+$D61) | M61: =+L61*(1+$D61) | N61: =+M61*(1+$D61) | O61: =+N61*(1+$D61)
A62: FIRE | C62: Fire & Safety System | D62: =+Dashboard!$P$15 | F62: =+Dashboard!V32 | G62: =+F62*(1+$D62) | H62: =+G62*(1+$D62) | I62: =+H62*(1+$D62) | J62: =+I62*(1+$D62) | K62: =+J62*(1+$D62) | L62: =+K62*(1+$D62) | M62: =+L62*(1+$D62) | N62: =+M62*(1+$D62) | O62: =+N62*(1+$D62)
A63: SEC | C63: Security | D63: =+Dashboard!$P$15 | F63: =+Dashboard!V33 | G63: =+F63*(1+$D63) | H63: =+G63*(1+$D63) | I63: =+H63*(1+$D63) | J63: =+I63*(1+$D63) | K63: =+J63*(1+$D63) | L63: =+K63*(1+$D63) | M63: =+L63*(1+$D63) | N63: =+M63*(1+$D63) | O63: =+N63*(1+$D63)
A64: PEST | C64: Pest Control | D64: =+Dashboard!$P$15 | F64: =+Dashboard!V34 | G64: =+F64*(1+$D64) | H64: =+G64*(1+$D64) | I64: =+H64*(1+$D64) | J64: =+I64*(1+$D64) | K64: =+J64*(1+$D64) | L64: =+K64*(1+$D64) | M64: =+L64*(1+$D64) | N64: =+M64*(1+$D64) | O64: =+N64*(1+$D64)
A65: CON | C65: Misc. Contracts | D65: =+Dashboard!$P$15 | F65: =+Dashboard!V35 | G65: =+F65*(1+$D65) | H65: =+G65*(1+$D65) | I65: =+H65*(1+$D65) | J65: =+I65*(1+$D65) | K65: =+J65*(1+$D65) | L65: =+K65*(1+$D65) | M65: =+L65*(1+$D65) | N65: =+M65*(1+$D65) | O65: =+N65*(1+$D65)
A66: ELEV | C66: Elevator Costs | D66: =+Dashboard!$P$15 | F66: =+Dashboard!V36 | G66: =+F66*(1+$D66) | H66: =+G66*(1+$D66) | I66: =+H66*(1+$D66) | J66: =+I66*(1+$D66) | K66: =+J66*(1+$D66) | L66: =+K66*(1+$D66) | M66: =+L66*(1+$D66) | N66: =+M66*(1+$D66) | O66: =+N66*(1+$D66)
A67: SNOW | C67: Snow | D67: =+Dashboard!$P$15 | F67: =+Dashboard!V37 | G67: =+F67*(1+$D67) | H67: =+G67*(1+$D67) | I67: =+H67*(1+$D67) | J67: =+I67*(1+$D67) | K67: =+J67*(1+$D67) | L67: =+K67*(1+$D67) | M67: =+L67*(1+$D67) | N67: =+M67*(1+$D67) | O67: =+N67*(1+$D67)
A68: MISCOP | C68: Misc. Operating & Maint. | D68: =+Dashboard!$P$15 | F68: =+Dashboard!V38 | G68: =+F68*(1+$D68) | H68: =+G68*(1+$D68) | I68: =+H68*(1+$D68) | J68: =+I68*(1+$D68) | K68: =+J68*(1+$D68) | L68: =+K68*(1+$D68) | M68: =+L68*(1+$D68) | N68: =+M68*(1+$D68) | O68: =+N68*(1+$D68)
C69: Contract Expenses | E69: =SUM(E61:E68) | F69: =SUM(F61:F68) | G69: =SUM(G61:G68) | H69: =SUM(H61:H68) | I69: =SUM(I61:I68) | J69: =SUM(J61:J68) | K69: =SUM(K61:K68) | L69: =SUM(L61:L68) | ... O69: =SUM(O61:O68)
A71: RETAX | C71: Real Estate Taxes | D71: =+Dashboard!$P$15 | F71: =+Dashboard!V46 | G71: =+F71*(1+$D71) | H71: =+G71*(1+$D71) | I71: =+H71*(1+$D71) | J71: =+I71*(1+$D71) | K71: =+J71*(1+$D71) | L71: =+K71*(1+$D71) | M71: =+L71*(1+$D71) | N71: =+M71*(1+$D71) | O71: =+N71*(1+$D71)
A72: INS | C72: Property & Liability Insurance | D72: =+Dashboard!$P$15 | F72: =+Dashboard!V48 | G72: =+F72*(1+$D72) | H72: =+G72*(1+$D72) | I72: =+H72*(1+$D72) | J72: =+I72*(1+$D72) | K72: =+J72*(1+$D72) | L72: =+K72*(1+$D72) | M72: =+L72*(1+$D72) | N72: =+M72*(1+$D72) | O72: =+N72*(1+$D72)
A73: WORKCOMP | C73: Workmens Comp | D73: =+Dashboard!$P$15 | F73: =+Dashboard!V49 | G73: =+F73*(1+$D73) | H73: =+G73*(1+$D73) | I73: =+H73*(1+$D73) | J73: =+I73*(1+$D73) | K73: =+J73*(1+$D73) | L73: =+K73*(1+$D73) | M73: =+L73*(1+$D73) | N73: =+M73*(1+$D73) | O73: =+N73*(1+$D73)
A74: HEALTH | C74: Health Insurance & Other Benefits | D74: =+Dashboard!$P$15 | F74: =+Dashboard!V50 | G74: =+F74*(1+$D74) | H74: =+G74*(1+$D74) | I74: =+H74*(1+$D74) | J74: =+I74*(1+$D74) | K74: =+J74*(1+$D74) | L74: =+K74*(1+$D74) | M74: =+L74*(1+$D74) | N74: =+M74*(1+$D74) | O74: =+N74*(1+$D74)
A75: PTAX | C75: Payroll Tax | D75: =+Dashboard!$P$15 | F75: =+Dashboard!V51 | G75: =+F75*(1+$D75) | H75: =+G75*(1+$D75) | I75: =+H75*(1+$D75) | J75: =+I75*(1+$D75) | K75: =+J75*(1+$D75) | L75: =+K75*(1+$D75) | M75: =+L75*(1+$D75) | N75: =+M75*(1+$D75) | O75: =+N75*(1+$D75)
A76: MISCTAX | C76: Misc Taxes, Licenses, Etc. | D76: =+Dashboard!$P$15 | F76: =+Dashboard!V52 | G76: =+F76*(1+$D76) | H76: =+G76*(1+$D76) | I76: =+H76*(1+$D76) | J76: =+I76*(1+$D76) | K76: =+J76*(1+$D76) | L76: =+K76*(1+$D76) | M76: =+L76*(1+$D76) | N76: =+M76*(1+$D76) | O76: =+N76*(1+$D76)
C77: Total Taxes and Insurance Expenses | E77: =SUM(E71:E76) | F77: =SUM(F71:F76) | G77: =SUM(G71:G76) | H77: =SUM(H71:H76) | I77: =SUM(I71:I76) | J77: =SUM(J71:J76) | K77: =SUM(K71:K76) | L77: =SUM(L71:L76) | ... O77: =SUM(O71:O76)
C79: Total Operating Expenses | E79: =+SUM(E18,E22,E29,E43,E51,E59,E69,E77,) | F79: =+SUM(F18,F22,F29,F43,F51,F59,F69,F77,) | G79: =+SUM(G18,G22,G29,G43,G51,G59,G69,G77,) | H79: =+SUM(H18,H22,H29,H43,H51,H59,H69,H77,) | I79: =+SUM(I18,I22,I29,I43,I51,I59,I69,I77,) | J79: =+SUM(J18,J22,J29,J43,J51,J59,J69,J77,) | K79: =+SUM(K18,K22,K29,K43,K51,K59,K69,K77,) | L79: =+SUM(L18,L22,L29,L43,L51,L59,L69,L77,) | ... O79: =+SUM(O18,O22,O29,O43,O51,O59,O69,O77,)
C81: Net Operating Income | E81: =+E12-E79 | F81: =+F12-F79 | G81: =+G12-G79 | H81: =+H12-H79 | I81: =+I12-I79 | J81: =+J12-J79 | K81: =+K12-K79 | L81: =+L12-L79 | ... O81: =+O12-O79
C82: NOI Margin | E82: =+IFERROR(E81/E12,"--") | F82: =+F81/F12 | G82: =+G81/G12 | H82: =+H81/H12 | I82: =+I81/I12 | J82: =+J81/J12 | K82: =+K81/K12 | L82: =+L81/L12 | M82: =+M81/M12 | ... O82: =+O81/O12
C84: Capital Expenditures
C85: Other CapEx
C86: Capital Reserve
C87: Total Capital Expenditures | E87: =+SUM(E85:E86) | F87: =+SUM(F85:F86) | G87: =+SUM(G85:G86) | H87: =+SUM(H85:H86) | I87: =+SUM(I85:I86) | J87: =+SUM(J85:J86) | K87: =+SUM(K85:K86) | L87: =+SUM(L85:L86) | ... O87: =+SUM(O85:O86)
C89: Cash Flow from Operations (Adj. NOI) | E89: =+E81-E87 | F89: =+F81-F87 | G89: =+G81-G87 | H89: =+H81-H87 | I89: =+I81-I87 | J89: =+J81-J87 | K89: =+K81-K87 | L89: =+L81-L87 | ... O89: =+O81-O87
C91: Interest Expense Debt Service | E91: -- | F91: =+Dashboard!$I$10*Dashboard!$E$50 | G91: =+F91 | H91: =+G91 | I91: =+H91 | J91: =+I91 | K91: =+J91 | L91: =+K91 | M91: =+L91 | N91: =+M91 | O91: =+N91
C92: Principal Repayment | E92: -- | F92: =IF(F$6<=Dashboard!$E$56,0,-PPMT(Dashboard!$E$50,'Scenario 0'!F3-'Scenario 0'!$E3,Dashboard!$E$55,Dashboard!$D$49)) | G92: =IF(G$6<=Dashboard!$E$56,0,-PPMT(Dashboard!$E$50,'Scenario 0'!G3-'Scenario 0'!$E3,Dashboard!$E$55,Dashboard!$D$49)) | H92: =IF(H$6<=Dashboard!$E$56,0,-PPMT(Dashboard!$E$50,'Scenario 0'!H3-'Scenario 0'!$E3,Dashboard!$E$55,Dashboard!$D$49)) | I92: =IF(I$6<=Dashboard!$E$56,0,-PPMT(Dashboard!$E$50,'Scenario 0'!I3-'Scenario 0'!$E3,Dashboard!$E$55,Dashboard!$D$49)) | J92: =IF(J$6<=Dashboard!$E$56,0,-PPMT(Dashboard!$E$50,'Scenario 0'!J3-'Scenario 0'!$E3,Dashboard!$E$55,Dashboard!$D$49)) | K92: =IF(K$6<=Dashboard!$E$56,0,-PPMT(Dashboard!$E$50,'Scenario 0'!K3-'Scenario 0'!$E3,Dashboard!$E$55,Dashboard!$D$49)) | L92: =IF(L$6<=Dashboard!$E$56,0,-PPMT(Dashboard!$E$50,'Scenario 0'!L3-'Scenario 0'!$E3,Dashboard!$E$55,Dashboard!$D$49)) | M92: =IF(M$6<=Dashboard!$E$56,0,-PPMT(Dashboard!$E$50,'Scenario 0'!M3-'Scenario 0'!$E3,Dashboard!$E$55,Dashboard!$D$49)) | ... O92: =IF(O$6<=Dashboard!$E$56,0,-PPMT(Dashboard!$E$50,'Scenario 0'!O3-'Scenario 0'!$E3,Dashboard!$E$55,Dashboard!$D$49))
C93: Cash Flow After Financing (CF to Equity Investors) | E93: -- | F93: =+F89-F91 | G93: =+G89-G91 | H93: =+H89-H91 | I93: =+I89-I91 | J93: =+J89-J91 | K93: =+K89-K91 | L93: =+L89-L91 | M93: =+M89-M91 | N93: =+N89-N91-N92 | O93: =+O89-O91-O92
C95: Ending Debt Balance | F95: =+Dashboard!$D$49-SUM('Scenario 0'!$F$92:F92) | G95: =+Dashboard!$D$49-SUM('Scenario 0'!$F$92:G92) | H95: =+Dashboard!$D$49-SUM('Scenario 0'!$F$92:H92) | I95: =+Dashboard!$D$49-SUM('Scenario 0'!$F$92:I92) | J95: =+Dashboard!$D$49-SUM('Scenario 0'!$F$92:J92) | K95: =+Dashboard!$D$49-SUM('Scenario 0'!$F$92:K92) | L95: =+Dashboard!$D$49-SUM('Scenario 0'!$F$92:L92) | M95: =+Dashboard!$D$49-SUM('Scenario 0'!$F$92:M92) | ... O95: =+Dashboard!$D$49-SUM('Scenario 0'!$F$92:O92)
C97: DSCR (NOI) | F97: =+IFERROR(F81/F91,"") | G97: =+IFERROR(G81/G91,"") | H97: =+IFERROR(H81/H91,"") | I97: =+IFERROR(I81/I91,"") | J97: =+IFERROR(J81/J91,"") | K97: =+IFERROR(K81/K91,"") | L97: =+IFERROR(L81/L91,"") | M97: =+IFERROR(M81/M91,"") | ... O97: =+IFERROR(O81/O91,"")
C98: DSCR (CFO) | F98: =+IFERROR(F89/F91,"") | G98: =+IFERROR(G89/G91,"") | H98: =+IFERROR(H89/H91,"") | I98: =+IFERROR(I89/I91,"") | J98: =+IFERROR(J89/J91,"") | K98: =+IFERROR(K89/K91,"") | L98: =+IFERROR(L89/L91,"") | M98: =+IFERROR(M89/M91,"") | ... O98: =+IFERROR(O89/O91,"")
C99: Debt Yield (CFO) | F99: =+F89/Dashboard!$I$10 | G99: =+G89/Dashboard!$I$10 | H99: =+H89/Dashboard!$I$10 | I99: =+I89/Dashboard!$I$10 | J99: =+J89/Dashboard!$I$10 | K99: =+K89/Dashboard!$I$10 | L99: =+L89/Dashboard!$I$10 | M99: =+M89/Dashboard!$I$10 | ... O99: =+O89/Dashboard!$I$10
C100: Break-Even Ratio | F100: =+SUM(F97,F79)/F12 | G100: =+SUM(G97,G79)/G12 | H100: =+SUM(H97,H79)/H12 | I100: =+SUM(I97,I79)/I12 | J100: =+SUM(J97,J79)/J12 | K100: =+SUM(K97,K79)/K12 | L100: =+SUM(L97,L79)/L12 | M100: =+SUM(M97,M79)/M12 | ... O100: =+SUM(O97,O79)/O12
C102: Cap Rate (Purchase Price) | F102: =+F81/Dashboard!$E$32 | G102: =+G81/Dashboard!$E$32 | H102: =+H81/Dashboard!$E$32 | I102: =+I81/Dashboard!$E$32 | J102: =+J81/Dashboard!$E$32 | K102: =+K81/Dashboard!$E$32 | L102: =+L81/Dashboard!$E$32 | M102: =+M81/Dashboard!$E$32 | ... O102: =+O81/Dashboard!$E$32
C103: Operating Cash Flow Before Taxes | F103: =+F81-F91-F92 | G103: =+G81-G91-G92 | H103: =+H81-H91-H92 | I103: =+I81-I91-I92 | J103: =+J81-J91-J92 | K103: =+K81-K91-K92 | L103: =+L81-L91-L92 | M103: =+M81-M91-M92 | ... O103: =+O81-O91-O92
C104: Cash on Cash Return | F104: =+F103/Dashboard!$I$11 | G104: =+G103/Dashboard!$I$11 | H104: =+H103/Dashboard!$I$11 | I104: =+I103/Dashboard!$I$11 | J104: =+J103/Dashboard!$I$11 | K104: =+K103/Dashboard!$I$11 | L104: =+L103/Dashboard!$I$11 | M104: =+M103/Dashboard!$I$11 | ... O104: =+O103/Dashboard!$I$11
C105: General Partner Cash Return | D105: =+Dashboard!J58 | F105: =+F103*$D$105 | G105: =+G103*$D$105 | H105: =+H103*$D$105 | I105: =+I103*$D$105 | J105: =+J103*$D$105 | K105: =+K103*$D$105 | L105: =+L103*$D$105 | M105: =+M103*$D$105 | ... O105: =+O103*$D$105
C106: Total Limited Partner Cash Return | D106: =+Dashboard!J59 | F106: =+F103*$D$106 | G106: =+G103*$D$106 | H106: =+H103*$D$106 | I106: =+I103*$D$106 | J106: =+J103*$D$106 | K106: =+K103*$D$106 | L106: =+L103*$D$106 | M106: =+M103*$D$106 | ... O106: =+O103*$D$106
C107: Cash on Cash LP Return | F107: =+F106/Dashboard!$I$11 | G107: =+G106/Dashboard!$I$11 | H107: =+H106/Dashboard!$I$11 | I107: =+I106/Dashboard!$I$11 | J107: =+J106/Dashboard!$I$11 | K107: =+K106/Dashboard!$I$11 | L107: =+L106/Dashboard!$I$11 | M107: =+M106/Dashboard!$I$11 | ... O107: =+O106/Dashboard!$I$11
C109: Return Metrics
C111: 5 Year Hold IRR | E111: Year 0 | F111: 1 | G111: 2 | H111: 3 | I111: 4 | J111: 5
C113: Exit Cap Rate Assumption | D113: =+Dashboard!$J$54
C115: Project Cash Flows (Unleveraged IRR):
C116: (+) Proceeds from Sale of Property: | F116: 0 | G116: 0 | H116: 0 | I116: 0 | J116: =+J$81/D$113
C117: (-) Selling Costs: | D117: =+Dashboard!$J$55 | F117: 0 | G117: 0 | H117: 0 | I117: 0 | J117: =-J$116*D$117
C118: (+) Adjusted NOI (Cash Flows to All Investors): | F118: =+F$89 | G118: =+G$89 | H118: =+H$89 | I118: =+I$89 | J118: =+J$89
C119: (-) Property Acquisition Price: | E119: =-Dashboard!$E$32 | F119: 0 | G119: 0 | H119: 0 | I119: 0 | J119: 0
C120: Total Project Cash Flows (Unleveraged IRR): | E120: =SUM(E116:E119) | F120: =SUM(F116:F119) | G120: =SUM(G116:G119) | H120: =SUM(H116:H119) | I120: =SUM(I116:I119) | J120: =SUM(J116:J119)
F121: =+F120-F116 | G121: =+G120-G116 | H121: =+H120-H116 | I121: =+I120-I116 | J121: =+J120-J116
C123: Unlevered IRR: | E123: =+IRR(E120:J120)
C124: Unlevered Cash-on-Cash Multiple: | E124: =+SUM(F116:J118)/-SUM(E119:J119)
C126: Cash Flow to Equity Investors (Leveraged IRR):
...

Sheet Scenario 1
C1: Underwriting Model Scenario 1
D3: Year | E3: =+'Scenario 0'!E3 | F3: =+'Scenario 0'!F3 | G3: =+'Scenario 0'!G3 | H3: =+'Scenario 0'!H3 | I3: =+'Scenario 0'!I3 | J3: =+'Scenario 0'!J3 | K3: =+'Scenario 0'!K3 | L3: =+'Scenario 0'!L3 | ... O3: =+'Scenario 0'!O3
C4: ='Unit Mix'!$P$3
C6: Income Statement | E6: =+'Scenario 0'!E6 | F6: =+'Scenario 0'!F6 | G6: =+'Scenario 0'!G6 | H6: =+'Scenario 0'!H6 | I6: =+'Scenario 0'!I6 | J6: =+'Scenario 0'!J6 | K6: =+'Scenario 0'!K6 | L6: =+'Scenario 0'!L6 | ... O6: =+'Scenario 0'!O6
C7: Gross Potential Income | E7: =+'Scenario 0'!$E$7 | F7: =+'Unit Mix'!U26 | G7: =+'Unit Mix'!U49 | H7: =+'Unit Mix'!U72 | I7: =+'Unit Mix'!U95 | J7: =+'Unit Mix'!U118 | K7: =+'Unit Mix'!U141 | L7: =+'Unit Mix'!U164 | M7: =+'Unit Mix'!U187 | N7: =+'Unit Mix'!U210 | O7: =+'Unit Mix'!U233
C8: Vacancy Factor | D8: =+Dashboard!$P$10 | E8: =+'Scenario 0'!$E$8 | F8: =+F7*$D$8 | G8: =+G7*$D$8 | H8: =+H7*$D$8 | I8: =+I7*$D$8 | J8: =+J7*$D$8 | K8: =+K7*$D$8 | L8: =+L7*$D$8 | M8: =+M7*$D$8 | ... O8: =+O7*$D$8
C9: Net Rental Income | E9: =+E7-E8 | F9: =+F7-F8 | G9: =+G7-G8 | H9: =+H7-H8 | I9: =+I7-I8 | J9: =+J7-J8 | K9: =+K7-K8 | L9: =+L7-L8 | ... O9: =+O7-O8
C11: Laundry and Other Income | D11: =+Dashboard!$P$14 | E11: =+'Scenario 0'!$E$11 | F11: =+Dashboard!$O$14 | G11: =+F11*(1+$D11) | H11: =+G11*(1+$D11) | I11: =+H11*(1+$D11) | J11: =+I11*(1+$D11) | K11: =+J11*(1+$D11) | L11: =+K11*(1+$D11) | M11: =+L11*(1+$D11) | N11: =+M11*(1+$D11) | O11: =+N11*(1+$D11)
C12: Total Gross Income | E12: =+SUM(E9:E11) | F12: =+SUM(F9:F11) | G12: =+SUM(G9:G11) | H12: =+SUM(H9:H11) | I12: =+SUM(I9:I11) | J12: =+SUM(J9:J11) | K12: =+SUM(K9:K11) | L12: =+SUM(L9:L11) | ... O12: =+SUM(O9:O11)
C13: Gross Income Growth | E13: -- | F13: =+F12/E12-1 | G13: =+G12/F12-1 | H13: =+H12/G12-1 | I13: =+I12/H12-1 | J13: =+J12/I12-1 | K13: =+K12/J12-1 | L13: =+L12/K12-1 | M13: =+M12/L12-1 | ... O13: =+O12/N12-1
C15: Opertating Expenses
A17: BAD
C18: Bad Debt | E18: =+'Scenario 0'!E18 | F18: =+'Scenario 0'!F18 | G18: =+'Scenario 0'!G18 | H18: =+'Scenario 0'!H18 | I18: =+'Scenario 0'!I18 | J18: =+'Scenario 0'!J18 | K18: =+'Scenario 0'!K18 | L18: =+'Scenario 0'!L18 | ... O18: =+'Scenario 0'!O18
A20: RES
A21: COM
C22: Total Replacement Reserves | E22: =+'Scenario 0'!E22 | F22: =+'Scenario 0'!F22 | G22: =+'Scenario 0'!G22 | H22: =+'Scenario 0'!H22 | I22: =+'Scenario 0'!I22 | J22: =+'Scenario 0'!J22 | K22: =+'Scenario 0'!K22 | L22: =+'Scenario 0'!L22 | ... O22: =+'Scenario 0'!O22
A24: MAN
A25: ASS
A26: PAY
A27: MAIT
C28: Payroll | E28: =+'Scenario 0'!E29 | F28: =+'Scenario 0'!F29 | G28: =+'Scenario 0'!G29 | H28: =+'Scenario 0'!H29 | I28: =+'Scenario 0'!I29 | J28: =+'Scenario 0'!J29 | K28: =+'Scenario 0'!K29 | L28: =+'Scenario 0'!L29 | ... O28: =+'Scenario 0'!O29
A30: MGMT
A31: LEGAL
A32: OFF
A33: TRAVEL
A34: AUD
A35: ADV
A36: TRAIN
A37: BANK
A38: BOOK
A39: PAYSERV
A40: UNIT
A41: MISCAD
C42: Admin Expenses | E42: =+'Scenario 0'!E43 | F42: =+'Scenario 0'!F43 | G42: =+'Scenario 0'!G43 | H42: =+'Scenario 0'!H43 | I42: =+'Scenario 0'!I43 | J42: =+'Scenario 0'!J43 | K42: =+'Scenario 0'!K43 | L42: =+'Scenario 0'!L43 | ... O42: =+'Scenario 0'!O43
A44: ELEC
A45: VAC
A46: WS
A47: GAS
A48: CABLE
A49: TRASH
C50: Utility Expenses | E50: =+'Scenario 0'!E51 | F50: =+'Scenario 0'!F51 | G50: =+'Scenario 0'!G51 | H50: =+'Scenario 0'!H51 | I50: =+'Scenario 0'!I51 | J50: =+'Scenario 0'!J51 | K50: =+'Scenario 0'!K51 | L50: =+'Scenario 0'!L51 | ... O50: =+'Scenario 0'!O51
A52: RM
A53: TURN
A54: SUPP
A55: APP
A56: HP
A57: CONC
C58: Operating and Maint. | E58: =+'Scenario 0'!E59 | F58: =+'Scenario 0'!F59 | G58: =+'Scenario 0'!G59 | H58: =+'Scenario 0'!H59 | I58: =+'Scenario 0'!I59 | J58: =+'Scenario 0'!J59 | K58: =+'Scenario 0'!K59 | L58: =+'Scenario 0'!L59 | ... O58: =+'Scenario 0'!O59
A60: LAND
A61: FIRE
A62: SEC
A63: PEST
A64: CON
A65: ELEV
A66: SNOW
A67: MISCOP
C68: Contract Expenses | E68: =+'Scenario 0'!E69 | F68: =+'Scenario 0'!F69 | G68: =+'Scenario 0'!G69 | H68: =+'Scenario 0'!H69 | I68: =+'Scenario 0'!I69 | J68: =+'Scenario 0'!J69 | K68: =+'Scenario 0'!K69 | L68: =+'Scenario 0'!L69 | ... O68: =+'Scenario 0'!O69
A70: RETAX
A71: INS
A72: WORKCOMP
A73: HEALTH
A74: PTAX
A75: MISCTAX
C76: Total Taxes and Insurance Expenses | E76: =+'Scenario 0'!E77 | F76: =+'Scenario 0'!F77 | G76: =+'Scenario 0'!G77 | H76: =+'Scenario 0'!H77 | I76: =+'Scenario 0'!I77 | J76: =+'Scenario 0'!J77 | K76: =+'Scenario 0'!K77 | L76: =+'Scenario 0'!L77 | ... O76: =+'Scenario 0'!O77
C78: Total Operating Expenses | E78: =+SUM(E18,E22,E28,E42,E50,E58,E68,E76,) | F78: =+SUM(F18,F22,F28,F42,F50,F58,F68,F76,) | G78: =+SUM(G18,G22,G28,G42,G50,G58,G68,G76,) | H78: =+SUM(H18,H22,H28,H42,H50,H58,H68,H76,) | I78: =+SUM(I18,I22,I28,I42,I50,I58,I68,I76,) | J78: =+SUM(J18,J22,J28,J42,J50,J58,J68,J76,) | K78: =+SUM(K18,K22,K28,K42,K50,K58,K68,K76,) | L78: =+SUM(L18,L22,L28,L42,L50,L58,L68,L76,) | ... O78: =+SUM(O18,O22,O28,O42,O50,O58,O68,O76,)
C80: Net Operating Income | E80: =+E12-E78 | F80: =+F12-F78 | G80: =+G12-G78 | H80: =+H12-H78 | I80: =+I12-I78 | J80: =+J12-J78 | K80: =+K12-K78 | L80: =+L12-L78 | ... O80: =+O12-O78
C81: NOI Margin | E81: =+IFERROR(E80/E12,"--") | F81: =+F80/F12 | G81: =+G80/G12 | H81: =+H80/H12 | I81: =+I80/I12 | J81: =+J80/J12 | K81: =+K80/K12 | L81: =+L80/L12 | M81: =+M80/M12 | ... O81: =+O80/O12
C83: Capital Expenditures
C84: Other CapEx
C85: Capital Reserve
C86: Total Capital Expenditures | E86: =+SUM(E84:E85) | F86: =+SUM(F84:F85) | G86: =+SUM(G84:G85) | H86: =+SUM(H84:H85) | I86: =+SUM(I84:I85) | J86: =+SUM(J84:J85) | K86: =+SUM(K84:K85) | L86: =+SUM(L84:L85) | ... O86: =+SUM(O84:O85)
C88: Cash Flow from Operations (Adj. NOI) | E88: =+E80-E86 | F88: =+F80-F86 | G88: =+G80-G86 | H88: =+H80-H86 | I88: =+I80-I86 | J88: =+J80-J86 | K88: =+K80-K86 | L88: =+L80-L86 | ... O88: =+O80-O86
C90: Debt Service | E90: -- | F90: =+Dashboard!$I$10*Dashboard!$E$50 | G90: =+F90 | H90: =+G90 | I90: =+H90 | J90: =+I90 | K90: =+J90 | L90: =+K90 | M90: =+L90 | N90: =+M90 | O90: =+N90
C91: Principal Repayment | E91: -- | F91: =IF(F$6<=Dashboard!$E$56,0,-PPMT(Dashboard!$E$50,'Scenario 1'!F3-'Scenario 1'!$E3,Dashboard!$E$55,Dashboard!$D$49)) | G91: =IF(G$6<=Dashboard!$E$56,0,-PPMT(Dashboard!$E$50,'Scenario 1'!G3-'Scenario 1'!$E3,Dashboard!$E$55,Dashboard!$D$49)) | H91: =IF(H$6<=Dashboard!$E$56,0,-PPMT(Dashboard!$E$50,'Scenario 1'!H3-'Scenario 1'!$E3,Dashboard!$E$55,Dashboard!$D$49)) | I91: =IF(I$6<=Dashboard!$E$56,0,-PPMT(Dashboard!$E$50,'Scenario 1'!I3-'Scenario 1'!$E3,Dashboard!$E$55,Dashboard!$D$49)) | J91: =IF(J$6<=Dashboard!$E$56,0,-PPMT(Dashboard!$E$50,'Scenario 1'!J3-'Scenario 1'!$E3,Dashboard!$E$55,Dashboard!$D$49)) | K91: =IF(K$6<=Dashboard!$E$56,0,-PPMT(Dashboard!$E$50,'Scenario 1'!K3-'Scenario 1'!$E3,Dashboard!$E$55,Dashboard!$D$49)) | L91: =IF(L$6<=Dashboard!$E$56,0,-PPMT(Dashboard!$E$50,'Scenario 1'!L3-'Scenario 1'!$E3,Dashboard!$E$55,Dashboard!$D$49)) | M91: =IF(M$6<=Dashboard!$E$56,0,-PPMT(Dashboard!$E$50,'Scenario 1'!M3-'Scenario 1'!$E3,Dashboard!$E$55,Dashboard!$D$49)) | ... O91: =IF(O$6<=Dashboard!$E$56,0,-PPMT(Dashboard!$E$50,'Scenario 1'!O3-'Scenario 1'!$E3,Dashboard!$E$55,Dashboard!$D$49))
C92: Cash Flow After Financing (CF to Equity Investors) | E92: -- | F92: =+F88-F90 | G92: =+G88-G90 | H92: =+H88-H90 | I92: =+I88-I90 | J92: =+J88-J90 | K92: =+K88-K90 | L92: =+L88-L90 | M92: =+M88-M90 | ... O92: =+O88-O90
C94: Ending Debt Balance | F94: =+Dashboard!$D$49-SUM('Scenario 1'!$F$91:F91) | G94: =+Dashboard!$D$49-SUM('Scenario 1'!$F$91:G91) | H94: =+Dashboard!$D$49-SUM('Scenario 1'!$F$91:H91) | I94: =+Dashboard!$D$49-SUM('Scenario 1'!$F$91:I91) | J94: =+Dashboard!$D$49-SUM('Scenario 1'!$F$91:J91) | K94: =+Dashboard!$D$49-SUM('Scenario 1'!$F$91:K91) | L94: =+Dashboard!$D$49-SUM('Scenario 1'!$F$91:L91) | M94: =+Dashboard!$D$49-SUM('Scenario 1'!$F$91:M91) | ... O94: =+Dashboard!$D$49-SUM('Scenario 1'!$F$91:O91)
C96: DSCR (NOI) | F96: =+IFERROR(F80/F90,"") | G96: =+IFERROR(G80/G90,"") | H96: =+IFERROR(H80/H90,"") | I96: =+IFERROR(I80/I90,"") | J96: =+IFERROR(J80/J90,"") | K96: =+IFERROR(K80/K90,"") | L96: =+IFERROR(L80/L90,"") | M96: =+IFERROR(M80/M90,"") | ... O96: =+IFERROR(O80/O90,"")
C97: DSCR (CFO) | F97: =+IFERROR(F88/F90,"") | G97: =+IFERROR(G88/G90,"") | H97: =+IFERROR(H88/H90,"") | I97: =+IFERROR(I88/I90,"") | J97: =+IFERROR(J88/J90,"") | K97: =+IFERROR(K88/K90,"") | L97: =+IFERROR(L88/L90,"") | M97: =+IFERROR(M88/M90,"") | ... O97: =+IFERROR(O88/O90,"")
C98: Debt Yield (CFO) | F98: =+F88/Dashboard!$I$10 | G98: =+G88/Dashboard!$I$10 | H98: =+H88/Dashboard!$I$10 | I98: =+I88/Dashboard!$I$10 | J98: =+J88/Dashboard!$I$10 | K98: =+K88/Dashboard!$I$10 | L98: =+L88/Dashboard!$I$10 | M98: =+M88/Dashboard!$I$10 | ... O98: =+O88/Dashboard!$I$10
C99: Break-Even Ratio | F99: =+SUM(F96,F78)/F12 | G99: =+SUM(G96,G78)/G12 | H99: =+SUM(H96,H78)/H12 | I99: =+SUM(I96,I78)/I12 | J99: =+SUM(J96,J78)/J12 | K99: =+SUM(K96,K78)/K12 | L99: =+SUM(L96,L78)/L12 | M99: =+SUM(M96,M78)/M12 | ... O99: =+SUM(O96,O78)/O12
C101: Cap Rate (Purchase Price) | F101: =+F80/Dashboard!$E$32 | G101: =+G80/Dashboard!$E$32 | H101: =+H80/Dashboard!$E$32 | I101: =+I80/Dashboard!$E$32 | J101: =+J80/Dashboard!$E$32 | K101: =+K80/Dashboard!$E$32 | L101: =+L80/Dashboard!$E$32 | M101: =+M80/Dashboard!$E$32 | ... O101: =+O80/Dashboard!$E$32
C102: Operating Cash Flow Before Taxes | F102: =+F80-F90-F91 | G102: =+G80-G90-G91 | H102: =+H80-H90-H91 | I102: =+I80-I90-I91 | J102: =+J80-J90-J91 | K102: =+K80-K90-K91 | L102: =+L80-L90-L91 | M102: =+M80-M90-M91 | ... O102: =+O80-O90-O91
C103: Cash on Cash Return | F103: =+F102/Dashboard!$I$11 | G103: =+G102/Dashboard!$I$11 | H103: =+H102/Dashboard!$I$11 | I103: =+I102/Dashboard!$I$11 | J103: =+J102/Dashboard!$I$11 | K103: =+K102/Dashboard!$I$11 | L103: =+L102/Dashboard!$I$11 | M103: =+M102/Dashboard!$I$11 | ... O103: =+O102/Dashboard!$I$11
C104: General Partner Cash Return | D104: =+Dashboard!J58 | F104: =+F102*$D$104 | G104: =+G102*$D$104 | H104: =+H102*$D$104 | I104: =+I102*$D$104 | J104: =+J102*$D$104 | K104: =+K102*$D$104 | L104: =+L102*$D$104 | M104: =+M102*$D$104 | ... O104: =+O102*$D$104
C105: Total Limited Partner Cash Return | D105: =+Dashboard!J59 | F105: =+F102*$D$105 | G105: =+G102*$D$105 | H105: =+H102*$D$105 | I105: =+I102*$D$105 | J105: =+J102*$D$105 | K105: =+K102*$D$105 | L105: =+L102*$D$105 | M105: =+M102*$D$105 | ... O105: =+O102*$D$105
C106: Cash on Cash LP Return | F106: =+F105/Dashboard!$I$11 | G106: =+G105/Dashboard!$I$11 | H106: =+H105/Dashboard!$I$11 | I106: =+I105/Dashboard!$I$11 | J106: =+J105/Dashboard!$I$11 | K106: =+K105/Dashboard!$I$11 | L106: =+L105/Dashboard!$I$11 | M106: =+M105/Dashboard!$I$11 | ... O106: =+O105/Dashboard!$I$11
C108: Return Metrics
C110: 5 Year Hold IRR | E110: =+'Scenario 0'!E111 | F110: =+'Scenario 0'!F111 | G110: =+'Scenario 0'!G111 | H110: =+'Scenario 0'!H111 | I110: =+'Scenario 0'!I111 | J110: =+'Scenario 0'!J111
C112: Exit Cap Rate Assumption | D112: =+Dashboard!$J$54
C114: Project Cash Flows (Unleveraged IRR):
C115: (+) Proceeds from Sale of Property: | F115: 0 | G115: 0 | H115: 0 | I115: 0 | J115: =+J$80/D$112
C116: (-) Selling Costs: | D116: =+Dashboard!$J$55 | F116: 0 | G116: 0 | H116: 0 | I116: 0 | J116: =-J$115*D$116
C117: (+) Adjusted NOI (Cash Flows to All Investors): | F117: =+F$88 | G117: =+G$88 | H117: =+H$88 | I117: =+I$88 | J117: =+J$88
C118: (-) Property Acquisition Price: | E118: =-Dashboard!$E$32 | F118: 0 | G118: 0 | H118: 0 | I118: 0 | J118: 0
C119: Total Project Cash Flows (Unleveraged IRR): | E119: =SUM(E115:E118) | F119: =SUM(F115:F118) | G119: =SUM(G115:G118) | H119: =SUM(H115:H118) | I119: =SUM(I115:I118) | J119: =SUM(J115:J118)
F120: =+F119-F115 | G120: =+G119-G115 | H120: =+H119-H115 | I120: =+I119-I115 | J120: =+J119-J115
C122: Unlevered IRR: | E122: =+IRR(E119:J119)
C123: Unlevered Cash-on-Cash Multiple: | E123: =+SUM(F115:J117)/-SUM(E118:J118)
C125: Cash Flow to Equity Investors (Leveraged IRR):
C126: (+) Proceeds from Sale of Property: | F126: 0 | G126: 0 | H126: 0 | I126: 0 | J126: =+J$80/D$112
...

Sheet Scenario 2
C1: Underwriting Model Scenario 2
D3: Year | E3: =+'Scenario 0'!E3 | F3: =+'Scenario 0'!F3 | G3: =+'Scenario 0'!G3 | H3: =+'Scenario 0'!H3 | I3: =+'Scenario 0'!I3 | J3: =+'Scenario 0'!J3 | K3: =+'Scenario 0'!K3 | L3: =+'Scenario 0'!L3 | ... O3: =+'Scenario 0'!O3
C4: ='Unit Mix'!$W$3
C6: Income Statement | E6: =+'Scenario 0'!E6 | F6: =+'Scenario 0'!F6 | G6: =+'Scenario 0'!G6 | H6: =+'Scenario 0'!H6 | I6: =+'Scenario 0'!I6 | J6: =+'Scenario 0'!J6 | K6: =+'Scenario 0'!K6 | L6: =+'Scenario 0'!L6 | ... O6: =+'Scenario 0'!O6
C7: Gross Potential Income | E7: =+'Scenario 0'!$E$7 | F7: =+'Unit Mix'!AB26 | G7: =+'Unit Mix'!AB49 | H7: =+'Unit Mix'!AB72 | I7: =+'Unit Mix'!AB95 | J7: =+'Unit Mix'!AB118 | K7: =+'Unit Mix'!AB141 | L7: =+'Unit Mix'!AB164 | M7: =+'Unit Mix'!AB187 | N7: =+'Unit Mix'!AB210 | O7: =+'Unit Mix'!AB233
C8: Vacancy Factor | D8: =+Dashboard!$P$10 | E8: =+'Scenario 0'!$E$8 | F8: =+F7*$D$8 | G8: =+G7*$D$8 | H8: =+H7*$D$8 | I8: =+I7*$D$8 | J8: =+J7*$D$8 | K8: =+K7*$D$8 | L8: =+L7*$D$8 | M8: =+M7*$D$8 | ... O8: =+O7*$D$8
C9: Net Rental Income | E9: =+E7-E8 | F9: =+F7-F8 | G9: =+G7-G8 | H9: =+H7-H8 | I9: =+I7-I8 | J9: =+J7-J8 | K9: =+K7-K8 | L9: =+L7-L8 | ... O9: =+O7-O8
C11: Laundry and Other Income | D11: =+Dashboard!$P$14 | E11: =+'Scenario 0'!$E$11 | F11: =+Dashboard!$O$14 | G11: =+F11*(1+$D11) | H11: =+G11*(1+$D11) | I11: =+H11*(1+$D11) | J11: =+I11*(1+$D11) | K11: =+J11*(1+$D11) | L11: =+K11*(1+$D11) | M11: =+L11*(1+$D11) | N11: =+M11*(1+$D11) | O11: =+N11*(1+$D11)
C12: Total Gross Income | E12: =+SUM(E9:E11) | F12: =+SUM(F9:F11) | G12: =+SUM(G9:G11) | H12: =+SUM(H9:H11) | I12: =+SUM(I9:I11) | J12: =+SUM(J9:J11) | K12: =+SUM(K9:K11) | L12: =+SUM(L9:L11) | ... O12: =+SUM(O9:O11)
C13: Gross Income Growth | E13: -- | F13: =+F12/E12-1 | G13: =+G12/F12-1 | H13: =+H12/G12-1 | I13: =+I12/H12-1 | J13: =+J12/I12-1 | K13: =+K12/J12-1 | L13: =+L12/K12-1 | M13: =+M12/L12-1 | ... O13: =+O12/N12-1
C15: Opertating Expenses
A17: BAD
C18: Bad Debt | E18: =+'Scenario 0'!E18 | F18: =+'Scenario 0'!F18 | G18: =+'Scenario 0'!G18 | H18: =+'Scenario 0'!H18 | I18: =+'Scenario 0'!I18 | J18: =+'Scenario 0'!J18 | K18: =+'Scenario 0'!K18 | L18: =+'Scenario 0'!L18 | ... O18: =+'Scenario 0'!O18
A20: RES
A21: COM
C22: Total Replacement Reserves | E22: =+'Scenario 0'!E22 | F22: =+'Scenario 0'!F22 | G22: =+'Scenario 0'!G22 | H22: =+'Scenario 0'!H22 | I22: =+'Scenario 0'!I22 | J22: =+'Scenario 0'!J22 | K22: =+'Scenario 0'!K22 | L22: =+'Scenario 0'!L22 | ... O22: =+'Scenario 0'!O22
A24: MAN
A25: ASS
A26: PAY
A27: MAIT
C28: Payroll | E28: =+'Scenario 0'!E29 | F28: =+'Scenario 0'!F29 | G28: =+'Scenario 0'!G29 | H28: =+'Scenario 0'!H29 | I28: =+'Scenario 0'!I29 | J28: =+'Scenario 0'!J29 | K28: =+'Scenario 0'!K29 | L28: =+'Scenario 0'!L29 | ... O28: =+'Scenario 0'!O29
A30: MGMT
A31: LEGAL
A32: OFF
A33: TRAVEL
A34: AUD
A35: ADV
A36: TRAIN
A37: BANK
A38: BOOK
A39: PAYSERV
A40: UNIT
A41: MISCAD
C42: Admin Expenses | E42: =+'Scenario 0'!E43 | F42: =+'Scenario 0'!F43 | G42: =+'Scenario 0'!G43 | H42: =+'Scenario 0'!H43 | I42: =+'Scenario 0'!I43 | J42: =+'Scenario 0'!J43 | K42: =+'Scenario 0'!K43 | L42: =+'Scenario 0'!L43 | ... O42: =+'Scenario 0'!O43
A44: ELEC
A45: VAC
A46: WS
A47: GAS
A48: CABLE
A49: TRASH
C50: Utility Expenses | E50: =+'Scenario 0'!E51 | F50: =+'Scenario 0'!F51 | G50: =+'Scenario 0'!G51 | H50: =+'Scenario 0'!H51 | I50: =+'Scenario 0'!I51 | J50: =+'Scenario 0'!J51 | K50: =+'Scenario 0'!K51 | L50: =+'Scenario 0'!L51 | ... O50: =+'Scenario 0'!O51
A52: RM
A53: TURN
A54: SUPP
A55: APP
A56: HP
A57: CONC
C58: Operating and Maint. | E58: =+'Scenario 0'!E59 | F58: =+'Scenario 0'!F59 | G58: =+'Scenario 0'!G59 | H58: =+'Scenario 0'!H59 | I58: =+'Scenario 0'!I59 | J58: =+'Scenario 0'!J59 | K58: =+'Scenario 0'!K59 | L58: =+'Scenario 0'!L59 | ... O58: =+'Scenario 0'!O59
A60: LAND
A61: FIRE
A62: SEC
A63: PEST
A64: CON
A65: ELEV
A66: SNOW
A67: MISCOP
C68: Contract Expenses | E68: =+'Scenario 0'!E69 | F68: =+'Scenario 0'!F69 | G68: =+'Scenario 0'!G69 | H68: =+'Scenario 0'!H69 | I68: =+'Scenario 0'!I69 | J68: =+'Scenario 0'!J69 | K68: =+'Scenario 0'!K69 | L68: =+'Scenario 0'!L69 | ... O68: =+'Scenario 0'!O69
A70: RETAX
A71: INS
A72: WORKCOMP
A73: HEALTH
A74: PTAX
A75: MISCTAX
C76: Total Taxes and Insurance Expenses | E76: =+'Scenario 0'!E77 | F76: =+'Scenario 0'!F77 | G76: =+'Scenario 0'!G77 | H76: =+'Scenario 0'!H77 | I76: =+'Scenario 0'!I77 | J76: =+'Scenario 0'!J77 | K76: =+'Scenario 0'!K77 | L76: =+'Scenario 0'!L77 | ... O76: =+'Scenario 0'!O77
C78: Total Operating Expenses | E78: =+SUM(E18,E22,E28,E42,E50,E58,E68,E76,) | F78: =+SUM(F18,F22,F28,F42,F50,F58,F68,F76,) | G78: =+SUM(G18,G22,G28,G42,G50,G58,G68,G76,) | H78: =+SUM(H18,H22,H28,H42,H50,H58,H68,H76,) | I78: =+SUM(I18,I22,I28,I42,I50,I58,I68,I76,) | J78: =+SUM(J18,J22,J28,J42,J50,J58,J68,J76,) | K78: =+SUM(K18,K22,K28,K42,K50,K58,K68,K76,) | L78: =+SUM(L18,L22,L28,L42,L50,L58,L68,L76,) | ... O78: =+SUM(O18,O22,O28,O42,O50,O58,O68,O76,)
C80: Net Operating Income | E80: =+E12-E78 | F80: =+F12-F78 | G80: =+G12-G78 | H80: =+H12-H78 | I80: =+I12-I78 | J80: =+J12-J78 | K80: =+K12-K78 | L80: =+L12-L78 | ... O80: =+O12-O78
C81: NOI Margin | E81: =+IFERROR(E80/E12,"--") | F81: =+F80/F12 | G81: =+G80/G12 | H81: =+H80/H12 | I81: =+I80/I12 | J81: =+J80/J12 | K81: =+K80/K12 | L81: =+L80/L12 | M81: =+M80/M12 | ... O81: =+O80/O12
C83: Capital Expenditures
C84: Other CapEx
C85: Capital Reserve
C86: Total Capital Expenditures | E86: =+SUM(E84:E85) | F86: =+SUM(F84:F85) | G86: =+SUM(G84:G85) | H86: =+SUM(H84:H85) | I86: =+SUM(I84:I85) | J86: =+SUM(J84:J85) | K86: =+SUM(K84:K85) | L86: =+SUM(L84:L85) | ... O86: =+SUM(O84:O85)
C88: Cash Flow from Operations (Adj. NOI) | E88: =+E80-E86 | F88: =+F80-F86 | G88: =+G80-G86 | H88: =+H80-H86 | I88: =+I80-I86 | J88: =+J80-J86 | K88: =+K80-K86 | L88: =+L80-L86 | ... O88: =+O80-O86
C90: Debt Service | E90: -- | F90: =+Dashboard!$I$10*Dashboard!$E$50 | G90: =+F90 | H90: =+G90 | I90: =+H90 | J90: =+I90 | K90: =+J90 | L90: =+K90 | M90: =+L90 | N90: =+M90 | O90: =+N90
C91: Principal Repayment | E91: -- | F91: =IF(F$6<=Dashboard!$E$56,0,-PPMT(Dashboard!$E$50,'Scenario 2'!F3-'Scenario 2'!$E3,Dashboard!$E$55,Dashboard!$D$49)) | G91: =IF(G$6<=Dashboard!$E$56,0,-PPMT(Dashboard!$E$50,'Scenario 2'!G3-'Scenario 2'!$E3,Dashboard!$E$55,Dashboard!$D$49)) | H91: =IF(H$6<=Dashboard!$E$56,0,-PPMT(Dashboard!$E$50,'Scenario 2'!H3-'Scenario 2'!$E3,Dashboard!$E$55,Dashboard!$D$49)) | I91: =IF(I$6<=Dashboard!$E$56,0,-PPMT(Dashboard!$E$50,'Scenario 2'!I3-'Scenario 2'!$E3,Dashboard!$E$55,Dashboard!$D$49)) | J91: =IF(J$6<=Dashboard!$E$56,0,-PPMT(Dashboard!$E$50,'Scenario 2'!J3-'Scenario 2'!$E3,Dashboard!$E$55,Dashboard!$D$49)) | K91: =IF(K$6<=Dashboard!$E$56,0,-PPMT(Dashboard!$E$50,'Scenario 2'!K3-'Scenario 2'!$E3,Dashboard!$E$55,Dashboard!$D$49)) | L91: =IF(L$6<=Dashboard!$E$56,0,-PPMT(Dashboard!$E$50,'Scenario 2'!L3-'Scenario 2'!$E3,Dashboard!$E$55,Dashboard!$D$49)) | M91: =IF(M$6<=Dashboard!$E$56,0,-PPMT(Dashboard!$E$50,'Scenario 2'!M3-'Scenario 2'!$E3,Dashboard!$E$55,Dashboard!$D$49)) | ... O91: =IF(O$6<=Dashboard!$E$56,0,-PPMT(Dashboard!$E$50,'Scenario 2'!O3-'Scenario 2'!$E3,Dashboard!$E$55,Dashboard!$D$49))
C92: Cash Flow After Financing (CF to Equity Investors) | E92: -- | F92: =+F88-F90 | G92: =+G88-G90 | H92: =+H88-H90 | I92: =+I88-I90 | J92: =+J88-J90 | K92: =+K88-K90 | L92: =+L88-L90 | M92: =+M88-M90 | ... O92: =+O88-O90
C94: Ending Debt Balance | F94: =+Dashboard!$D$49-SUM('Scenario 2'!$F$91:F91) | G94: =+Dashboard!$D$49-SUM('Scenario 2'!$F$91:G91) | H94: =+Dashboard!$D$49-SUM('Scenario 2'!$F$91:H91) | I94: =+Dashboard!$D$49-SUM('Scenario 2'!$F$91:I91) | J94: =+Dashboard!$D$49-SUM('Scenario 2'!$F$91:J91) | K94: =+Dashboard!$D$49-SUM('Scenario 2'!$F$91:K91) | L94: =+Dashboard!$D$49-SUM('Scenario 2'!$F$91:L91) | M94: =+Dashboard!$D$49-SUM('Scenario 2'!$F$91:M91) | ... O94: =+Dashboard!$D$49-SUM('Scenario 2'!$F$91:O91)
C96: DSCR (NOI) | F96: =+IFERROR(F80/F90,"") | G96: =+IFERROR(G80/G90,"") | H96: =+IFERROR(H80/H90,"") | I96: =+IFERROR(I80/I90,"") | J96: =+IFERROR(J80/J90,"") | K96: =+IFERROR(K80/K90,"") | L96: =+IFERROR(L80/L90,"") | M96: =+IFERROR(M80/M90,"") | ... O96: =+IFERROR(O80/O90,"")
C97: DSCR (CFO) | F97: =+IFERROR(F88/F90,"") | G97: =+IFERROR(G88/G90,"") | H97: =+IFERROR(H88/H90,"") | I97: =+IFERROR(I88/I90,"") | J97: =+IFERROR(J88/J90,"") | K97: =+IFERROR(K88/K90,"") | L97: =+IFERROR(L88/L90,"") | M97: =+IFERROR(M88/M90,"") | ... O97: =+IFERROR(O88/O90,"")
C98: Debt Yield (CFO) | F98: =+F88/Dashboard!$I$10 | G98: =+G88/Dashboard!$I$10 | H98: =+H88/Dashboard!$I$10 | I98: =+I88/Dashboard!$I$10 | J98: =+J88/Dashboard!$I$10 | K98: =+K88/Dashboard!$I$10 | L98: =+L88/Dashboard!$I$10 | M98: =+M88/Dashboard!$I$10 | ... O98: =+O88/Dashboard!$I$10
C99: Break-Even Ratio | F99: =+SUM(F96,F78)/F12 | G99: =+SUM(G96,G78)/G12 | H99: =+SUM(H96,H78)/H12 | I99: =+SUM(I96,I78)/I12 | J99: =+SUM(J96,J78)/J12 | K99: =+SUM(K96,K78)/K12 | L99: =+SUM(L96,L78)/L12 | M99: =+SUM(M96,M78)/M12 | ... O99: =+SUM(O96,O78)/O12
C101: Cap Rate (Purchase Price) | F101: =+F80/Dashboard!$E$32 | G101: =+G80/Dashboard!$E$32 | H101: =+H80/Dashboard!$E$32 | I101: =+I80/Dashboard!$E$32 | J101: =+J80/Dashboard!$E$32 | K101: =+K80/Dashboard!$E$32 | L101: =+L80/Dashboard!$E$32 | M101: =+M80/Dashboard!$E$32 | ... O101: =+O80/Dashboard!$E$32
C102: Operating Cash Flow Before Taxes | F102: =+F80-F90-F91 | G102: =+G80-G90-G91 | H102: =+H80-H90-H91 | I102: =+I80-I90-I91 | J102: =+J80-J90-J91 | K102: =+K80-K90-K91 | L102: =+L80-L90-L91 | M102: =+M80-M90-M91 | ... O102: =+O80-O90-O91
C103: Cash on Cash Return | F103: =+F102/Dashboard!$I$11 | G103: =+G102/Dashboard!$I$11 | H103: =+H102/Dashboard!$I$11 | I103: =+I102/Dashboard!$I$11 | J103: =+J102/Dashboard!$I$11 | K103: =+K102/Dashboard!$I$11 | L103: =+L102/Dashboard!$I$11 | M103: =+M102/Dashboard!$I$11 | ... O103: =+O102/Dashboard!$I$11
C104: General Partner Cash Return | D104: =+Dashboard!J58 | F104: =+F102*$D$104 | G104: =+G102*$D$104 | H104: =+H102*$D$104 | I104: =+I102*$D$104 | J104: =+J102*$D$104 | K104: =+K102*$D$104 | L104: =+L102*$D$104 | M104: =+M102*$D$104 | ... O104: =+O102*$D$104
C105: Total Limited Partner Cash Return | D105: =+Dashboard!J59 | F105: =+F102*$D$105 | G105: =+G102*$D$105 | H105: =+H102*$D$105 | I105: =+I102*$D$105 | J105: =+J102*$D$105 | K105: =+K102*$D$105 | L105: =+L102*$D$105 | M105: =+M102*$D$105 | ... O105: =+O102*$D$105
C106: Cash on Cash LP Return | F106: =+F105/Dashboard!$I$11 | G106: =+G105/Dashboard!$I$11 | H106: =+H105/Dashboard!$I$11 | I106: =+I105/Dashboard!$I$11 | J106: =+J105/Dashboard!$I$11 | K106: =+K105/Dashboard!$I$11 | L106: =+L105/Dashboard!$I$11 | M106: =+M105/Dashboard!$I$11 | ... O106: =+O105/Dashboard!$I$11
C108: Return Metrics
C110: 5 Year Hold IRR | E110: =+'Scenario 0'!E111 | F110: =+'Scenario 0'!F111 | G110: =+'Scenario 0'!G111 | H110: =+'Scenario 0'!H111 | I110: =+'Scenario 0'!I111 | J110: =+'Scenario 0'!J111
C112: Exit Cap Rate Assumption | D112: =+Dashboard!$J$54
C114: Project Cash Flows (Unleveraged IRR):
C115: (+) Proceeds from Sale of Property: | F115: 0 | G115: 0 | H115: 0 | I115: 0 | J115: =+J$80/D$112
C116: (-) Selling Costs: | D116: =+Dashboard!$J$55 | F116: 0 | G116: 0 | H116: 0 | I116: 0 | J116: =-J$115*D$116
C117: (+) Adjusted NOI (Cash Flows to All Investors): | F117: =+F$88 | G117: =+G$88 | H117: =+H$88 | I117: =+I$88 | J117: =+J$88
C118: (-) Property Acquisition Price: | E118: =-Dashboard!$E$32 | F118: 0 | G118: 0 | H118: 0 | I118: 0 | J118: 0
C119: Total Project Cash Flows (Unleveraged IRR): | E119: =SUM(E115:E118) | F119: =SUM(F115:F118) | G119: =SUM(G115:G118) | H119: =SUM(H115:H118) | I119: =SUM(I115:I118) | J119: =SUM(J115:J118)
F120: =+F119-F115 | G120: =+G119-G115 | H120: =+H119-H115 | I120: =+I119-I115 | J120: =+J119-J115
C122: Unlevered IRR: | E122: =+IRR(E119:J119)
C123: Unlevered Cash-on-Cash Multiple: | E123: =+SUM(F115:J117)/-SUM(E118:J118)
C125: Cash Flow to Equity Investors (Leveraged IRR):
C126: (+) Proceeds from Sale of Property: | F126: 0 | G126: 0 | H126: 0 | I126: 0 | J126: =+J$80/D$112
...

Sheet Scenario 3
C1: Underwriting Model Scenario 3
D3: Year | E3: =+'Scenario 0'!E3 | F3: =+'Scenario 0'!F3 | G3: =+'Scenario 0'!G3 | H3: =+'Scenario 0'!H3 | I3: =+'Scenario 0'!I3 | J3: =+'Scenario 0'!J3 | K3: =+'Scenario 0'!K3 | L3: =+'Scenario 0'!L3 | ... O3: =+'Scenario 0'!O3
C4: =+'Unit Mix'!AD3
C6: Income Statement | E6: =+'Scenario 0'!E6 | F6: =+'Scenario 0'!F6 | G6: =+'Scenario 0'!G6 | H6: =+'Scenario 0'!H6 | I6: =+'Scenario 0'!I6 | J6: =+'Scenario 0'!J6 | K6: =+'Scenario 0'!K6 | L6: =+'Scenario 0'!L6 | ... O6: =+'Scenario 0'!O6
C7: Gross Potential Income | E7: =+'Scenario 0'!$E$7 | F7: =+'Unit Mix'!AI26 | G7: =+'Unit Mix'!AI49 | H7: =+'Unit Mix'!AI72 | I7: =+'Unit Mix'!AI95 | J7: =+'Unit Mix'!AI118 | K7: =+'Unit Mix'!AI141 | L7: =+'Unit Mix'!AI164 | M7: =+'Unit Mix'!AI187 | N7: =+'Unit Mix'!AI210 | O7: =+'Unit Mix'!AI233
C8: Vacancy Factor | D8: =+Dashboard!$P$10 | E8: =+'Scenario 0'!$E$8 | F8: =+F7*$D$8 | G8: =+G7*$D$8 | H8: =+H7*$D$8 | I8: =+I7*$D$8 | J8: =+J7*$D$8 | K8: =+K7*$D$8 | L8: =+L7*$D$8 | M8: =+M7*$D$8 | ... O8: =+O7*$D$8
C9: Net Rental Income | E9: =+E7-E8 | F9: =+F7-F8 | G9: =+G7-G8 | H9: =+H7-H8 | I9: =+I7-I8 | J9: =+J7-J8 | K9: =+K7-K8 | L9: =+L7-L8 | ... O9: =+O7-O8
C11: Laundry and Other Income | D11: =+Dashboard!$P$14 | E11: =+'Scenario 0'!$E$11 | F11: =+Dashboard!$O$14 | G11: =+F11*(1+$D11) | H11: =+G11*(1+$D11) | I11: =+H11*(1+$D11) | J11: =+I11*(1+$D11) | K11: =+J11*(1+$D11) | L11: =+K11*(1+$D11) | M11: =+L11*(1+$D11) | N11: =+M11*(1+$D11) | O11: =+N11*(1+$D11)
C12: Total Gross Income | E12: =+SUM(E9:E11) | F12: =+SUM(F9:F11) | G12: =+SUM(G9:G11) | H12: =+SUM(H9:H11) | I12: =+SUM(I9:I11) | J12: =+SUM(J9:J11) | K12: =+SUM(K9:K11) | L12: =+SUM(L9:L11) | ... O12: =+SUM(O9:O11)
C13: Gross Income Growth | E13: -- | F13: =+F12/E12-1 | G13: =+G12/F12-1 | H13: =+H12/G12-1 | I13: =+I12/H12-1 | J13: =+J12/I12-1 | K13: =+K12/J12-1 | L13: =+L12/K12-1 | M13: =+M12/L12-1 | ... O13: =+O12/N12-1
C15: Opertating Expenses
A17: BAD
C18: Bad Debt | E18: =+'Scenario 0'!E18 | F18: =+'Scenario 0'!F18 | G18: =+'Scenario 0'!G18 | H18: =+'Scenario 0'!H18 | I18: =+'Scenario 0'!I18 | J18: =+'Scenario 0'!J18 | K18: =+'Scenario 0'!K18 | L18: =+'Scenario 0'!L18 | ... O18: =+'Scenario 0'!O18
A20: RES
A21: COM
C22: Total Replacement Reserves | E22: =+'Scenario 0'!E22 | F22: =+'Scenario 0'!F22 | G22: =+'Scenario 0'!G22 | H22: =+'Scenario 0'!H22 | I22: =+'Scenario 0'!I22 | J22: =+'Scenario 0'!J22 | K22: =+'Scenario 0'!K22 | L22: =+'Scenario 0'!L22 | ... O22: =+'Scenario 0'!O22
A24: MAN
A25: ASS
A26: PAY
A27: MAIT
C28: Payroll | E28: =+'Scenario 0'!E29 | F28: =+'Scenario 0'!F29 | G28: =+'Scenario 0'!G29 | H28: =+'Scenario 0'!H29 | I28: =+'Scenario 0'!I29 | J28: =+'Scenario 0'!J29 | K28: =+'Scenario 0'!K29 | L28: =+'Scenario 0'!L29 | ... O28: =+'Scenario 0'!O29
A30: MGMT
A31: LEGAL
A32: OFF
A33: TRAVEL
A34: AUD
A35: ADV
A36: TRAIN
A37: BANK
A38: BOOK
A39: PAYSERV
A40: UNIT
A41: MISCAD
C42: Admin Expenses | E42: =+'Scenario 0'!E43 | F42: =+'Scenario 0'!F43 | G42: =+'Scenario 0'!G43 | H42: =+'Scenario 0'!H43 | I42: =+'Scenario 0'!I43 | J42: =+'Scenario 0'!J43 | K42: =+'Scenario 0'!K43 | L42: =+'Scenario 0'!L43 | ... O42: =+'Scenario 0'!O43
A44: ELEC
A45: VAC
A46: WS
A47: GAS
A48: CABLE
A49: TRASH
C50: Utility Expenses | E50: =+'Scenario 0'!E51 | F50: =+'Scenario 0'!F51 | G50: =+'Scenario 0'!G51 | H50: =+'Scenario 0'!H51 | I50: =+'Scenario 0'!I51 | J50: =+'Scenario 0'!J51 | K50: =+'Scenario 0'!K51 | L50: =+'Scenario 0'!L51 | ... O50: =+'Scenario 0'!O51
A52: RM
A53: TURN
A54: SUPP
A55: APP
A56: HP
A57: CONC
C58: Operating and Maint. | E58: =+'Scenario 0'!E59 | F58: =+'Scenario 0'!F59 | G58: =+'Scenario 0'!G59 | H58: =+'Scenario 0'!H59 | I58: =+'Scenario 0'!I59 | J58: =+'Scenario 0'!J59 | K58: =+'Scenario 0'!K59 | L58: =+'Scenario 0'!L59 | ... O58: =+'Scenario 0'!O59
A60: LAND
A61: FIRE
A62: SEC
A63: PEST
A64: CON
A65: ELEV
A66: SNOW
A67: MISCOP
C68: Contract Expenses | E68: =+'Scenario 0'!E69 | F68: =+'Scenario 0'!F69 | G68: =+'Scenario 0'!G69 | H68: =+'Scenario 0'!H69 | I68: =+'Scenario 0'!I69 | J68: =+'Scenario 0'!J69 | K68: =+'Scenario 0'!K69 | L68: =+'Scenario 0'!L69 | ... O68: =+'Scenario 0'!O69
A70: RETAX
A71: INS
A72: WORKCOMP
A73: HEALTH
A74: PTAX
A75: MISCTAX
C76: Total Taxes and Insurance Expenses | E76: =+'Scenario 0'!E77 | F76: =+'Scenario 0'!F77 | G76: =+'Scenario 0'!G77 | H76: =+'Scenario 0'!H77 | I76: =+'Scenario 0'!I77 | J76: =+'Scenario 0'!J77 | K76: =+'Scenario 0'!K77 | L76: =+'Scenario 0'!L77 | ... O76: =+'Scenario 0'!O77
C78: Total Operating Expenses | E78: =+SUM(E18,E22,E28,E42,E50,E58,E68,E76,) | F78: =+SUM(F18,F22,F28,F42,F50,F58,F68,F76,) | G78: =+SUM(G18,G22,G28,G42,G50,G58,G68,G76,) | H78: =+SUM(H18,H22,H28,H42,H50,H58,H68,H76,) | I78: =+SUM(I18,I22,I28,I42,I50,I58,I68,I76,) | J78: =+SUM(J18,J22,J28,J42,J50,J58,J68,J76,) | K78: =+SUM(K18,K22,K28,K42,K50,K58,K68,K76,) | L78: =+SUM(L18,L22,L28,L42,L50,L58,L68,L76,) | ... O78: =+SUM(O18,O22,O28,O42,O50,O58,O68,O76,)
C80: Net Operating Income | E80: =+E12-E78 | F80: =+F12-F78 | G80: =+G12-G78 | H80: =+H12-H78 | I80: =+I12-I78 | J80: =+J12-J78 | K80: =+K12-K78 | L80: =+L12-L78 | ... O80: =+O12-O78
C81: NOI Margin | E81: =+IFERROR(E80/E12,"--") | F81: =+F80/F12 | G81: =+G80/G12 | H81: =+H80/H12 | I81: =+I80/I12 | J81: =+J80/J12 | K81: =+K80/K12 | L81: =+L80/L12 | M81: =+M80/M12 | ... O81: =+O80/O12
C83: Capital Expenditures
C84: Other CapEx
C85: Capital Reserve
C86: Total Capital Expenditures | E86: =+SUM(E84:E85) | F86: =+SUM(F84:F85) | G86: =+SUM(G84:G85) | H86: =+SUM(H84:H85) | I86: =+SUM(I84:I85) | J86: =+SUM(J84:J85) | K86: =+SUM(K84:K85) | L86: =+SUM(L84:L85) | ... O86: =+SUM(O84:O85)
C88: Cash Flow from Operations (Adj. NOI) | E88: =+E80-E86 | F88: =+F80-F86 | G88: =+G80-G86 | H88: =+H80-H86 | I88: =+I80-I86 | J88: =+J80-J86 | K88: =+K80-K86 | L88: =+L80-L86 | ... O88: =+O80-O86
C90: Debt Service | E90: -- | F90: =+Dashboard!$I$10*Dashboard!$E$50 | G90: =+F90 | H90: =+G90 | I90: =+H90 | J90: =+I90 | K90: =+J90 | L90: =+K90 | M90: =+L90 | N90: =+M90 | O90: =+N90
C91: Principal Repayment | E91: -- | F91: =IF(F$6<=Dashboard!$E$56,0,-PPMT(Dashboard!$E$50,'Scenario 3'!F3-'Scenario 3'!$E3,Dashboard!$E$55,Dashboard!$D$49)) | G91: =IF(G$6<=Dashboard!$E$56,0,-PPMT(Dashboard!$E$50,'Scenario 3'!G3-'Scenario 3'!$E3,Dashboard!$E$55,Dashboard!$D$49)) | H91: =IF(H$6<=Dashboard!$E$56,0,-PPMT(Dashboard!$E$50,'Scenario 3'!H3-'Scenario 3'!$E3,Dashboard!$E$55,Dashboard!$D$49)) | I91: =IF(I$6<=Dashboard!$E$56,0,-PPMT(Dashboard!$E$50,'Scenario 3'!I3-'Scenario 3'!$E3,Dashboard!$E$55,Dashboard!$D$49)) | J91: =IF(J$6<=Dashboard!$E$56,0,-PPMT(Dashboard!$E$50,'Scenario 3'!J3-'Scenario 3'!$E3,Dashboard!$E$55,Dashboard!$D$49)) | K91: =IF(K$6<=Dashboard!$E$56,0,-PPMT(Dashboard!$E$50,'Scenario 3'!K3-'Scenario 3'!$E3,Dashboard!$E$55,Dashboard!$D$49)) | L91: =IF(L$6<=Dashboard!$E$56,0,-PPMT(Dashboard!$E$50,'Scenario 3'!L3-'Scenario 3'!$E3,Dashboard!$E$55,Dashboard!$D$49)) | M91: =IF(M$6<=Dashboard!$E$56,0,-PPMT(Dashboard!$E$50,'Scenario 3'!M3-'Scenario 3'!$E3,Dashboard!$E$55,Dashboard!$D$49)) | ... O91: =IF(O$6<=Dashboard!$E$56,0,-PPMT(Dashboard!$E$50,'Scenario 3'!O3-'Scenario 3'!$E3,Dashboard!$E$55,Dashboard!$D$49))
C92: Cash Flow After Financing (CF to Equity Investors) | E92: -- | F92: =+F88-F90 | G92: =+G88-G90 | H92: =+H88-H90 | I92: =+I88-I90 | J92: =+J88-J90 | K92: =+K88-K90 | L92: =+L88-L90 | M92: =+M88-M90 | ... O92: =+O88-O90
C94: Ending Debt Balance | F94: =+Dashboard!$D$49-SUM('Scenario 3'!$F$91:F91) | G94: =+Dashboard!$D$49-SUM('Scenario 3'!$F$91:G91) | H94: =+Dashboard!$D$49-SUM('Scenario 3'!$F$91:H91) | I94: =+Dashboard!$D$49-SUM('Scenario 3'!$F$91:I91) | J94: =+Dashboard!$D$49-SUM('Scenario 3'!$F$91:J91) | K94: =+Dashboard!$D$49-SUM('Scenario 3'!$F$91:K91) | L94: =+Dashboard!$D$49-SUM('Scenario 3'!$F$91:L91) | M94: =+Dashboard!$D$49-SUM('Scenario 3'!$F$91:M91) | ... O94: =+Dashboard!$D$49-SUM('Scenario 3'!$F$91:O91)
C96: DSCR (NOI) | F96: =+IFERROR(F80/F90,"") | G96: =+IFERROR(G80/G90,"") | H96: =+IFERROR(H80/H90,"") | I96: =+IFERROR(I80/I90,"") | J96: =+IFERROR(J80/J90,"") | K96: =+IFERROR(K80/K90,"") | L96: =+IFERROR(L80/L90,"") | M96: =+IFERROR(M80/M90,"") | ... O96: =+IFERROR(O80/O90,"")
C97: DSCR (CFO) | F97: =+IFERROR(F88/F90,"") | G97: =+IFERROR(G88/G90,"") | H97: =+IFERROR(H88/H90,"") | I97: =+IFERROR(I88/I90,"") | J97: =+IFERROR(J88/J90,"") | K97: =+IFERROR(K88/K90,"") | L97: =+IFERROR(L88/L90,"") | M97: =+IFERROR(M88/M90,"") | ... O97: =+IFERROR(O88/O90,"")
C98: Debt Yield (CFO) | F98: =+F88/Dashboard!$I$10 | G98: =+G88/Dashboard!$I$10 | H98: =+H88/Dashboard!$I$10 | I98: =+I88/Dashboard!$I$10 | J98: =+J88/Dashboard!$I$10 | K98: =+K88/Dashboard!$I$10 | L98: =+L88/Dashboard!$I$10 | M98: =+M88/Dashboard!$I$10 | ... O98: =+O88/Dashboard!$I$10
C99: Break-Even Ratio | F99: =+SUM(F96,F78)/F12 | G99: =+SUM(G96,G78)/G12 | H99: =+SUM(H96,H78)/H12 | I99: =+SUM(I96,I78)/I12 | J99: =+SUM(J96,J78)/J12 | K99: =+SUM(K96,K78)/K12 | L99: =+SUM(L96,L78)/L12 | M99: =+SUM(M96,M78)/M12 | ... O99: =+SUM(O96,O78)/O12
C101: Cap Rate (Purchase Price) | F101: =+F80/Dashboard!$E$32 | G101: =+G80/Dashboard!$E$32 | H101: =+H80/Dashboard!$E$32 | I101: =+I80/Dashboard!$E$32 | J101: =+J80/Dashboard!$E$32 | K101: =+K80/Dashboard!$E$32 | L101: =+L80/Dashboard!$E$32 | M101: =+M80/Dashboard!$E$32 | ... O101: =+O80/Dashboard!$E$32
C102: Operating Cash Flow Before Taxes | F102: =+F80-F90-F91 | G102: =+G80-G90-G91 | H102: =+H80-H90-H91 | I102: =+I80-I90-I91 | J102: =+J80-J90-J91 | K102: =+K80-K90-K91 | L102: =+L80-L90-L91 | M102: =+M80-M90-M91 | ... O102: =+O80-O90-O91
C103: Cash on Cash Return | F103: =+F102/Dashboard!$I$11 | G103: =+G102/Dashboard!$I$11 | H103: =+H102/Dashboard!$I$11 | I103: =+I102/Dashboard!$I$11 | J103: =+J102/Dashboard!$I$11 | K103: =+K102/Dashboard!$I$11 | L103: =+L102/Dashboard!$I$11 | M103: =+M102/Dashboard!$I$11 | ... O103: =+O102/Dashboard!$I$11
C104: General Partner Cash Return | D104: =+Dashboard!J58 | F104: =+F102*$D$104 | G104: =+G102*$D$104 | H104: =+H102*$D$104 | I104: =+I102*$D$104 | J104: =+J102*$D$104 | K104: =+K102*$D$104 | L104: =+L102*$D$104 | M104: =+M102*$D$104 | ... O104: =+O102*$D$104
C105: Total Limited Partner Cash Return | D105: =+Dashboard!J59 | F105: =+F102*$D$105 | G105: =+G102*$D$105 | H105: =+H102*$D$105 | I105: =+I102*$D$105 | J105: =+J102*$D$105 | K105: =+K102*$D$105 | L105: =+L102*$D$105 | M105: =+M102*$D$105 | ... O105: =+O102*$D$105
C106: Cash on Cash LP Return | F106: =+F105/Dashboard!$I$11 | G106: =+G105/Dashboard!$I$11 | H106: =+H105/Dashboard!$I$11 | I106: =+I105/Dashboard!$I$11 | J106: =+J105/Dashboard!$I$11 | K106: =+K105/Dashboard!$I$11 | L106: =+L105/Dashboard!$I$11 | M106: =+M105/Dashboard!$I$11 | ... O106: =+O105/Dashboard!$I$11
C108: Return Metrics
C110: 5 Year Hold IRR | E110: =+'Scenario 0'!E111 | F110: =+'Scenario 0'!F111 | G110: =+'Scenario 0'!G111 | H110: =+'Scenario 0'!H111 | I110: =+'Scenario 0'!I111 | J110: =+'Scenario 0'!J111
C112: Exit Cap Rate Assumption | D112: =+Dashboard!$J$54
C114: Project Cash Flows (Unleveraged IRR):
C115: (+) Proceeds from Sale of Property: | F115: 0 | G115: 0 | H115: 0 | I115: 0 | J115: =+J$80/D$112
C116: (-) Selling Costs: | D116: =+Dashboard!$J$55 | F116: 0 | G116: 0 | H116: 0 | I116: 0 | J116: =-J$115*D$116
C117: (+) Adjusted NOI (Cash Flows to All Investors): | F117: =+F$88 | G117: =+G$88 | H117: =+H$88 | I117: =+I$88 | J117: =+J$88
C118: (-) Property Acquisition Price: | E118: =-Dashboard!$E$32 | F118: 0 | G118: 0 | H118: 0 | I118: 0 | J118: 0
C119: Total Project Cash Flows (Unleveraged IRR): | E119: =SUM(E115:E118) | F119: =SUM(F115:F118) | G119: =SUM(G115:G118) | H119: =SUM(H115:H118) | I119: =SUM(I115:I118) | J119: =SUM(J115:J118)
F120: =+F119-F115 | G120: =+G119-G115 | H120: =+H119-H115 | I120: =+I119-I115 | J120: =+J119-J115
C122: Unlevered IRR: | E122: =+IRR(E119:J119)
C123: Unlevered Cash-on-Cash Multiple: | E123: =+SUM(F115:J117)/-SUM(E118:J118)
C125: Cash Flow to Equity Investors (Leveraged IRR):
C126: (+) Proceeds from Sale of Property: | F126: 0 | G126: 0 | H126: 0 | I126: 0 | J126: =+J$80/D$112
...

Sheet Scenario 4
C1: Underwriting Model Scenario 4
D3: Year | E3: =+'Scenario 0'!E3 | F3: =+'Scenario 0'!F3 | G3: =+'Scenario 0'!G3 | H3: =+'Scenario 0'!H3 | I3: =+'Scenario 0'!I3 | J3: =+'Scenario 0'!J3 | K3: =+'Scenario 0'!K3 | L3: =+'Scenario 0'!L3 | ... O3: =+'Scenario 0'!O3
C4: =+'Unit Mix'!AK3
C6: Income Statement | E6: =+'Scenario 0'!E6 | F6: =+'Scenario 0'!F6 | G6: =+'Scenario 0'!G6 | H6: =+'Scenario 0'!H6 | I6: =+'Scenario 0'!I6 | J6: =+'Scenario 0'!J6 | K6: =+'Scenario 0'!K6 | L6: =+'Scenario 0'!L6 | ... O6: =+'Scenario 0'!O6
C7: Gross Potential Income | E7: =+'Scenario 0'!$E$7 | F7: =+'Unit Mix'!AP26 | G7: =+'Unit Mix'!AP49 | H7: =+'Unit Mix'!AP72 | I7: =+'Unit Mix'!AP95 | J7: =+'Unit Mix'!AP118 | K7: =+'Unit Mix'!AP141 | L7: =+'Unit Mix'!AP164 | M7: =+'Unit Mix'!AP187 | N7: =+'Unit Mix'!AP210 | O7: =+'Unit Mix'!AP233
C8: Vacancy Factor | D8: =+Dashboard!$P$10 | E8: =+'Scenario 0'!$E$8 | F8: =+F7*$D$8 | G8: =+G7*$D$8 | H8: =+H7*$D$8 | I8: =+I7*$D$8 | J8: =+J7*$D$8 | K8: =+K7*$D$8 | L8: =+L7*$D$8 | M8: =+M7*$D$8 | ... O8: =+O7*$D$8
C9: Net Rental Income | E9: =+E7-E8 | F9: =+F7-F8 | G9: =+G7-G8 | H9: =+H7-H8 | I9: =+I7-I8 | J9: =+J7-J8 | K9: =+K7-K8 | L9: =+L7-L8 | ... O9: =+O7-O8
C11: Laundry and Other Income | D11: =+Dashboard!$P$14 | E11: =+'Scenario 0'!$E$11 | F11: =+Dashboard!$O$14 | G11: =+F11*(1+$D11) | H11: =+G11*(1+$D11) | I11: =+H11*(1+$D11) | J11: =+I11*(1+$D11) | K11: =+J11*(1+$D11) | L11: =+K11*(1+$D11) | M11: =+L11*(1+$D11) | N11: =+M11*(1+$D11) | O11: =+N11*(1+$D11)
C12: Total Gross Income | E12: =+SUM(E9:E11) | F12: =+SUM(F9:F11) | G12: =+SUM(G9:G11) | H12: =+SUM(H9:H11) | I12: =+SUM(I9:I11) | J12: =+SUM(J9:J11) | K12: =+SUM(K9:K11) | L12: =+SUM(L9:L11) | ... O12: =+SUM(O9:O11)
C13: Gross Income Growth | E13: -- | F13: =+F12/E12-1 | G13: =+G12/F12-1 | H13: =+H12/G12-1 | I13: =+I12/H12-1 | J13: =+J12/I12-1 | K13: =+K12/J12-1 | L13: =+L12/K12-1 | M13: =+M12/L12-1 | ... O13: =+O12/N12-1
C15: Opertating Expenses
A17: BAD
C18: Bad Debt | E18: =+'Scenario 0'!E18 | F18: =+'Scenario 0'!F18 | G18: =+'Scenario 0'!G18 | H18: =+'Scenario 0'!H18 | I18: =+'Scenario 0'!I18 | J18: =+'Scenario 0'!J18 | K18: =+'Scenario 0'!K18 | L18: =+'Scenario 0'!L18 | ... O18: =+'Scenario 0'!O18
A20: RES
A21: COM
C22: Total Replacement Reserves | E22: =+'Scenario 0'!E22 | F22: =+'Scenario 0'!F22 | G22: =+'Scenario 0'!G22 | H22: =+'Scenario 0'!H22 | I22: =+'Scenario 0'!I22 | J22: =+'Scenario 0'!J22 | K22: =+'Scenario 0'!K22 | L22: =+'Scenario 0'!L22 | ... O22: =+'Scenario 0'!O22
A24: MAN
A25: ASS
A26: PAY
A27: MAIT
C28: Payroll | E28: =+'Scenario 0'!E29 | F28: =+'Scenario 0'!F29 | G28: =+'Scenario 0'!G29 | H28: =+'Scenario 0'!H29 | I28: =+'Scenario 0'!I29 | J28: =+'Scenario 0'!J29 | K28: =+'Scenario 0'!K29 | L28: =+'Scenario 0'!L29 | ... O28: =+'Scenario 0'!O29
A30: MGMT
A31: LEGAL
A32: OFF
A33: TRAVEL
A34: AUD
A35: ADV
A36: TRAIN
A37: BANK
A38: BOOK
A39: PAYSERV
A40: UNIT
A41: MISCAD
C42: Admin Expenses | E42: =+'Scenario 0'!E43 | F42: =+'Scenario 0'!F43 | G42: =+'Scenario 0'!G43 | H42: =+'Scenario 0'!H43 | I42: =+'Scenario 0'!I43 | J42: =+'Scenario 0'!J43 | K42: =+'Scenario 0'!K43 | L42: =+'Scenario 0'!L43 | ... O42: =+'Scenario 0'!O43
A44: ELEC
A45: VAC
A46: WS
A47: GAS
A48: CABLE
A49: TRASH
C50: Utility Expenses | E50: =+'Scenario 0'!E51 | F50: =+'Scenario 0'!F51 | G50: =+'Scenario 0'!G51 | H50: =+'Scenario 0'!H51 | I50: =+'Scenario 0'!I51 | J50: =+'Scenario 0'!J51 | K50: =+'Scenario 0'!K51 | L50: =+'Scenario 0'!L51 | ... O50: =+'Scenario 0'!O51
A52: RM
A53: TURN
A54: SUPP
A55: APP
A56: HP
A57: CONC
C58: Operating and Maint. | E58: =+'Scenario 0'!E59 | F58: =+'Scenario 0'!F59 | G58: =+'Scenario 0'!G59 | H58: =+'Scenario 0'!H59 | I58: =+'Scenario 0'!I59 | J58: =+'Scenario 0'!J59 | K58: =+'Scenario 0'!K59 | L58: =+'Scenario 0'!L59 | ... O58: =+'Scenario 0'!O59
A60: LAND
A61: FIRE
A62: SEC
A63: PEST
A64: CON
A65: ELEV
A66: SNOW
A67: MISCOP
C68: Contract Expenses | E68: =+'Scenario 0'!E69 | F68: =+'Scenario 0'!F69 | G68: =+'Scenario 0'!G69 | H68: =+'Scenario 0'!H69 | I68: =+'Scenario 0'!I69 | J68: =+'Scenario 0'!J69 | K68: =+'Scenario 0'!K69 | L68: =+'Scenario 0'!L69 | ... O68: =+'Scenario 0'!O69
A70: RETAX
A71: INS
A72: WORKCOMP
A73: HEALTH
A74: PTAX
A75: MISCTAX
C76: Total Taxes and Insurance Expenses | E76: =+'Scenario 0'!E77 | F76: =+'Scenario 0'!F77 | G76: =+'Scenario 0'!G77 | H76: =+'Scenario 0'!H77 | I76: =+'Scenario 0'!I77 | J76: =+'Scenario 0'!J77 | K76: =+'Scenario 0'!K77 | L76: =+'Scenario 0'!L77 | ... O76: =+'Scenario 0'!O77
C78: Total Operating Expenses | E78: =+SUM(E18,E22,E28,E42,E50,E58,E68,E76,) | F78: =+SUM(F18,F22,F28,F42,F50,F58,F68,F76,) | G78: =+SUM(G18,G22,G28,G42,G50,G58,G68,G76,) | H78: =+SUM(H18,H22,H28,H42,H50,H58,H68,H76,) | I78: =+SUM(I18,I22,I28,I42,I50,I58,I68,I76,) | J78: =+SUM(J18,J22,J28,J42,J50,J58,J68,J76,) | K78: =+SUM(K18,K22,K28,K42,K50,K58,K68,K76,) | L78: =+SUM(L18,L22,L28,L42,L50,L58,L68,L76,) | ... O78: =+SUM(O18,O22,O28,O42,O50,O58,O68,O76,)
C80: Net Operating Income | E80: =+E12-E78 | F80: =+F12-F78 | G80: =+G12-G78 | H80: =+H12-H78 | I80: =+I12-I78 | J80: =+J12-J78 | K80: =+K12-K78 | L80: =+L12-L78 | ... O80: =+O12-O78
C81: NOI Margin | E81: =+IFERROR(E80/E12,"--") | F81: =+F80/F12 | G81: =+G80/G12 | H81: =+H80/H12 | I81: =+I80/I12 | J81: =+J80/J12 | K81: =+K80/K12 | L81: =+L80/L12 | M81: =+M80/M12 | ... O81: =+O80/O12
C83: Capital Expenditures
C84: Other CapEx
C85: Capital Reserve
C86: Total Capital Expenditures | E86: =+SUM(E84:E85) | F86: =+SUM(F84:F85) | G86: =+SUM(G84:G85) | H86: =+SUM(H84:H85) | I86: =+SUM(I84:I85) | J86: =+SUM(J84:J85) | K86: =+SUM(K84:K85) | L86: =+SUM(L84:L85) | ... O86: =+SUM(O84:O85)
C88: Cash Flow from Operations (Adj. NOI) | E88: =+E80-E86 | F88: =+F80-F86 | G88: =+G80-G86 | H88: =+H80-H86 | I88: =+I80-I86 | J88: =+J80-J86 | K88: =+K80-K86 | L88: =+L80-L86 | ... O88: =+O80-O86
C90: Debt Service | E90: -- | F90: =+Dashboard!$I$10*Dashboard!$E$50 | G90: =+F90 | H90: =+G90 | I90: =+H90 | J90: =+I90 | K90: =+J90 | L90: =+K90 | M90: =+L90 | N90: =+M90 | O90: =+N90
C91: Principal Repayment | E91: -- | F91: =IF(F$6<=Dashboard!$E$56,0,-PPMT(Dashboard!$E$50,'Scenario 4'!F3-'Scenario 4'!$E3,Dashboard!$E$55,Dashboard!$D$49)) | G91: =IF(G$6<=Dashboard!$E$56,0,-PPMT(Dashboard!$E$50,'Scenario 4'!G3-'Scenario 4'!$E3,Dashboard!$E$55,Dashboard!$D$49)) | H91: =IF(H$6<=Dashboard!$E$56,0,-PPMT(Dashboard!$E$50,'Scenario 4'!H3-'Scenario 4'!$E3,Dashboard!$E$55,Dashboard!$D$49)) | I91: =IF(I$6<=Dashboard!$E$56,0,-PPMT(Dashboard!$E$50,'Scenario 4'!I3-'Scenario 4'!$E3,Dashboard!$E$55,Dashboard!$D$49)) | J91: =IF(J$6<=Dashboard!$E$56,0,-PPMT(Dashboard!$E$50,'Scenario 4'!J3-'Scenario 4'!$E3,Dashboard!$E$55,Dashboard!$D$49)) | K91: =IF(K$6<=Dashboard!$E$56,0,-PPMT(Dashboard!$E$50,'Scenario 4'!K3-'Scenario 4'!$E3,Dashboard!$E$55,Dashboard!$D$49)) | L91: =IF(L$6<=Dashboard!$E$56,0,-PPMT(Dashboard!$E$50,'Scenario 4'!L3-'Scenario 4'!$E3,Dashboard!$E$55,Dashboard!$D$49)) | M91: =IF(M$6<=Dashboard!$E$56,0,-PPMT(Dashboard!$E$50,'Scenario 4'!M3-'Scenario 4'!$E3,Dashboard!$E$55,Dashboard!$D$49)) | ... O91: =IF(O$6<=Dashboard!$E$56,0,-PPMT(Dashboard!$E$50,'Scenario 4'!O3-'Scenario 4'!$E3,Dashboard!$E$55,Dashboard!$D$49))
C92: Cash Flow After Financing (CF to Equity Investors) | E92: -- | F92: =+F88-F90 | G92: =+G88-G90 | H92: =+H88-H90 | I92: =+I88-I90 | J92: =+J88-J90 | K92: =+K88-K90 | L92: =+L88-L90 | M92: =+M88-M90 | ... O92: =+O88-O90
C94: Ending Debt Balance | F94: =+Dashboard!$D$49-SUM('Scenario 4'!$F$91:F91) | G94: =+Dashboard!$D$49-SUM('Scenario 4'!$F$91:G91) | H94: =+Dashboard!$D$49-SUM('Scenario 4'!$F$91:H91) | I94: =+Dashboard!$D$49-SUM('Scenario 4'!$F$91:I91) | J94: =+Dashboard!$D$49-SUM('Scenario 4'!$F$91:J91) | K94: =+Dashboard!$D$49-SUM('Scenario 4'!$F$91:K91) | L94: =+Dashboard!$D$49-SUM('Scenario 4'!$F$91:L91) | M94: =+Dashboard!$D$49-SUM('Scenario 4'!$F$91:M91) | ... O94: =+Dashboard!$D$49-SUM('Scenario 4'!$F$91:O91)
C96: DSCR (NOI) | F96: =+IFERROR(F80/F90,"") | G96: =+IFERROR(G80/G90,"") | H96: =+IFERROR(H80/H90,"") | I96: =+IFERROR(I80/I90,"") | J96: =+IFERROR(J80/J90,"") | K96: =+IFERROR(K80/K90,"") | L96: =+IFERROR(L80/L90,"") | M96: =+IFERROR(M80/M90,"") | ... O96: =+IFERROR(O80/O90,"")
C97: DSCR (CFO) | F97: =+IFERROR(F88/F90,"") | G97: =+IFERROR(G88/G90,"") | H97: =+IFERROR(H88/H90,"") | I97: =+IFERROR(I88/I90,"") | J97: =+IFERROR(J88/J90,"") | K97: =+IFERROR(K88/K90,"") | L97: =+IFERROR(L88/L90,"") | M97: =+IFERROR(M88/M90,"") | ... O97: =+IFERROR(O88/O90,"")
C98: Debt Yield (CFO) | F98: =+F88/Dashboard!$I$10 | G98: =+G88/Dashboard!$I$10 | H98: =+H88/Dashboard!$I$10 | I98: =+I88/Dashboard!$I$10 | J98: =+J88/Dashboard!$I$10 | K98: =+K88/Dashboard!$I$10 | L98: =+L88/Dashboard!$I$10 | M98: =+M88/Dashboard!$I$10 | ... O98: =+O88/Dashboard!$I$10
C99: Break-Even Ratio | F99: =+SUM(F96,F78)/F12 | G99: =+SUM(G96,G78)/G12 | H99: =+SUM(H96,H78)/H12 | I99: =+SUM(I96,I78)/I12 | J99: =+SUM(J96,J78)/J12 | K99: =+SUM(K96,K78)/K12 | L99: =+SUM(L96,L78)/L12 | M99: =+SUM(M96,M78)/M12 | ... O99: =+SUM(O96,O78)/O12
C101: Cap Rate (Purchase Price) | F101: =+F80/Dashboard!$E$32 | G101: =+G80/Dashboard!$E$32 | H101: =+H80/Dashboard!$E$32 | I101: =+I80/Dashboard!$E$32 | J101: =+J80/Dashboard!$E$32 | K101: =+K80/Dashboard!$E$32 | L101: =+L80/Dashboard!$E$32 | M101: =+M80/Dashboard!$E$32 | ... O101: =+O80/Dashboard!$E$32
C102: Operating Cash Flow Before Taxes | F102: =+F80-F90-F91 | G102: =+G80-G90-G91 | H102: =+H80-H90-H91 | I102: =+I80-I90-I91 | J102: =+J80-J90-J91 | K102: =+K80-K90-K91 | L102: =+L80-L90-L91 | M102: =+M80-M90-M91 | ... O102: =+O80-O90-O91
C103: Cash on Cash Return | F103: =+F102/Dashboard!$I$11 | G103: =+G102/Dashboard!$I$11 | H103: =+H102/Dashboard!$I$11 | I103: =+I102/Dashboard!$I$11 | J103: =+J102/Dashboard!$I$11 | K103: =+K102/Dashboard!$I$11 | L103: =+L102/Dashboard!$I$11 | M103: =+M102/Dashboard!$I$11 | ... O103: =+O102/Dashboard!$I$11
C104: General Partner Cash Return | D104: =+Dashboard!J58 | F104: =+F102*$D$104 | G104: =+G102*$D$104 | H104: =+H102*$D$104 | I104: =+I102*$D$104 | J104: =+J102*$D$104 | K104: =+K102*$D$104 | L104: =+L102*$D$104 | M104: =+M102*$D$104 | ... O104: =+O102*$D$104
C105: Total Limited Partner Cash Return | D105: =+Dashboard!J59 | F105: =+F102*$D$105 | G105: =+G102*$D$105 | H105: =+H102*$D$105 | I105: =+I102*$D$105 | J105: =+J102*$D$105 | K105: =+K102*$D$105 | L105: =+L102*$D$105 | M105: =+M102*$D$105 | ... O105: =+O102*$D$105
C106: Cash on Cash LP Return | F106: =+F105/Dashboard!$I$11 | G106: =+G105/Dashboard!$I$11 | H106: =+H105/Dashboard!$I$11 | I106: =+I105/Dashboard!$I$11 | J106: =+J105/Dashboard!$I$11 | K106: =+K105/Dashboard!$I$11 | L106: =+L105/Dashboard!$I$11 | M106: =+M105/Dashboard!$I$11 | ... O106: =+O105/Dashboard!$I$11
C108: Return Metrics
C110: 5 Year Hold IRR | E110: =+'Scenario 0'!E111 | F110: =+'Scenario 0'!F111 | G110: =+'Scenario 0'!G111 | H110: =+'Scenario 0'!H111 | I110: =+'Scenario 0'!I111 | J110: =+'Scenario 0'!J111
C112: Exit Cap Rate Assumption | D112: =+Dashboard!$J$54
C114: Project Cash Flows (Unleveraged IRR):
C115: (+) Proceeds from Sale of Property: | F115: 0 | G115: 0 | H115: 0 | I115: 0 | J115: =+J$80/D$112
C116: (-) Selling Costs: | D116: =+Dashboard!$J$55 | F116: 0 | G116: 0 | H116: 0 | I116: 0 | J116: =-J$115*D$116
C117: (+) Adjusted NOI (Cash Flows to All Investors): | F117: =+F$88 | G117: =+G$88 | H117: =+H$88 | I117: =+I$88 | J117: =+J$88
C118: (-) Property Acquisition Price: | E118: =-Dashboard!$E$32 | F118: 0 | G118: 0 | H118: 0 | I118: 0 | J118: 0
C119: Total Project Cash Flows (Unleveraged IRR): | E119: =SUM(E115:E118) | F119: =SUM(F115:F118) | G119: =SUM(G115:G118) | H119: =SUM(H115:H118) | I119: =SUM(I115:I118) | J119: =SUM(J115:J118)
F120: =+F119-F115 | G120: =+G119-G115 | H120: =+H119-H115 | I120: =+I119-I115 | J120: =+J119-J115
C122: Unlevered IRR: | E122: =+IRR(E119:J119)
C123: Unlevered Cash-on-Cash Multiple: | E123: =+SUM(F115:J117)/-SUM(E118:J118)
C125: Cash Flow to Equity Investors (Leveraged IRR):
C126: (+) Proceeds from Sale of Property: | F126: 0 | G126: 0 | H126: 0 | I126: 0 | J126: =+J$80/D$112
...

Sheet Rent Roll Calcs -->

Sheet Unit Mix
B3: Scenario 0 (No Change to Asset) | P3: Scenario 1 ( Max Current Vouchers) | W3: Scenario 2 (Max Net LIHTC) | AD3: Scenario 3 ( Max Current Vouchers + NET LIHTC) | AK3: Scenario 4 (Max Net LIHTC)
B5: Year 1 | P5: =+$B5 | W5: =+$B5 | AD5: =+$B5 | AK5: =+$B5
B6: Unit Type | C6: AMI / S8 | D6: # of Units | E6: Avg. SF | F6: Avg. Utilities | G6: Avg. Max LITHC | H6: Net LIHTC | I6: Avg. Max FMR | J6: Net FMR | K6: CoStar Rent | L6: Gross Rent | M6: Avg. Current Rent | N6: Yrly. Gross Income (Net Rent) | P6: Unit Type | Q6: AMI / S8 | R6: # of Units | S6: Avg. SF | T6: Avg. Utilities | U6: Max Current Vouchers | W6: Unit Type | X6: AMI / S8 | Y6: # of Units | Z6: Avg. SF | AA6: Avg. Utilities | AB6: Max NET LIHTC | AD6: Unit Type | AE6: AMI / S8 | AF6: # of Units | AG6: Avg. SF | AH6: Avg. Utilities | AI6: Max Current Vouchers + NET LIHTC | AK6: Unit Type | AL6: AMI / S8 | AM6: # of Units | AN6: Avg. SF | AO6: Avg. Utilities | AP6: Max Net LIHTC / Voucher Floor
B7: ='Rent Roll'!C13 | C7: ='Rent Roll'!D13 | D7: ='Rent Roll'!E13 | E7: ='Rent Roll'!F13 | F7: ='Rent Roll'!K13 | G7: ='Rent Roll'!M13 | H7: =+G7-F7 | I7: ='Rent Roll'!O13 | J7: =I7-F7 | K7: ='Rent Roll'!G13 | L7: ='Rent Roll'!L13 | M7: ='Rent Roll'!J13 | N7: =((M7*D7)*12) | P7: =B7 | Q7: =C7 | R7: =D7 | S7: =E7 | T7: =F7 | U7: =((M7*R7)*12) | W7: =B7 | X7: =C7 | Y7: =D7 | Z7: =E7 | AA7: =F7 | AB7: =((H7*Y7)*12) | AD7: =B7 | AE7: =C7 | AF7: =D7 | AG7: =E7 | AH7: =F7 | AI7: =+MAX(U7,AB7) | AK7: =B7 | AL7: =C7 | AM7: =D7 | AN7: =E7 | AO7: =F7 | AP7: =IF(G7>0,MAX(U7,AB7),N7)
B8: ='Rent Roll'!C14 | C8: ='Rent Roll'!D14 | D8: ='Rent Roll'!E14 | E8: ='Rent Roll'!F14 | F8: ='Rent Roll'!K14 | G8: ='Rent Roll'!M14 | H8: =+G8-F8 | I8: ='Rent Roll'!O14 | J8: =I8-F8 | K8: ='Rent Roll'!G14 | L8: ='Rent Roll'!L14 | M8: ='Rent Roll'!J14 | N8: =((M8*D8)*12) | P8: =B8 | Q8: =C8 | R8: =D8 | S8: =E8 | T8: =F8 | U8: =((M8*R8)*12) | W8: =B8 | X8: =C8 | Y8: =D8 | Z8: =E8 | AA8: =F8 | AB8: =((H8*Y8)*12) | AD8: =B8 | AE8: =C8 | AF8: =D8 | AG8: =E8 | AH8: =F8 | AI8: =+MAX(U8,AB8) | AK8: =B8 | AL8: =C8 | AM8: =D8 | AN8: =E8 | AO8: =F8 | AP8: =IF(G8>0,MAX(U8,AB8),N8)
B9: ='Rent Roll'!C15 | C9: ='Rent Roll'!D15 | D9: ='Rent Roll'!E15 | E9: ='Rent Roll'!F15 | F9: ='Rent Roll'!K15 | G9: ='Rent Roll'!M15 | H9: =+G9-F9 | I9: ='Rent Roll'!O15 | J9: =I9-F9 | K9: ='Rent Roll'!G15 | L9: ='Rent Roll'!L15 | M9: ='Rent Roll'!J15 | N9: =((M9*D9)*12) | P9: =B9 | Q9: =C9 | R9: =D9 | S9: =E9 | T9: =F9 | U9: =((M9*R9)*12) | W9: =B9 | X9: =C9 | Y9: =D9 | Z9: =E9 | AA9: =F9 | AB9: =((H9*Y9)*12) | AD9: =B9 | AE9: =C9 | AF9: =D9 | AG9: =E9 | AH9: =F9 | AI9: =+MAX(U9,AB9) | AK9: =B9 | AL9: =C9 | AM9: =D9 | AN9: =E9 | AO9: =F9 | AP9: =IF(G9>0,MAX(U9,AB9),N9)
B10: ='Rent Roll'!C16 | C10: ='Rent Roll'!D16 | D10: ='Rent Roll'!E16 | E10: ='Rent Roll'!F16 | F10: ='Rent Roll'!K16 | G10: ='Rent Roll'!M16 | H10: =+G10-F10 | I10: ='Rent Roll'!O16 | J10: =I10-F10 | K10: ='Rent Roll'!G16 | L10: ='Rent Roll'!L16 | M10: ='Rent Roll'!J16 | N10: =((M10*D10)*12) | P10: =B10 | Q10: =C10 | R10: =D10 | S10: =E10 | T10: =F10 | U10: =((M10*R10)*12) | W10: =B10 | X10: =C10 | Y10: =D10 | Z10: =E10 | AA10: =F10 | AB10: =((H10*Y10)*12) | AD10: =B10 | AE10: =C10 | AF10: =D10 | AG10: =E10 | AH10: =F10 | AI10: =+MAX(U10,AB10) | AK10: =B10 | AL10: =C10 | AM10: =D10 | AN10: =E10 | AO10: =F10 | AP10: =IF(G10>0,MAX(U10,AB10),N10)
B11: ='Rent Roll'!C17 | C11: ='Rent Roll'!D17 | D11: ='Rent Roll'!E17 | E11: ='Rent Roll'!F17 | F11: ='Rent Roll'!K17 | G11: ='Rent Roll'!M17 | H11: =+G11-F11 | I11: ='Rent Roll'!O17 | J11: =I11-F11 | K11: ='Rent Roll'!G17 | L11: ='Rent Roll'!L17 | M11: ='Rent Roll'!J17 | N11: =((M11*D11)*12) | P11: =B11 | Q11: =C11 | R11: =D11 | S11: =E11 | T11: =F11 | U11: =((M11*R11)*12) | W11: =B11 | X11: =C11 | Y11: =D11 | Z11: =E11 | AA11: =F11 | AB11: =((H11*Y11)*12) | AD11: =B11 | AE11: =C11 | AF11: =D11 | AG11: =E11 | AH11: =F11 | AI11: =+MAX(U11,AB11) | AK11: =B11 | AL11: =C11 | AM11: =D11 | AN11: =E11 | AO11: =F11 | AP11: =IF(G11>0,MAX(U11,AB11),N11)
B12: ='Rent Roll'!C18 | C12: ='Rent Roll'!D18 | D12: ='Rent Roll'!E18 | E12: ='Rent Roll'!F18 | F12: ='Rent Roll'!K18 | G12: ='Rent Roll'!M18 | H12: =+G12-F12 | I12: ='Rent Roll'!O18 | J12: =I12-F12 | K12: ='Rent Roll'!G18 | L12: ='Rent Roll'!L18 | M12: ='Rent Roll'!J18 | N12: =((M12*D12)*12) | P12: =B12 | Q12: =C12 | R12: =D12 | S12: =E12 | T12: =F12 | U12: =((M12*R12)*12) | W12: =B12 | X12: =C12 | Y12: =D12 | Z12: =E12 | AA12: =F12 | AB12: =((H12*Y12)*12) | AD12: =B12 | AE12: =C12 | AF12: =D12 | AG12: =E12 | AH12: =F12 | AI12: =+MAX(U12,AB12) | AK12: =B12 | AL12: =C12 | AM12: =D12 | AN12: =E12 | AO12: =F12 | AP12: =IF(G12>0,MAX(U12,AB12),N12)
B13: ='Rent Roll'!C19 | C13: ='Rent Roll'!D19 | D13: ='Rent Roll'!E19 | E13: ='Rent Roll'!F19 | F13: ='Rent Roll'!K19 | G13: ='Rent Roll'!M19 | H13: =+G13-F13 | I13: ='Rent Roll'!O19 | J13: =I13-F13 | K13: ='Rent Roll'!G19 | L13: ='Rent Roll'!L19 | M13: ='Rent Roll'!J19 | N13: =((M13*D13)*12) | P13: =B13 | Q13: =C13 | R13: =D13 | S13: =E13 | T13: =F13 | U13: =((M13*R13)*12) | W13: =B13 | X13: =C13 | Y13: =D13 | Z13: =E13 | AA13: =F13 | AB13: =((H13*Y13)*12) | AD13: =B13 | AE13: =C13 | AF13: =D13 | AG13: =E13 | AH13: =F13 | AI13: =+MAX(U13,AB13) | AK13: =B13 | AL13: =C13 | AM13: =D13 | AN13: =E13 | AO13: =F13 | AP13: =IF(G13>0,MAX(U13,AB13),N13)
B14: ='Rent Roll'!C20 | C14: ='Rent Roll'!D20 | D14: ='Rent Roll'!E20 | E14: ='Rent Roll'!F20 | F14: ='Rent Roll'!K20 | G14: ='Rent Roll'!M20 | H14: =+G14-F14 | I14: ='Rent Roll'!O20 | J14: =I14-F14 | K14: ='Rent Roll'!G20 | L14: ='Rent Roll'!L20 | M14: ='Rent Roll'!J20 | N14: =((M14*D14)*12) | P14: =B14 | Q14: =C14 | R14: =D14 | S14: =E14 | T14: =F14 | U14: =((M14*R14)*12) | W14: =B14 | X14: =C14 | Y14: =D14 | Z14: =E14 | AA14: =F14 | AB14: =((H14*Y14)*12) | AD14: =B14 | AE14: =C14 | AF14: =D14 | AG14: =E14 | AH14: =F14 | AI14: =+MAX(U14,AB14) | AK14: =B14 | AL14: =C14 | AM14: =D14 | AN14: =E14 | AO14: =F14 | AP14: =IF(G14>0,MAX(U14,AB14),N14)
B15: ='Rent Roll'!C21 | C15: ='Rent Roll'!D21 | D15: ='Rent Roll'!E21 | E15: ='Rent Roll'!F21 | F15: ='Rent Roll'!K21 | G15: ='Rent Roll'!M21 | H15: =+G15-F15 | I15: ='Rent Roll'!O21 | J15: =I15-F15 | K15: ='Rent Roll'!G21 | L15: ='Rent Roll'!L21 | M15: ='Rent Roll'!J21 | N15: =((M15*D15)*12) | P15: =B15 | Q15: =C15 | R15: =D15 | S15: =E15 | T15: =F15 | U15: =((M15*R15)*12) | W15: =B15 | X15: =C15 | Y15: =D15 | Z15: =E15 | AA15: =F15 | AB15: =((H15*Y15)*12) | AD15: =B15 | AE15: =C15 | AF15: =D15 | AG15: =E15 | AH15: =F15 | AI15: =+MAX(U15,AB15) | AK15: =B15 | AL15: =C15 | AM15: =D15 | AN15: =E15 | AO15: =F15 | AP15: =IF(G15>0,MAX(U15,AB15),N15)
B16: ='Rent Roll'!C22 | C16: ='Rent Roll'!D22 | D16: ='Rent Roll'!E22 | E16: ='Rent Roll'!F22 | F16: ='Rent Roll'!K22 | G16: ='Rent Roll'!M22 | H16: =+G16-F16 | I16: ='Rent Roll'!O22 | J16: =I16-F16 | K16: ='Rent Roll'!G22 | L16: ='Rent Roll'!L22 | M16: ='Rent Roll'!J22 | N16: =((M16*D16)*12) | P16: =B16 | Q16: =C16 | R16: =D16 | S16: =E16 | T16: =F16 | U16: =((M16*R16)*12) | W16: =B16 | X16: =C16 | Y16: =D16 | Z16: =E16 | AA16: =F16 | AB16: =((H16*Y16)*12) | AD16: =B16 | AE16: =C16 | AF16: =D16 | AG16: =E16 | AH16: =F16 | AI16: =+MAX(U16,AB16) | AK16: =B16 | AL16: =C16 | AM16: =D16 | AN16: =E16 | AO16: =F16 | AP16: =IF(G16>0,MAX(U16,AB16),N16)
B17: ='Rent Roll'!C23 | C17: ='Rent Roll'!D23 | D17: ='Rent Roll'!E23 | E17: ='Rent Roll'!F23 | F17: ='Rent Roll'!K23 | G17: ='Rent Roll'!M23 | H17: =+G17-F17 | I17: ='Rent Roll'!O23 | J17: =I17-F17 | K17: ='Rent Roll'!G23 | L17: ='Rent Roll'!L23 | M17: ='Rent Roll'!J23 | N17: =((M17*D17)*12) | P17: =B17 | Q17: =C17 | R17: =D17 | S17: =E17 | T17: =F17 | U17: =((M17*R17)*12) | W17: =B17 | X17: =C17 | Y17: =D17 | Z17: =E17 | AA17: =F17 | AB17: =((H17*Y17)*12) | AD17: =B17 | AE17: =C17 | AF17: =D17 | AG17: =E17 | AH17: =F17 | AI17: =+MAX(U17,AB17) | AK17: =B17 | AL17: =C17 | AM17: =D17 | AN17: =E17 | AO17: =F17 | AP17: =IF(G17>0,MAX(U17,AB17),N17)
B18: ='Rent Roll'!C24 | C18: ='Rent Roll'!D24 | D18: ='Rent Roll'!E24 | E18: ='Rent Roll'!F24 | F18: ='Rent Roll'!K24 | G18: ='Rent Roll'!M24 | H18: =+G18-F18 | I18: ='Rent Roll'!O24 | J18: =I18-F18 | K18: ='Rent Roll'!G24 | L18: ='Rent Roll'!L24 | M18: ='Rent Roll'!J24 | N18: =((M18*D18)*12) | P18: =B18 | Q18: =C18 | R18: =D18 | S18: =E18 | T18: =F18 | U18: =((M18*R18)*12) | W18: =B18 | X18: =C18 | Y18: =D18 | Z18: =E18 | AA18: =F18 | AB18: =((H18*Y18)*12) | AD18: =B18 | AE18: =C18 | AF18: =D18 | AG18: =E18 | AH18: =F18 | AI18: =+MAX(U18,AB18) | AK18: =B18 | AL18: =C18 | AM18: =D18 | AN18: =E18 | AO18: =F18 | AP18: =IF(G18>0,MAX(U18,AB18),N18)
... B25: ='Rent Roll'!C31 | C25: ='Rent Roll'!D31 | D25: ='Rent Roll'!E31 | E25: ='Rent Roll'!F31 | F25: ='Rent Roll'!K31 | G25: ='Rent Roll'!M31 | H25: =+G25-F25 | I25: ='Rent Roll'!O31 | J25: =I25-F25 | K25: ='Rent Roll'!G31 | L25: ='Rent Roll'!L31 | M25: ='Rent Roll'!J31 | N25: =((M25*D25)*12) | P25: =B25 | Q25: =C25 | R25: =D25 | S25: =E25 | T25: =F25 | U25: =((M25*R25)*12) | W25: =B25 | X25: =C25 | Y25: =D25 | Z25: =E25 | AA25: =F25 | AB25: =((H25*Y25)*12) | AD25: =B25 | AE25: =C25 | AF25: =D25 | AG25: =E25 | AH25: =F25 | AI25: =+MAX(U25,AB25) | AK25: =B25 | AL25: =C25 | AM25: =D25 | AN25: =E25 | AO25: =F25 | AP25: =IF(G25>0,MAX(U25,AB25),N25)
B26: Total (Pre-Vacancy) | D26: =SUM(D7:D25) | E26: =+SUMPRODUCT(E7:E25,$D7:$D25) | F26: =+SUMPRODUCT(F7:F25,$D7:$D25) | G26: =+SUMPRODUCT(G7:G25,$D7:$D25) | H26: =+SUMPRODUCT(H7:H25,$D7:$D25) | I26: =+SUMPRODUCT(I7:I25,$D7:$D25) | J26: =+SUMPRODUCT(J7:J25,$D7:$D25) | K26: =+SUMPRODUCT(K7:K25,$D7:$D25) | L26: =+SUMPRODUCT(L7:L25,$D7:$D25) | M26: =+SUMPRODUCT(M7:M25,$D7:$D25) | N26: =SUM(N7:N25) | P26: Total (Pre-Vacancy) | R26: =SUM(R7:R25) | S26: =+SUMPRODUCT(S7:S25,$R7:$R25) | T26: =+SUMPRODUCT(T7:T25,$R7:$R25) | U26: =SUM(U7:U25) | W26: Total (Pre-Vacancy) | Y26: =SUM(Y7:Y25) | Z26: =+SUMPRODUCT(Z7:Z25,$Y7:$Y25) | AA26: =+SUMPRODUCT(AA7:AA25,$Y7:$Y25) | AB26: =SUM(AB7:AB25) | AD26: Total (Pre-Vacancy) | AF26: =SUM(AF7:AF25) | AG26: =+SUMPRODUCT(AG7:AG25,$AF7:$AF25) | AH26: =+SUMPRODUCT(AH7:AH25,$AF7:$AF25) | AI26: =SUM(AI7:AI25) | AK26: Total (Pre-Vacancy) | AM26: =SUM(AF7:AF25) | AN26: =+SUMPRODUCT(AG7:AG25,$AF7:$AF25) | AO26: =+SUMPRODUCT(AH7:AH25,$AF7:$AF25) | AP26: =SUM(AP7:AP25)
B28: Year 2 | P28: =+$B28 | W28: =+$B28 | AD28: =+$B28 | AK28: =+$B28
B29: Unit Type | C29: AMI / S8 | D29: # of Units | E29: Avg. SF | F29: Avg. Utilities | G29: Avg. Max LITHC | H29: Net LIHTC | I29: Avg. Max FMR | J29: Net FMR | K29: =+K6 | L29: Gross Rent | M29: Avg. Current Rent | N29: Yrly. Gross Income (Net Rent) | P29: Unit Type | Q29: AMI / S8 | R29: # of Units | S29: Avg. SF | T29: Avg. Utilities | U29: Max Current Vouchers | W29: Unit Type | X29: AMI / S8 | Y29: # of Units | Z29: Avg. SF | AA29: Avg. Utilities | AB29: Max NET LIHTC | AD29: Unit Type | AE29: AMI / S8 | AF29: # of Units | AG29: Avg. SF | AH29: Avg. Utilities | AI29: Max Current Vouchers + NET LIHTC | AK29: Unit Type | AL29: AMI / S8 | AM29: # of Units | AN29: Avg. SF | AO29: Avg. Utilities | AP29: Max Current Vouchers + NET LIHTC
B30: =B7 | C30: =C7 | D30: =$D7 | E30: =E7 | F30: =F7*(1+Dashboard!$P$12) | G30: =G7*(1+Dashboard!$P$11) | H30: =+G30-F30 | I30: =I7*(1+Dashboard!$P$11) | J30: =I30-F30 | K30: =K7*(1+Dashboard!$P$11) | L30: =M30+F30 | M30: =M7*(1+Dashboard!$P$11) | N30: =((M30*D30)*12) | P30: =B30 | Q30: =C30 | R30: =D30 | S30: =E30 | T30: =F30 | U30: =((M30*R30)*12) | W30: =B30 | X30: =C30 | Y30: =D30 | Z30: =E30 | AA30: =F30 | AB30: =((H30*Y30)*12) | AD30: =B30 | AE30: =C30 | AF30: =D30 | AG30: =E30 | AH30: =F30 | AI30: =+MAX(U30,AB30) | AK30: =B30 | AL30: =C30 | AM30: =D30 | AN30: =E30 | AO30: =F30 | AP30: =IF(G30>0,MAX(U30,AB30),N30)
B31: =B8 | C31: =C8 | D31: =$D8 | E31: =E8 | F31: =F8*(1+Dashboard!$P$12) | G31: =G8*(1+Dashboard!$P$11) | H31: =+G31-F31 | I31: =I8*(1+Dashboard!$P$11) | J31: =I31-F31 | K31: =K8*(1+Dashboard!$P$11) | L31: =M31+F31 | M31: =M8*(1+Dashboard!$P$11) | N31: =((M31*D31)*12) | P31: =B31 | Q31: =C31 | R31: =D31 | S31: =E31 | T31: =F31 | U31: =((M31*R31)*12) | W31: =B31 | X31: =C31 | Y31: =D31 | Z31: =E31 | AA31: =F31 | AB31: =((H31*Y31)*12) | AD31: =B31 | AE31: =C31 | AF31: =D31 | AG31: =E31 | AH31: =F31 | AI31: =+MAX(U31,AB31) | AK31: =B31 | AL31: =C31 | AM31: =D31 | AN31: =E31 | AO31: =F31 | AP31: =IF(G31>0,MAX(U31,AB31),N31)
B32: =B9 | C32: =C9 | D32: =$D9 | E32: =E9 | F32: =F9*(1+Dashboard!$P$12) | G32: =G9*(1+Dashboard!$P$11) | H32: =+G32-F32 | I32: =I9*(1+Dashboard!$P$11) | J32: =I32-F32 | K32: =K9*(1+Dashboard!$P$11) | L32: =M32+F32 | M32: =M9*(1+Dashboard!$P$11) | N32: =((M32*D32)*12) | P32: =B32 | Q32: =C32 | R32: =D32 | S32: =E32 | T32: =F32 | U32: =((M32*R32)*12) | W32: =B32 | X32: =C32 | Y32: =D32 | Z32: =E32 | AA32: =F32 | AB32: =((H32*Y32)*12) | AD32: =B32 | AE32: =C32 | AF32: =D32 | AG32: =E32 | AH32: =F32 | AI32: =+MAX(U32,AB32) | AK32: =B32 | AL32: =C32 | AM32: =D32 | AN32: =E32 | AO32: =F32 | AP32: =IF(G32>0,MAX(U32,AB32),N32)
B33: =B10 | C33: =C10 | D33: =$D10 | E33: =E10 | F33: =F10*(1+Dashboard!$P$12) | G33: =G10*(1+Dashboard!$P$11) | H33: =+G33-F33 | I33: =I10*(1+Dashboard!$P$11) | J33: =I33-F33 | K33: =K10*(1+Dashboard!$P$11) | L33: =M33+F33 | M33: =M10*(1+Dashboard!$P$11) | N33: =((M33*D33)*12) | P33: =B33 | Q33: =C33 | R33: =D33 | S33: =E33 | T33: =F33 | U33: =((M33*R33)*12) | W33: =B33 | X33: =C33 | Y33: =D33 | Z33: =E33 | AA33: =F33 | AB33: =((H33*Y33)*12) | AD33: =B33 | AE33: =C33 | AF33: =D33 | AG33: =E33 | AH33: =F33 | AI33: =+MAX(U33,AB33) | AK33: =B33 | AL33: =C33 | AM33: =D33 | AN33: =E33 | AO33: =F33 | AP33: =IF(G33>0,MAX(U33,AB33),N33)
B34: =B11 | C34: =C11 | D34: =$D11 | E34: =E11 | F34: =F11*(1+Dashboard!$P$12) | G34: =G11*(1+Dashboard!$P$11) | H34: =+G34-F34 | I34: =I11*(1+Dashboard!$P$11) | J34: =I34-F34 | K34: =K11*(1+Dashboard!$P$11) | L34: =M34+F34 | M34: =M11*(1+Dashboard!$P$11) | N34: =((M34*D34)*12) | P34: =B34 | Q34: =C34 | R34: =D34 | S34: =E34 | T34: =F34 | U34: =((M34*R34)*12) | W34: =B34 | X34: =C34 | Y34: =D34 | Z34: =E34 | AA34: =F34 | AB34: =((H34*Y34)*12) | AD34: =B34 | AE34: =C34 | AF34: =D34 | AG34: =E34 | AH34: =F34 | AI34: =+MAX(U34,AB34) | AK34: =B34 | AL34: =C34 | AM34: =D34 | AN34: =E34 | AO34: =F34 | AP34: =IF(G34>0,MAX(U34,AB34),N34)
B35: =B12 | C35: =C12 | D35: =$D12 | E35: =E12 | F35: =F12*(1+Dashboard!$P$12) | G35: =G12*(1+Dashboard!$P$11) | H35: =+G35-F35 | I35: =I12*(1+Dashboard!$P$11) | J35: =I35-F35 | K35: =K12*(1+Dashboard!$P$11) | L35: =M35+F35 | M35: =M12*(1+Dashboard!$P$11) | N35: =((M35*D35)*12) | P35: =B35 | Q35: =C35 | R35: =D35 | S35: =E35 | T35: =F35 | U35: =((M35*R35)*12) | W35: =B35 | X35: =C35 | Y35: =D35 | Z35: =E35 | AA35: =F35 | AB35: =((H35*Y35)*12) | AD35: =B35 | AE35: =C35 | AF35: =D35 | AG35: =E35 | AH35: =F35 | AI35: =+MAX(U35,AB35) | AK35: =B35 | AL35: =C35 | AM35: =D35 | AN35: =E35 | AO35: =F35 | AP35: =IF(G35>0,MAX(U35,AB35),N35)
B36: =B13 | C36: =C13 | D36: =$D13 | E36: =E13 | F36: =F13*(1+Dashboard!$P$12) | G36: =G13*(1+Dashboard!$P$11) | H36: =+G36-F36 | I36: =I13*(1+Dashboard!$P$11) | J36: =I36-F36 | K36: =K13*(1+Dashboard!$P$11) | L36: =M36+F36 | M36: =M13*(1+Dashboard!$P$11) | N36: =((M36*D36)*12) | P36: =B36 | Q36: =C36 | R36: =D36 | S36: =E36 | T36: =F36 | U36: =((M36*R36)*12) | W36: =B36 | X36: =C36 | Y36: =D36 | Z36: =E36 | AA36: =F36 | AB36: =((H36*Y36)*12) | AD36: =B36 | AE36: =C36 | AF36: =D36 | AG36: =E36 | AH36: =F36 | AI36: =+MAX(U36,AB36) | AK36: =B36 | AL36: =C36 | AM36: =D36 | AN36: =E36 | AO36: =F36 | AP36: =IF(G36>0,MAX(U36,AB36),N36)
B37: =B14 | C37: =C14 | D37: =$D14 | E37: =E14 | F37: =F14*(1+Dashboard!$P$12) | G37: =G14*(1+Dashboard!$P$11) | H37: =+G37-F37 | I37: =I14*(1+Dashboard!$P$11) | J37: =I37-F37 | K37: =K14*(1+Dashboard!$P$11) | L37: =M37+F37 | M37: =M14*(1+Dashboard!$P$11) | N37: =((M37*D37)*12) | P37: =B37 | Q37: =C37 | R37: =D37 | S37: =E37 | T37: =F37 | U37: =((M37*R37)*12) | W37: =B37 | X37: =C37 | Y37: =D37 | Z37: =E37 | AA37: =F37 | AB37: =((H37*Y37)*12) | AD37: =B37 | AE37: =C37 | AF37: =D37 | AG37: =E37 | AH37: =F37 | AI37: =+MAX(U37,AB37) | AK37: =B37 | AL37: =C37 | AM37: =D37 | AN37: =E37 | AO37: =F37 | AP37: =IF(G37>0,MAX(U37,AB37),N37)
B38: =B15 | C38: =C15 | D38: =$D15 | E38: =E15 | F38: =F15*(1+Dashboard!$P$12) | G38: =G15*(1+Dashboard!$P$11) | H38: =+G38-F38 | I38: =I15*(1+Dashboard!$P$11) | J38: =I38-F38 | K38: =K15*(1+Dashboard!$P$11) | L38: =M38+F38 | M38: =M15*(1+Dashboard!$P$11) | N38: =((M38*D38)*12) | P38: =B38 | Q38: =C38 | R38: =D38 | S38: =E38 | T38: =F38 | U38: =((M38*R38)*12) | W38: =B38 | X38: =C38 | Y38: =D38 | Z38: =E38 | AA38: =F38 | AB38: =((H38*Y38)*12) | AD38: =B38 | AE38: =C38 | AF38: =D38 | AG38: =E38 | AH38: =F38 | AI38: =+MAX(U38,AB38) | AK38: =B38 | AL38: =C38 | AM38: =D38 | AN38: =E38 | AO38: =F38 | AP38: =IF(G38>0,MAX(U38,AB38),N38)
B39: =B16 | C39: =C16 | D39: =$D16 | E39: =E16 | F39: =F16*(1+Dashboard!$P$12) | G39: =G16*(1+Dashboard!$P$11) | H39: =+G39-F39 | I39: =I16*(1+Dashboard!$P$11) | J39: =I39-F39 | K39: =K16*(1+Dashboard!$P$11) | L39: =M39+F39 | M39: =M16*(1+Dashboard!$P$11) | N39: =((M39*D39)*12) | P39: =B39 | Q39: =C39 | R39: =D39 | S39: =E39 | T39: =F39 | U39: =((M39*R39)*12) | W39: =B39 | X39: =C39 | Y39: =D39 | Z39: =E39 | AA39: =F39 | AB39: =((H39*Y39)*12) | AD39: =B39 | AE39: =C39 | AF39: =D39 | AG39: =E39 | AH39: =F39 | AI39: =+MAX(U39,AB39) | AK39: =B39 | AL39: =C39 | AM39: =D39 | AN39: =E39 | AO39: =F39 | AP39: =IF(G39>0,MAX(U39,AB39),N39)
B40: =B17 | C40: =C17 | D40: =$D17 | E40: =E17 | F40: =F17*(1+Dashboard!$P$12) | G40: =G17*(1+Dashboard!$P$11) | H40: =+G40-F40 | I40: =I17*(1+Dashboard!$P$11) | J40: =I40-F40 | K40: =K17*(1+Dashboard!$P$11) | L40: =M40+F40 | M40: =M17*(1+Dashboard!$P$11) | N40: =((M40*D40)*12) | P40: =B40 | Q40: =C40 | R40: =D40 | S40: =E40 | T40: =F40 | U40: =((M40*R40)*12) | W40: =B40 | X40: =C40 | Y40: =D40 | Z40: =E40 | AA40: =F40 | AB40: =((H40*Y40)*12) | AD40: =B40 | AE40: =C40 | AF40: =D40 | AG40: =E40 | AH40: =F40 | AI40: =+MAX(U40,AB40) | AK40: =B40 | AL40: =C40 | AM40: =D40 | AN40: =E40 | AO40: =F40 | AP40: =IF(G40>0,MAX(U40,AB40),N40)
B41: =B18 | C41: =C18 | D41: =$D18 | E41: =E18 | F41: =F18*(1+Dashboard!$P$12) | G41: =G18*(1+Dashboard!$P$11) | H41: =+G41-F41 | I41: =I18*(1+Dashboard!$P$11) | J41: =I41-F41 | K41: =K18*(1+Dashboard!$P$11) | L41: =M41+F41 | M41: =M18*(1+Dashboard!$P$11) | N41: =((M41*D41)*12) | P41: =B41 | Q41: =C41 | R41: =D41 | S41: =E41 | T41: =F41 | U41: =((M41*R41)*12) | W41: =B41 | X41: =C41 | Y41: =D41 | Z41: =E41 | AA41: =F41 | AB41: =((H41*Y41)*12) | AD41: =B41 | AE41: =C41 | AF41: =D41 | AG41: =E41 | AH41: =F41 | AI41: =+MAX(U41,AB41) | AK41: =B41 | AL41: =C41 | AM41: =D41 | AN41: =E41 | AO41: =F41 | AP41: =IF(G41>0,MAX(U41,AB41),N41)
... B48: =B25 | C48: =C25 | D48: =$D25 | E48: =E25 | F48: =F25*(1+Dashboard!$P$12) | G48: =G25*(1+Dashboard!$P$11) | H48: =+G48-F48 | I48: =I25*(1+Dashboard!$P$11) | J48: =I48-F48 | K48: =K25*(1+Dashboard!$P$11) | L48: =M48+F48 | M48: =M25*(1+Dashboard!$P$11) | N48: =((M48*D48)*12) | P48: =B48 | Q48: =C48 | R48: =D48 | S48: =E48 | T48: =F48 | U48: =((M48*R48)*12) | W48: =B48 | X48: =C48 | Y48: =D48 | Z48: =E48 | AA48: =F48 | AB48: =((H48*Y48)*12) | AD48: =B48 | AE48: =C48 | AF48: =D48 | AG48: =E48 | AH48: =F48 | AI48: =+MAX(U48,AB48) | AK48: =B48 | AL48: =C48 | AM48: =D48 | AN48: =E48 | AO48: =F48 | AP48: =IF(G48>0,MAX(U48,AB48),N48)
B49: Total (Pre-Vacancy) | D49: =SUM(D30:D48) | E49: =+SUMPRODUCT(E30:E48,$D30:$D48) | F49: =+SUMPRODUCT(F30:F48,$D30:$D48) | G49: =+SUMPRODUCT(G30:G48,$D30:$D48) | H49: =+SUMPRODUCT(H30:H48,$D30:$D48) | I49: =+SUMPRODUCT(I30:I48,$D30:$D48) | J49: =+SUMPRODUCT(J30:J48,$D30:$D48) | K49: =+SUMPRODUCT(K30:K48,$D30:$D48) | L49: =+SUMPRODUCT(L30:L48,$D30:$D48) | M49: =+SUMPRODUCT(M30:M48,$D30:$D48) | N49: =SUM(N30:N48) | P49: Total (Pre-Vacancy) | R49: =SUM(R30:R48) | S49: =+SUMPRODUCT(S30:S48,$R30:$R48) | T49: =+SUMPRODUCT(T30:T48,$R30:$R48) | U49: =SUM(U30:U48) | W49: Total (Pre-Vacancy) | Y49: =SUM(Y30:Y48) | Z49: =+SUMPRODUCT(Z30:Z48,$Y30:$Y48) | AA49: =+SUMPRODUCT(AA30:AA48,$Y30:$Y48) | AB49: =SUM(AB30:AB48) | AD49: Total (Pre-Vacancy) | AF49: =SUM(AF30:AF48) | AG49: =+SUMPRODUCT(AG30:AG48,$AF30:$AF48) | AH49: =+SUMPRODUCT(AH30:AH48,$AF30:$AF48) | AI49: =SUM(AI30:AI48) | AK49: Total (Pre-Vacancy) | AM49: =SUM(AF30:AF48) | AN49: =+SUMPRODUCT(AG30:AG48,$AF30:$AF48) | AO49: =+SUMPRODUCT(AH30:AH48,$AF30:$AF48) | AP49: =SUM(AP30:AP48)
B51: Year 3 | P51: =+$B51 | W51: =+$B51 | AD51: =+$B51 | AK51: =+$B51
B52: Unit Type | C52: AMI / S8 | D52: # of Units | E52: Avg. SF | F52: Avg. Utilities | G52: Avg. Max LITHC | H52: Net LIHTC | I52: Avg. Max FMR | J52: Net FMR | K52: =+K29 | L52: Gross Rent | M52: Avg. Current Rent | N52: Yrly. Gross Income (Net Rent) | P52: Unit Type | Q52: AMI / S8 | R52: # of Units | S52: Avg. SF | T52: Avg. Utilities | U52: Max Current Vouchers | W52: Unit Type | X52: AMI / S8 | Y52: # of Units | Z52: Avg. SF | AA52: Avg. Utilities | AB52: Max NET LIHTC | AD52: Unit Type | AE52: AMI / S8 | AF52: # of Units | AG52: Avg. SF | AH52: Avg. Utilities | AI52: Max Current Vouchers + NET LIHTC | AK52: Unit Type | AL52: AMI / S8 | AM52: # of Units | AN52: Avg. SF | AO52: Avg. Utilities | AP52: Max Current Vouchers + NET LIHTC
B53: =B30 | C53: =C30 | D53: =$D30 | E53: =E30 | F53: =F30*(1+Dashboard!$P$12) | G53: =G30*(1+Dashboard!$P$11) | H53: =+G53-F53 | I53: =I30*(1+Dashboard!$P$11) | J53: =I53-F53 | K53: =K30*(1+Dashboard!$P$11) | L53: =M53+F53 | M53: =M30*(1+Dashboard!$P$11) | N53: =((M53*D53)*12) | P53: =B53 | Q53: =C53 | R53: =D53 | S53: =E53 | T53: =F53 | U53: =((M53*R53)*12) | W53: =B53 | X53: =C53 | Y53: =D53 | Z53: =E53 | AA53: =F53 | AB53: =((H53*Y53)*12) | AD53: =B53 | AE53: =C53 | AF53: =D53 | AG53: =E53 | AH53: =F53 | AI53: =+MAX(U53,AB53) | AK53: =B53 | AL53: =C53 | AM53: =D53 | AN53: =E53 | AO53: =F53 | AP53: =IF(G53>0,MAX(U53,AB53),N53)
B54: =B31 | C54: =C31 | D54: =$D31 | E54: =E31 | F54: =F31*(1+Dashboard!$P$12) | G54: =G31*(1+Dashboard!$P$11) | H54: =+G54-F54 | I54: =I31*(1+Dashboard!$P$11) | J54: =I54-F54 | K54: =K31*(1+Dashboard!$P$11) | L54: =M54+F54 | M54: =M31*(1+Dashboard!$P$11) | N54: =((M54*D54)*12) | P54: =B54 | Q54: =C54 | R54: =D54 | S54: =E54 | T54: =F54 | U54: =((M54*R54)*12) | W54: =B54 | X54: =C54 | Y54: =D54 | Z54: =E54 | AA54: =F54 | AB54: =((H54*Y54)*12) | AD54: =B54 | AE54: =C54 | AF54: =D54 | AG54: =E54 | AH54: =F54 | AI54: =+MAX(U54,AB54) | AK54: =B54 | AL54: =C54 | AM54: =D54 | AN54: =E54 | AO54: =F54 | AP54: =IF(G54>0,MAX(U54,AB54),N54)
B55: =B32 | C55: =C32 | D55: =$D32 | E55: =E32 | F55: =F32*(1+Dashboard!$P$12) | G55: =G32*(1+Dashboard!$P$11) | H55: =+G55-F55 | I55: =I32*(1+Dashboard!$P$11) | J55: =I55-F55 | K55: =K32*(1+Dashboard!$P$11) | L55: =M55+F55 | M55: =M32*(1+Dashboard!$P$11) | N55: =((M55*D55)*12) | P55: =B55 | Q55: =C55 | R55: =D55 | S55: =E55 | T55: =F55 | U55: =((M55*R55)*12) | W55: =B55 | X55: =C55 | Y55: =D55 | Z55: =E55 | AA55: =F55 | AB55: =((H55*Y55)*12) | AD55: =B55 | AE55: =C55 | AF55: =D55 | AG55: =E55 | AH55: =F55 | AI55: =+MAX(U55,AB55) | AK55: =B55 | AL55: =C55 | AM55: =D55 | AN55: =E55 | AO55: =F55 | AP55: =IF(G55>0,MAX(U55,AB55),N55)
B56: =B33 | C56: =C33 | D56: =$D33 | E56: =E33 | F56: =F33*(1+Dashboard!$P$12) | G56: =G33*(1+Dashboard!$P$11) | H56: =+G56-F56 | I56: =I33*(1+Dashboard!$P$11) | J56: =I56-F56 | K56: =K33*(1+Dashboard!$P$11) | L56: =M56+F56 | M56: =M33*(1+Dashboard!$P$11) | N56: =((M56*D56)*12) | P56: =B56 | Q56: =C56 | R56: =D56 | S56: =E56 | T56: =F56 | U56: =((M56*R56)*12) | W56: =B56 | X56: =C56 | Y56: =D56 | Z56: =E56 | AA56: =F56 | AB56: =((H56*Y56)*12) | AD56: =B56 | AE56: =C56 | AF56: =D56 | AG56: =E56 | AH56: =F56 | AI56: =+MAX(U56,AB56) | AK56: =B56 | AL56: =C56 | AM56: =D56 | AN56: =E56 | AO56: =F56 | AP56: =IF(G56>0,MAX(U56,AB56),N56)
B57: =B34 | C57: =C34 | D57: =$D34 | E57: =E34 | F57: =F34*(1+Dashboard!$P$12) | G57: =G34*(1+Dashboard!$P$11) | H57: =+G57-F57 | I57: =I34*(1+Dashboard!$P$11) | J57: =I57-F57 | K57: =K34*(1+Dashboard!$P$11) | L57: =M57+F57 | M57: =M34*(1+Dashboard!$P$11) | N57: =((M57*D57)*12) | P57: =B57 | Q57: =C57 | R57: =D57 | S57: =E57 | T57: =F57 | U57: =((M57*R57)*12) | W57: =B57 | X57: =C57 | Y57: =D57 | Z57: =E57 | AA57: =F57 | AB57: =((H57*Y57)*12) | AD57: =B57 | AE57: =C57 | AF57: =D57 | AG57: =E57 | AH57: =F57 | AI57: =+MAX(U57,AB57) | AK57: =B57 | AL57: =C57 | AM57: =D57 | AN57: =E57 | AO57: =F57 | AP57: =IF(G57>0,MAX(U57,AB57),N57)
B58: =B35 | C58: =C35 | D58: =$D35 | E58: =E35 | F58: =F35*(1+Dashboard!$P$12) | G58: =G35*(1+Dashboard!$P$11) | H58: =+G58-F58 | I58: =I35*(1+Dashboard!$P$11) | J58: =I58-F58 | K58: =K35*(1+Dashboard!$P$11) | L58: =M58+F58 | M58: =M35*(1+Dashboard!$P$11) | N58: =((M58*D58)*12) | P58: =B58 | Q58: =C58 | R58: =D58 | S58: =E58 | T58: =F58 | U58: =((M58*R58)*12) | W58: =B58 | X58: =C58 | Y58: =D58 | Z58: =E58 | AA58: =F58 | AB58: =((H58*Y58)*12) | AD58: =B58 | AE58: =C58 | AF58: =D58 | AG58: =E58 | AH58: =F58 | AI58: =+MAX(U58,AB58) | AK58: =B58 | AL58: =C58 | AM58: =D58 | AN58: =E58 | AO58: =F58 | AP58: =IF(G58>0,MAX(U58,AB58),N58)
B59: =B36 | C59: =C36 | D59: =$D36 | E59: =E36 | F59: =F36*(1+Dashboard!$P$12) | G59: =G36*(1+Dashboard!$P$11) | H59: =+G59-F59 | I59: =I36*(1+Dashboard!$P$11) | J59: =I59-F59 | K59: =K36*(1+Dashboard!$P$11) | L59: =M59+F59 | M59: =M36*(1+Dashboard!$P$11) | N59: =((M59*D59)*12) | P59: =B59 | Q59: =C59 | R59: =D59 | S59: =E59 | T59: =F59 | U59: =((M59*R59)*12) | W59: =B59 | X59: =C59 | Y59: =D59 | Z59: =E59 | AA59: =F59 | AB59: =((H59*Y59)*12) | AD59: =B59 | AE59: =C59 | AF59: =D59 | AG59: =E59 | AH59: =F59 | AI59: =+MAX(U59,AB59) | AK59: =B59 | AL59: =C59 | AM59: =D59 | AN59: =E59 | AO59: =F59 | AP59: =IF(G59>0,MAX(U59,AB59),N59)
B60: =B37 | C60: =C37 | D60: =$D37 | E60: =E37 | F60: =F37*(1+Dashboard!$P$12) | G60: =G37*(1+Dashboard!$P$11) | H60: =+G60-F60 | I60: =I37*(1+Dashboard!$P$11) | J60: =I60-F60 | K60: =K37*(1+Dashboard!$P$11) | L60: =M60+F60 | M60: =M37*(1+Dashboard!$P$11) | N60: =((M60*D60)*12) | P60: =B60 | Q60: =C60 | R60: =D60 | S60: =E60 | T60: =F60 | U60: =((M60*R60)*12) | W60: =B60 | X60: =C60 | Y60: =D60 | Z60: =E60 | AA60: =F60 | AB60: =((H60*Y60)*12) | AD60: =B60 | AE60: =C60 | AF60: =D60 | AG60: =E60 | AH60: =F60 | AI60: =+MAX(U60,AB60) | AK60: =B60 | AL60: =C60 | AM60: =D60 | AN60: =E60 | AO60: =F60 | AP60: =IF(G60>0,MAX(U60,AB60),N60)
B61: =B38 | C61: =C38 | D61: =$D38 | E61: =E38 | F61: =F38*(1+Dashboard!$P$12) | G61: =G38*(1+Dashboard!$P$11) | H61: =+G61-F61 | I61: =I38*(1+Dashboard!$P$11) | J61: =I61-F61 | K61: =K38*(1+Dashboard!$P$11) | L61: =M61+F61 | M61: =M38*(1+Dashboard!$P$11) | N61: =((M61*D61)*12) | P61: =B61 | Q61: =C61 | R61: =D61 | S61: =E61 | T61: =F61 | U61: =((M61*R61)*12) | W61: =B61 | X61: =C61 | Y61: =D61 | Z61: =E61 | AA61: =F61 | AB61: =((H61*Y61)*12) | AD61: =B61 | AE61: =C61 | AF61: =D61 | AG61: =E61 | AH61: =F61 | AI61: =+MAX(U61,AB61) | AK61: =B61 | AL61: =C61 | AM61: =D61 | AN61: =E61 | AO61: =F61 | AP61: =IF(G61>0,MAX(U61,AB61),N61)
B62: =B39 | C62: =C39 | D62: =$D39 | E62: =E39 | F62: =F39*(1+Dashboard!$P$12) | G62: =G39*(1+Dashboard!$P$11) | H62: =+G62-F62 | I62: =I39*(1+Dashboard!$P$11) | J62: =I62-F62 | K62: =K39*(1+Dashboard!$P$11) | L62: =M62+F62 | M62: =M39*(1+Dashboard!$P$11) | N62: =((M62*D62)*12) | P62: =B62 | Q62: =C62 | R62: =D62 | S62: =E62 | T62: =F62 | U62: =((M62*R62)*12) | W62: =B62 | X62: =C62 | Y62: =D62 | Z62: =E62 | AA62: =F62 | AB62: =((H62*Y62)*12) | AD62: =B62 | AE62: =C62 | AF62: =D62 | AG62: =E62 | AH62: =F62 | AI62: =+MAX(U62,AB62) | AK62: =B62 | AL62: =C62 | AM62: =D62 | AN62: =E62 | AO62: =F62 | AP62: =IF(G62>0,MAX(U62,AB62),N62)
B63: =B40 | C63: =C40 | D63: =$D40 | E63: =E40 | F63: =F40*(1+Dashboard!$P$12) | G63: =G40*(1+Dashboard!$P$11) | H63: =+G63-F63 | I63: =I40*(1+Dashboard!$P$11) | J63: =I63-F63 | K63: =K40*(1+Dashboard!$P$11) | L63: =M63+F63 | M63: =M40*(1+Dashboard!$P$11) | N63: =((M63*D63)*12) | P63: =B63 | Q63: =C63 | R63: =D63 | S63: =E63 | T63: =F63 | U63: =((M63*R63)*12) | W63: =B63 | X63: =C63 | Y63: =D63 | Z63: =E63 | AA63: =F63 | AB63: =((H63*Y63)*12) | AD63: =B63 | AE63: =C63 | AF63: =D63 | AG63: =E63 | AH63: =F63 | AI63: =+MAX(U63,AB63) | AK63: =B63 | AL63: =C63 | AM63: =D63 | AN63: =E63 | AO63: =F63 | AP63: =IF(G63>0,MAX(U63,AB63),N63)
B64: =B41 | C64: =C41 | D64: =$D41 | E64: =E41 | F64: =F41*(1+Dashboard!$P$12) | G64: =G41*(1+Dashboard!$P$11) | H64: =+G64-F64 | I64: =I41*(1+Dashboard!$P$11) | J64: =I64-F64 | K64: =K41*(1+Dashboard!$P$11) | L64: =M64+F64 | M64: =M41*(1+Dashboard!$P$11) | N64: =((M64*D64)*12) | P64: =B64 | Q64: =C64 | R64: =D64 | S64: =E64 | T64: =F64 | U64: =((M64*R64)*12) | W64: =B64 | X64: =C64 | Y64: =D64 | Z64: =E64 | AA64: =F64 | AB64: =((H64*Y64)*12) | AD64: =B64 | AE64: =C64 | AF64: =D64 | AG64: =E64 | AH64: =F64 | AI64: =+MAX(U64,AB64) | AK64: =B64 | AL64: =C64 | AM64: =D64 | AN64: =E64 | AO64: =F64 | AP64: =IF(G64>0,MAX(U64,AB64),N64)
... B71: =B48 | C71: =C48 | D71: =$D48 | E71: =E48 | F71: =F48*(1+Dashboard!$P$12) | G71: =G48*(1+Dashboard!$P$11) | H71: =+G71-F71 | I71: =I48*(1+Dashboard!$P$11) | J71: =I71-F71 | K71: =K48*(1+Dashboard!$P$11) | L71: =M71+F71 | M71: =M48*(1+Dashboard!$P$11) | N71: =((M71*D71)*12) | P71: =B71 | Q71: =C71 | R71: =D71 | S71: =E71 | T71: =F71 | U71: =((M71*R71)*12) | W71: =B71 | X71: =C71 | Y71: =D71 | Z71: =E71 | AA71: =F71 | AB71: =((H71*Y71)*12) | AD71: =B71 | AE71: =C71 | AF71: =D71 | AG71: =E71 | AH71: =F71 | AI71: =+MAX(U71,AB71) | AK71: =B71 | AL71: =C71 | AM71: =D71 | AN71: =E71 | AO71: =F71 | AP71: =IF(G71>0,MAX(U71,AB71),N71)
B72: Total (Pre-Vacancy) | D72: =SUM(D53:D71) | E72: =+SUMPRODUCT(E53:E71,$D53:$D71) | F72: =+SUMPRODUCT(F53:F71,$D53:$D71) | G72: =+SUMPRODUCT(G53:G71,$D53:$D71) | H72: =+SUMPRODUCT(H53:H71,$D53:$D71) | I72: =+SUMPRODUCT(I53:I71,$D53:$D71) | J72: =+SUMPRODUCT(J53:J71,$D53:$D71) | K72: =+SUMPRODUCT(K53:K71,$D53:$D71) | L72: =+SUMPRODUCT(L53:L71,$D53:$D71) | M72: =+SUMPRODUCT(M53:M71,$D53:$D71) | N72: =SUM(N53:N71) | P72: Total (Pre-Vacancy) | R72: =SUM(R53:R71) | S72: =+SUMPRODUCT(S53:S71,$R53:$R71) | T72: =+SUMPRODUCT(T53:T71,$R53:$R71) | U72: =SUM(U53:U71) | W72: Total (Pre-Vacancy) | Y72: =SUM(Y53:Y71) | Z72: =+SUMPRODUCT(Z53:Z71,$Y53:$Y71) | AA72: =+SUMPRODUCT(AA53:AA71,$Y53:$Y71) | AB72: =SUM(AB53:AB71) | AD72: Total (Pre-Vacancy) | AF72: =SUM(AF53:AF71) | AG72: =+SUMPRODUCT(AG53:AG71,$AF53:$AF71) | AH72: =+SUMPRODUCT(AH53:AH71,$AF53:$AF71) | AI72: =SUM(AI53:AI71) | AK72: Total (Pre-Vacancy) | AM72: =SUM(AF53:AF71) | AN72: =+SUMPRODUCT(AG53:AG71,$AF53:$AF71) | AO72: =+SUMPRODUCT(AH53:AH71,$AF53:$AF71) | AP72: =SUM(AP53:AP71)
B74: Year 4 | P74: =+$B74 | W74: =+$B74 | AD74: =+$B74 | AK74: =+$B74
B75: Unit Type | C75: AMI / S8 | D75: # of Units | E75: Avg. SF | F75: Avg. Utilities | G75: Avg. Max LITHC | H75: Net LIHTC | I75: Avg. Max FMR | J75: Net FMR | K75: =+K52 | L75: Gross Rent | M75: Avg. Current Rent | N75: Yrly. Gross Income (Net Rent) | P75: Unit Type | Q75: AMI / S8 | R75: # of Units | S75: Avg. SF | T75: Avg. Utilities | U75: Max Current Vouchers | W75: Unit Type | X75: AMI / S8 | Y75: # of Units | Z75: Avg. SF | AA75: Avg. Utilities | AB75: Max NET LIHTC | AD75: Unit Type | AE75: AMI / S8 | AF75: # of Units | AG75: Avg. SF | AH75: Avg. Utilities | AI75: Max Current Vouchers + NET LIHTC | AK75: Unit Type | AL75: AMI / S8 | AM75: # of Units | AN75: Avg. SF | AO75: Avg. Utilities | AP75: Max Current Vouchers + NET LIHTC
B76: =B53 | C76: =C53 | D76: =$D53 | E76: =E53 | F76: =F53*(1+Dashboard!$P$12) | G76: =G53*(1+Dashboard!$P$11) | H76: =+G76-F76 | I76: =I53*(1+Dashboard!$P$11) | J76: =I76-F76 | K76: =K53*(1+Dashboard!$P$11) | L76: =M76+F76 | M76: =M53*(1+Dashboard!$P$11) | N76: =((M76*D76)*12) | P76: =B76 | Q76: =C76 | R76: =D76 | S76: =E76 | T76: =F76 | U76: =((M76*R76)*12) | W76: =B76 | X76: =C76 | Y76: =D76 | Z76: =E76 | AA76: =F76 | AB76: =((H76*Y76)*12) | AD76: =B76 | AE76: =C76 | AF76: =D76 | AG76: =E76 | AH76: =F76 | AI76: =+MAX(U76,AB76) | AK76: =B76 | AL76: =C76 | AM76: =D76 | AN76: =E76 | AO76: =F76 | AP76: =IF(G76>0,MAX(U76,AB76),N76)
B77: =B54 | C77: =C54 | D77: =$D54 | E77: =E54 | F77: =F54*(1+Dashboard!$P$12) | G77: =G54*(1+Dashboard!$P$11) | H77: =+G77-F77 | I77: =I54*(1+Dashboard!$P$11) | J77: =I77-F77 | K77: =K54*(1+Dashboard!$P$11) | L77: =M77+F77 | M77: =M54*(1+Dashboard!$P$11) | N77: =((M77*D77)*12) | P77: =B77 | Q77: =C77 | R77: =D77 | S77: =E77 | T77: =F77 | U77: =((M77*R77)*12) | W77: =B77 | X77: =C77 | Y77: =D77 | Z77: =E77 | AA77: =F77 | AB77: =((H77*Y77)*12) | AD77: =B77 | AE77: =C77 | AF77: =D77 | AG77: =E77 | AH77: =F77 | AI77: =+MAX(U77,AB77) | AK77: =B77 | AL77: =C77 | AM77: =D77 | AN77: =E77 | AO77: =F77 | AP77: =IF(G77>0,MAX(U77,AB77),N77)
B78: =B55 | C78: =C55 | D78: =$D55 | E78: =E55 | F78: =F55*(1+Dashboard!$P$12) | G78: =G55*(1+Dashboard!$P$11) | H78: =+G78-F78 | I78: =I55*(1+Dashboard!$P$11) | J78: =I78-F78 | K78: =K55*(1+Dashboard!$P$11) | L78: =M78+F78 | M78: =M55*(1+Dashboard!$P$11) | N78: =((M78*D78)*12) | P78: =B78 | Q78: =C78 | R78: =D78 | S78: =E78 | T78: =F78 | U78: =((M78*R78)*12) | W78: =B78 | X78: =C78 | Y78: =D78 | Z78: =E78 | AA78: =F78 | AB78: =((H78*Y78)*12) | AD78: =B78 | AE78: =C78 | AF78: =D78 | AG78: =E78 | AH78: =F78 | AI78: =+MAX(U78,AB78) | AK78: =B78 | AL78: =C78 | AM78: =D78 | AN78: =E78 | AO78: =F78 | AP78: =IF(G78>0,MAX(U78,AB78),N78)
B79: =B56 | C79: =C56 | D79: =$D56 | E79: =E56 | F79: =F56*(1+Dashboard!$P$12) | G79: =G56*(1+Dashboard!$P$11) | H79: =+G79-F79 | I79: =I56*(1+Dashboard!$P$11) | J79: =I79-F79 | K79: =K56*(1+Dashboard!$P$11) | L79: =M79+F79 | M79: =M56*(1+Dashboard!$P$11) | N79: =((M79*D79)*12) | P79: =B79 | Q79: =C79 | R79: =D79 | S79: =E79 | T79: =F79 | U79: =((M79*R79)*12) | W79: =B79 | X79: =C79 | Y79: =D79 | Z79: =E79 | AA79: =F79 | AB79: =((H79*Y79)*12) | AD79: =B79 | AE79: =C79 | AF79: =D79 | AG79: =E79 | AH79: =F79 | AI79: =+MAX(U79,AB79) | AK79: =B79 | AL79: =C79 | AM79: =D79 | AN79: =E79 | AO79: =F79 | AP79: =IF(G79>0,MAX(U79,AB79),N79)
B80: =B57 | C80: =C57 | D80: =$D57 | E80: =E57 | F80: =F57*(1+Dashboard!$P$12) | G80: =G57*(1+Dashboard!$P$11) | H80: =+G80-F80 | I80: =I57*(1+Dashboard!$P$11) | J80: =I80-F80 | K80: =K57*(1+Dashboard!$P$11) | L80: =M80+F80 | M80: =M57*(1+Dashboard!$P$11) | N80: =((M80*D80)*12) | P80: =B80 | Q80: =C80 | R80: =D80 | S80: =E80 | T80: =F80 | U80: =((M80*R80)*12) | W80: =B80 | X80: =C80 | Y80: =D80 | Z80: =E80 | AA80: =F80 | AB80: =((H80*Y80)*12) | AD80: =B80 | AE80: =C80 | AF80: =D80 | AG80: =E80 | AH80: =F80 | AI80: =+MAX(U80,AB80) | AK80: =B80 | AL80: =C80 | AM80: =D80 | AN80: =E80 | AO80: =F80 | AP80: =IF(G80>0,MAX(U80,AB80),N80)
B81: =B58 | C81: =C58 | D81: =$D58 | E81: =E58 | F81: =F58*(1+Dashboard!$P$12) | G81: =G58*(1+Dashboard!$P$11) | H81: =+G81-F81 | I81: =I58*(1+Dashboard!$P$11) | J81: =I81-F81 | K81: =K58*(1+Dashboard!$P$11) | L81: =M81+F81 | M81: =M58*(1+Dashboard!$P$11) | N81: =((M81*D81)*12) | P81: =B81 | Q81: =C81 | R81: =D81 | S81: =E81 | T81: =F81 | U81: =((M81*R81)*12) | W81: =B81 | X81: =C81 | Y81: =D81 | Z81: =E81 | AA81: =F81 | AB81: =((H81*Y81)*12) | AD81: =B81 | AE81: =C81 | AF81: =D81 | AG81: =E81 | AH81: =F81 | AI81: =+MAX(U81,AB81) | AK81: =B81 | AL81: =C81 | AM81: =D81 | AN81: =E81 | AO81: =F81 | AP81: =IF(G81>0,MAX(U81,AB81),N81)
B82: =B59 | C82: =C59 | D82: =$D59 | E82: =E59 | F82: =F59*(1+Dashboard!$P$12) | G82: =G59*(1+Dashboard!$P$11) | H82: =+G82-F82 | I82: =I59*(1+Dashboard!$P$11) | J82: =I82-F82 | K82: =K59*(1+Dashboard!$P$11) | L82: =M82+F82 | M82: =M59*(1+Dashboard!$P$11) | N82: =((M82*D82)*12) | P82: =B82 | Q82: =C82 | R82: =D82 | S82: =E82 | T82: =F82 | U82: =((M82*R82)*12) | W82: =B82 | X82: =C82 | Y82: =D82 | Z82: =E82 | AA82: =F82 | AB82: =((H82*Y82)*12) | AD82: =B82 | AE82: =C82 | AF82: =D82 | AG82: =E82 | AH82: =F82 | AI82: =+MAX(U82,AB82) | AK82: =B82 | AL82: =C82 | AM82: =D82 | AN82: =E82 | AO82: =F82 | AP82: =IF(G82>0,MAX(U82,AB82),N82)
B83: =B60 | C83: =C60 | D83: =$D60 | E83: =E60 | F83: =F60*(1+Dashboard!$P$12) | G83: =G60*(1+Dashboard!$P$11) | H83: =+G83-F83 | I83: =I60*(1+Dashboard!$P$11) | J83: =I83-F83 | K83: =K60*(1+Dashboard!$P$11) | L83: =M83+F83 | M83: =M60*(1+Dashboard!$P$11) | N83: =((M83*D83)*12) | P83: =B83 | Q83: =C83 | R83: =D83 | S83: =E83 | T83: =F83 | U83: =((M83*R83)*12) | W83: =B83 | X83: =C83 | Y83: =D83 | Z83: =E83 | AA83: =F83 | AB83: =((H83*Y83)*12) | AD83: =B83 | AE83: =C83 | AF83: =D83 | AG83: =E83 | AH83: =F83 | AI83: =+MAX(U83,AB83) | AK83: =B83 | AL83: =C83 | AM83: =D83 | AN83: =E83 | AO83: =F83 | AP83: =IF(G83>0,MAX(U83,AB83),N83)
B84: =B61 | C84: =C61 | D84: =$D61 | E84: =E61 | F84: =F61*(1+Dashboard!$P$12) | G84: =G61*(1+Dashboard!$P$11) | H84: =+G84-F84 | I84: =I61*(1+Dashboard!$P$11) | J84: =I84-F84 | K84: =K61*(1+Dashboard!$P$11) | L84: =M84+F84 | M84: =M61*(1+Dashboard!$P$11) | N84: =((M84*D84)*12) | P84: =B84 | Q84: =C84 | R84: =D84 | S84: =E84 | T84: =F84 | U84: =((M84*R84)*12) | W84: =B84 | X84: =C84 | Y84: =D84 | Z84: =E84 | AA84: =F84 | AB84: =((H84*Y84)*12) | AD84: =B84 | AE84: =C84 | AF84: =D84 | AG84: =E84 | AH84: =F84 | AI84: =+MAX(U84,AB84) | AK84: =B84 | AL84: =C84 | AM84: =D84 | AN84: =E84 | AO84: =F84 | AP84: =IF(G84>0,MAX(U84,AB84),N84)
B85: =B62 | C85: =C62 | D85: =$D62 | E85: =E62 | F85: =F62*(1+Dashboard!$P$12) | G85: =G62*(1+Dashboard!$P$11) | H85: =+G85-F85 | I85: =I62*(1+Dashboard!$P$11) | J85: =I85-F85 | K85: =K62*(1+Dashboard!$P$11) | L85: =M85+F85 | M85: =M62*(1+Dashboard!$P$11) | N85: =((M85*D85)*12) | P85: =B85 | Q85: =C85 | R85: =D85 | S85: =E85 | T85: =F85 | U85: =((M85*R85)*12) | W85: =B85 | X85: =C85 | Y85: =D85 | Z85: =E85 | AA85: =F85 | AB85: =((H85*Y85)*12) | AD85: =B85 | AE85: =C85 | AF85: =D85 | AG85: =E85 | AH85: =F85 | AI85: =+MAX(U85,AB85) | AK85: =B85 | AL85: =C85 | AM85: =D85 | AN85: =E85 | AO85: =F85 | AP85: =IF(G85>0,MAX(U85,AB85),N85)
B86: =B63 | C86: =C63 | D86: =$D63 | E86: =E63 | F86: =F63*(1+Dashboard!$P$12) | G86: =G63*(1+Dashboard!$P$11) | H86: =+G86-F86 | I86: =I63*(1+Dashboard!$P$11) | J86: =I86-F86 | K86: =K63*(1+Dashboard!$P$11) | L86: =M86+F86 | M86: =M63*(1+Dashboard!$P$11) | N86: =((M86*D86)*12) | P86: =B86 | Q86: =C86 | R86: =D86 | S86: =E86 | T86: =F86 | U86: =((M86*R86)*12) | W86: =B86 | X86: =C86 | Y86: =D86 | Z86: =E86 | AA86: =F86 | AB86: =((H86*Y86)*12) | AD86: =B86 | AE86: =C86 | AF86: =D86 | AG86: =E86 | AH86: =F86 | AI86: =+MAX(U86,AB86) | AK86: =B86 | AL86: =C86 | AM86: =D86 | AN86: =E86 | AO86: =F86 | AP86: =IF(G86>0,MAX(U86,AB86),N86)
B87: =B64 | C87: =C64 | D87: =$D64 | E87: =E64 | F87: =F64*(1+Dashboard!$P$12) | G87: =G64*(1+Dashboard!$P$11) | H87: =+G87-F87 | I87: =I64*(1+Dashboard!$P$11) | J87: =I87-F87 | K87: =K64*(1+Dashboard!$P$11) | L87: =M87+F87 | M87: =M64*(1+Dashboard!$P$11) | N87: =((M87*D87)*12) | P87: =B87 | Q87: =C87 | R87: =D87 | S87: =E87 | T87: =F87 | U87: =((M87*R87)*12) | W87: =B87 | X87: =C87 | Y87: =D87 | Z87: =E87 | AA87: =F87 | AB87: =((H87*Y87)*12) | AD87: =B87 | AE87: =C87 | AF87: =D87 | AG87: =E87 | AH87: =F87 | AI87: =+MAX(U87,AB87) | AK87: =B87 | AL87: =C87 | AM87: =D87 | AN87: =E87 | AO87: =F87 | AP87: =IF(G87>0,MAX(U87,AB87),N87)
... B94: =B71 | C94: =C71 | D94: =$D71 | E94: =E71 | F94: =F71*(1+Dashboard!$P$12) | G94: =G71*(1+Dashboard!$P$11) | H94: =+G94-F94 | I94: =I71*(1+Dashboard!$P$11) | J94: =I94-F94 | K94: =K71*(1+Dashboard!$P$11) | L94: =M94+F94 | M94: =M71*(1+Dashboard!$P$11) | N94: =((M94*D94)*12) | P94: =B94 | Q94: =C94 | R94: =D94 | S94: =E94 | T94: =F94 | U94: =((M94*R94)*12) | W94: =B94 | X94: =C94 | Y94: =D94 | Z94: =E94 | AA94: =F94 | AB94: =((H94*Y94)*12) | AD94: =B94 | AE94: =C94 | AF94: =D94 | AG94: =E94 | AH94: =F94 | AI94: =+MAX(U94,AB94) | AK94: =B94 | AL94: =C94 | AM94: =D94 | AN94: =E94 | AO94: =F94 | AP94: =IF(G94>0,MAX(U94,AB94),N94)
B95: Total (Pre-Vacancy) | D95: =SUM(D76:D94) | E95: =+SUMPRODUCT(E76:E94,$D76:$D94) | F95: =+SUMPRODUCT(F76:F94,$D76:$D94) | G95: =+SUMPRODUCT(G76:G94,$D76:$D94) | H95: =+SUMPRODUCT(H76:H94,$D76:$D94) | I95: =+SUMPRODUCT(I76:I94,$D76:$D94) | J95: =+SUMPRODUCT(J76:J94,$D76:$D94) | K95: =+SUMPRODUCT(K76:K94,$D76:$D94) | L95: =+SUMPRODUCT(L76:L94,$D76:$D94) | M95: =+SUMPRODUCT(M76:M94,$D76:$D94) | N95: =SUM(N76:N94) | P95: Total (Pre-Vacancy) | R95: =SUM(R76:R94) | S95: =+SUMPRODUCT(S76:S94,$R76:$R94) | T95: =+SUMPRODUCT(T76:T94,$R76:$R94) | U95: =SUM(U76:U94) | W95: Total (Pre-Vacancy) | Y95: =SUM(Y76:Y94) | Z95: =+SUMPRODUCT(Z76:Z94,$Y76:$Y94) | AA95: =+SUMPRODUCT(AA76:AA94,$Y76:$Y94) | AB95: =SUM(AB76:AB94) | AD95: Total (Pre-Vacancy) | AF95: =SUM(AF76:AF94) | AG95: =+SUMPRODUCT(AG76:AG94,$AF76:$AF94) | AH95: =+SUMPRODUCT(AH76:AH94,$AF76:$AF94) | AI95: =SUM(AI76:AI94) | AK95: Total (Pre-Vacancy) | AM95: =SUM(AF76:AF94) | AN95: =+SUMPRODUCT(AG76:AG94,$AF76:$AF94) | AO95: =+SUMPRODUCT(AH76:AH94,$AF76:$AF94) | AP95: =SUM(AP76:AP94)
B97: Year 5 | P97: =+$B97 | W97: =+$B97 | AD97: =+$B97 | AK97: =+$B97
B98: Unit Type | C98: AMI / S8 | D98: # of Units | E98: Avg. SF | F98: Avg. Utilities | G98: Avg. Max LITHC | H98: Net LIHTC | I98: Avg. Max FMR | J98: Net FMR | K98: =+K75 | L98: Gross Rent | M98: Avg. Current Rent | N98: Yrly. Gross Income (Net Rent) | P98: Unit Type | Q98: AMI / S8 | R98: # of Units | S98: Avg. SF | T98: Avg. Utilities | U98: Max Current Vouchers | W98: Unit Type | X98: AMI / S8 | Y98: # of Units | Z98: Avg. SF | AA98: Avg. Utilities | AB98: Max NET LIHTC | AD98: Unit Type | AE98: AMI / S8 | AF98: # of Units | AG98: Avg. SF | AH98: Avg. Utilities | AI98: Max Current Vouchers + NET LIHTC | AK98: Unit Type | AL98: AMI / S8 | AM98: # of Units | AN98: Avg. SF | AO98: Avg. Utilities | AP98: Max Current Vouchers + NET LIHTC
B99: =B76 | C99: =C76 | D99: =$D76 | E99: =E76 | F99: =F76*(1+Dashboard!$P$12) | G99: =G76*(1+Dashboard!$P$11) | H99: =+G99-F99 | I99: =I76*(1+Dashboard!$P$11) | J99: =I99-F99 | K99: =K76*(1+Dashboard!$P$11) | L99: =M99+F99 | M99: =M76*(1+Dashboard!$P$11) | N99: =((M99*D99)*12) | P99: =B99 | Q99: =C99 | R99: =D99 | S99: =E99 | T99: =F99 | U99: =((M99*R99)*12) | W99: =B99 | X99: =C99 | Y99: =D99 | Z99: =E99 | AA99: =F99 | AB99: =((H99*Y99)*12) | AD99: =B99 | AE99: =C99 | AF99: =D99 | AG99: =E99 | AH99: =F99 | AI99: =+MAX(U99,AB99) | AK99: =B99 | AL99: =C99 | AM99: =D99 | AN99: =E99 | AO99: =F99 | AP99: =IF(G99>0,MAX(U99,AB99),N99)
B100: =B77 | C100: =C77 | D100: =$D77 | E100: =E77 | F100: =F77*(1+Dashboard!$P$12) | G100: =G77*(1+Dashboard!$P$11) | H100: =+G100-F100 | I100: =I77*(1+Dashboard!$P$11) | J100: =I100-F100 | K100: =K77*(1+Dashboard!$P$11) | L100: =M100+F100 | M100: =M77*(1+Dashboard!$P$11) | N100: =((M100*D100)*12) | P100: =B100 | Q100: =C100 | R100: =D100 | S100: =E100 | T100: =F100 | U100: =((M100*R100)*12) | W100: =B100 | X100: =C100 | Y100: =D100 | Z100: =E100 | AA100: =F100 | AB100: =((H100*Y100)*12) | AD100: =B100 | AE100: =C100 | AF100: =D100 | AG100: =E100 | AH100: =F100 | AI100: =+MAX(U100,AB100) | AK100: =B100 | AL100: =C100 | AM100: =D100 | AN100: =E100 | AO100: =F100 | AP100: =IF(G100>0,MAX(U100,AB100),N100)
B101: =B78 | C101: =C78 | D101: =$D78 | E101: =E78 | F101: =F78*(1+Dashboard!$P$12) | G101: =G78*(1+Dashboard!$P$11) | H101: =+G101-F101 | I101: =I78*(1+Dashboard!$P$11) | J101: =I101-F101 | K101: =K78*(1+Dashboard!$P$11) | L101: =M101+F101 | M101: =M78*(1+Dashboard!$P$11) | N101: =((M101*D101)*12) | P101: =B101 | Q101: =C101 | R101: =D101 | S101: =E101 | T101: =F101 | U101: =((M101*R101)*12) | W101: =B101 | X101: =C101 | Y101: =D101 | Z101: =E101 | AA101: =F101 | AB101: =((H101*Y101)*12) | AD101: =B101 | AE101: =C101 | AF101: =D101 | AG101: =E101 | AH101: =F101 | AI101: =+MAX(U101,AB101) | AK101: =B101 | AL101: =C101 | AM101: =D101 | AN101: =E101 | AO101: =F101 | AP101: =IF(G101>0,MAX(U101,AB101),N101)
B102: =B79 | C102: =C79 | D102: =$D79 | E102: =E79 | F102: =F79*(1+Dashboard!$P$12) | G102: =G79*(1+Dashboard!$P$11) | H102: =+G102-F102 | I102: =I79*(1+Dashboard!$P$11) | J102: =I102-F102 | K102: =K79*(1+Dashboard!$P$11) | L102: =M102+F102 | M102: =M79*(1+Dashboard!$P$11) | N102: =((M102*D102)*12) | P102: =B102 | Q102: =C102 | R102: =D102 | S102: =E102 | T102: =F102 | U102: =((M102*R102)*12) | W102: =B102 | X102: =C102 | Y102: =D102 | Z102: =E102 | AA102: =F102 | AB102: =((H102*Y102)*12) | AD102: =B102 | AE102: =C102 | AF102: =D102 | AG102: =E102 | AH102: =F102 | AI102: =+MAX(U102,AB102) | AK102: =B102 | AL102: =C102 | AM102: =D102 | AN102: =E102 | AO102: =F102 | AP102: =IF(G102>0,MAX(U102,AB102),N102)
B103: =B80 | C103: =C80 | D103: =$D80 | E103: =E80 | F103: =F80*(1+Dashboard!$P$12) | G103: =G80*(1+Dashboard!$P$11) | H103: =+G103-F103 | I103: =I80*(1+Dashboard!$P$11) | J103: =I103-F103 | K103: =K80*(1+Dashboard!$P$11) | L103: =M103+F103 | M103: =M80*(1+Dashboard!$P$11) | N103: =((M103*D103)*12) | P103: =B103 | Q103: =C103 | R103: =D103 | S103: =E103 | T103: =F103 | U103: =((M103*R103)*12) | W103: =B103 | X103: =C103 | Y103: =D103 | Z103: =E103 | AA103: =F103 | AB103: =((H103*Y103)*12) | AD103: =B103 | AE103: =C103 | AF103: =D103 | AG103: =E103 | AH103: =F103 | AI103: =+MAX(U103,AB103) | AK103: =B103 | AL103: =C103 | AM103: =D103 | AN103: =E103 | AO103: =F103 | AP103: =IF(G103>0,MAX(U103,AB103),N103)
B104: =B81 | C104: =C81 | D104: =$D81 | E104: =E81 | F104: =F81*(1+Dashboard!$P$12) | G104: =G81*(1+Dashboard!$P$11) | H104: =+G104-F104 | I104: =I81*(1+Dashboard!$P$11) | J104: =I104-F104 | K104: =K81*(1+Dashboard!$P$11) | L104: =M104+F104 | M104: =M81*(1+Dashboard!$P$11) | N104: =((M104*D104)*12) | P104: =B104 | Q104: =C104 | R104: =D104 | S104: =E104 | T104: =F104 | U104: =((M104*R104)*12) | W104: =B104 | X104: =C104 | Y104: =D104 | Z104: =E104 | AA104: =F104 | AB104: =((H104*Y104)*12) | AD104: =B104 | AE104: =C104 | AF104: =D104 | AG104: =E104 | AH104: =F104 | AI104: =+MAX(U104,AB104) | AK104: =B104 | AL104: =C104 | AM104: =D104 | AN104: =E104 | AO104: =F104 | AP104: =IF(G104>0,MAX(U104,AB104),N104)
B105: =B82 | C105: =C82 | D105: =$D82 | E105: =E82 | F105: =F82*(1+Dashboard!$P$12) | G105: =G82*(1+Dashboard!$P$11) | H105: =+G105-F105 | I105: =I82*(1+Dashboard!$P$11) | J105: =I105-F105 | K105: =K82*(1+Dashboard!$P$11) | L105: =M105+F105 | M105: =M82*(1+Dashboard!$P$11) | N105: =((M105*D105)*12) | P105: =B105 | Q105: =C105 | R105: =D105 | S105: =E105 | T105: =F105 | U105: =((M105*R105)*12) | W105: =B105 | X105: =C105 | Y105: =D105 | Z105: =E105 | AA105: =F105 | AB105: =((H105*Y105)*12) | AD105: =B105 | AE105: =C105 | AF105: =D105 | AG105: =E105 | AH105: =F105 | AI105: =+MAX(U105,AB105) | AK105: =B105 | AL105: =C105 | AM105: =D105 | AN105: =E105 | AO105: =F105 | AP105: =IF(G105>0,MAX(U105,AB105),N105)
B106: =B83 | C106: =C83 | D106: =$D83 | E106: =E83 | F106: =F83*(1+Dashboard!$P$12) | G106: =G83*(1+Dashboard!$P$11) | H106: =+G106-F106 | I106: =I83*(1+Dashboard!$P$11) | J106: =I106-F106 | K106: =K83*(1+Dashboard!$P$11) | L106: =M106+F106 | M106: =M83*(1+Dashboard!$P$11) | N106: =((M106*D106)*12) | P106: =B106 | Q106: =C106 | R106: =D106 | S106: =E106 | T106: =F106 | U106: =((M106*R106)*12) | W106: =B106 | X106: =C106 | Y106: =D106 | Z106: =E106 | AA106: =F106 | AB106: =((H106*Y106)*12) | AD106: =B106 | AE106: =C106 | AF106: =D106 | AG106: =E106 | AH106: =F106 | AI106: =+MAX(U106,AB106) | AK106: =B106 | AL106: =C106 | AM106: =D106 | AN106: =E106 | AO106: =F106 | AP106: =IF(G106>0,MAX(U106,AB106),N106)
B107: =B84 | C107: =C84 | D107: =$D84 | E107: =E84 | F107: =F84*(1+Dashboard!$P$12) | G107: =G84*(1+Dashboard!$P$11) | H107: =+G107-F107 | I107: =I84*(1+Dashboard!$P$11) | J107: =I107-F107 | K107: =K84*(1+Dashboard!$P$11) | L107: =M107+F107 | M107: =M84*(1+Dashboard!$P$11) | N107: =((M107*D107)*12) | P107: =B107 | Q107: =C107 | R107: =D107 | S107: =E107 | T107: =F107 | U107: =((M107*R107)*12) | W107: =B107 | X107: =C107 | Y107: =D107 | Z107: =E107 | AA107: =F107 | AB107: =((H107*Y107)*12) | AD107: =B107 | AE107: =C107 | AF107: =D107 | AG107: =E107 | AH107: =F107 | AI107: =+MAX(U107,AB107) | AK107: =B107 | AL107: =C107 | AM107: =D107 | AN107: =E107 | AO107: =F107 | AP107: =IF(G107>0,MAX(U107,AB107),N107)
B108: =B85 | C108: =C85 | D108: =$D85 | E108: =E85 | F108: =F85*(1+Dashboard!$P$12) | G108: =G85*(1+Dashboard!$P$11) | H108: =+G108-F108 | I108: =I85*(1+Dashboard!$P$11) | J108: =I108-F108 | K108: =K85*(1+Dashboard!$P$11) | L108: =M108+F108 | M108: =M85*(1+Dashboard!$P$11) | N108: =((M108*D108)*12) | P108: =B108 | Q108: =C108 | R108: =D108 | S108: =E108 | T108: =F108 | U108: =((M108*R108)*12) | W108: =B108 | X108: =C108 | Y108: =D108 | Z108: =E108 | AA108: =F108 | AB108: =((H108*Y108)*12) | AD108: =B108 | AE108: =C108 | AF108: =D108 | AG108: =E108 | AH108: =F108 | AI108: =+MAX(U108,AB108) | AK108: =B108 | AL108: =C108 | AM108: =D108 | AN108: =E108 | AO108: =F108 | AP108: =IF(G108>0,MAX(U108,AB108),N108)
B109: =B86 | C109: =C86 | D109: =$D86 | E109: =E86 | F109: =F86*(1+Dashboard!$P$12) | G109: =G86*(1+Dashboard!$P$11) | H109: =+G109-F109 | I109: =I86*(1+Dashboard!$P$11) | J109: =I109-F109 | K109: =K86*(1+Dashboard!$P$11) | L109: =M109+F109 | M109: =M86*(1+Dashboard!$P$11) | N109: =((M109*D109)*12) | P109: =B109 | Q109: =C109 | R109: =D109 | S109: =E109 | T109: =F109 | U109: =((M109*R109)*12) | W109: =B109 | X109: =C109 | Y109: =D109 | Z109: =E109 | AA109: =F109 | AB109: =((H109*Y109)*12) | AD109: =B109 | AE109: =C109 | AF109: =D109 | AG109: =E109 | AH109: =F109 | AI109: =+MAX(U109,AB109) | AK109: =B109 | AL109: =C109 | AM109: =D109 | AN109: =E109 | AO109: =F109 | AP109: =IF(G109>0,MAX(U109,AB109),N109)
B110: =B87 | C110: =C87 | D110: =$D87 | E110: =E87 | F110: =F87*(1+Dashboard!$P$12) | G110: =G87*(1+Dashboard!$P$11) | H110: =+G110-F110 | I110: =I87*(1+Dashboard!$P$11) | J110: =I110-F110 | K110: =K87*(1+Dashboard!$P$11) | L110: =M110+F110 | M110: =M87*(1+Dashboard!$P$11) | N110: =((M110*D110)*12) | P110: =B110 | Q110: =C110 | R110: =D110 | S110: =E110 | T110: =F110 | U110: =((M110*R110)*12) | W110: =B110 | X110: =C110 | Y110: =D110 | Z110: =E110 | AA110: =F110 | AB110: =((H110*Y110)*12) | AD110: =B110 | AE110: =C110 | AF110: =D110 | AG110: =E110 | AH110: =F110 | AI110: =+MAX(U110,AB110) | AK110: =B110 | AL110: =C110 | AM110: =D110 | AN110: =E110 | AO110: =F110 | AP110: =IF(G110>0,MAX(U110,AB110),N110)
... B117: =B94 | C117: =C94 | D117: =$D94 | E117: =E94 | F117: =F94*(1+Dashboard!$P$12) | G117: =G94*(1+Dashboard!$P$11) | H117: =+G117-F117 | I117: =I94*(1+Dashboard!$P$11) | J117: =I117-F117 | K117: =K94*(1+Dashboard!$P$11) | L117: =M117+F117 | M117: =M94*(1+Dashboard!$P$11) | N117: =((M117*D117)*12) | P117: =B117 | Q117: =C117 | R117: =D117 | S117: =E117 | T117: =F117 | U117: =((M117*R117)*12) | W117: =B117 | X117: =C117 | Y117: =D117 | Z117: =E117 | AA117: =F117 | AB117: =((H117*Y117)*12) | AD117: =B117 | AE117: =C117 | AF117: =D117 | AG117: =E117 | AH117: =F117 | AI117: =+MAX(U117,AB117) | AK117: =B117 | AL117: =C117 | AM117: =D117 | AN117: =E117 | AO117: =F117 | AP117: =IF(G117>0,MAX(U117,AB117),N117)
B118: Total (Pre-Vacancy) | D118: =SUM(D99:D117) | E118: =+SUMPRODUCT(E99:E117,$D99:$D117) | F118: =+SUMPRODUCT(F99:F117,$D99:$D117) | G118: =+SUMPRODUCT(G99:G117,$D99:$D117) | H118: =+SUMPRODUCT(H99:H117,$D99:$D117) | I118: =+SUMPRODUCT(I99:I117,$D99:$D117) | J118: =+SUMPRODUCT(J99:J117,$D99:$D117) | K118: =+SUMPRODUCT(K99:K117,$D99:$D117) | L118: =+SUMPRODUCT(L99:L117,$D99:$D117) | M118: =+SUMPRODUCT(M99:M117,$D99:$D117) | N118: =SUM(N99:N117) | P118: Total (Pre-Vacancy) | R118: =SUM(R99:R117) | S118: =+SUMPRODUCT(S99:S117,$R99:$R117) | T118: =+SUMPRODUCT(T99:T117,$R99:$R117) | U118: =SUM(U99:U117) | W118: Total (Pre-Vacancy) | Y118: =SUM(Y99:Y117) | Z118: =+SUMPRODUCT(Z99:Z117,$Y99:$Y117) | AA118: =+SUMPRODUCT(AA99:AA117,$Y99:$Y117) | AB118: =SUM(AB99:AB117) | AD118: Total (Pre-Vacancy) | AF118: =SUM(AF99:AF117) | AG118: =+SUMPRODUCT(AG99:AG117,$AF99:$AF117) | AH118: =+SUMPRODUCT(AH99:AH117,$AF99:$AF117) | AI118: =SUM(AI99:AI117) | AK118: Total (Pre-Vacancy) | AM118: =SUM(AF99:AF117) | AN118: =+SUMPRODUCT(AG99:AG117,$AF99:$AF117) | AO118: =+SUMPRODUCT(AH99:AH117,$AF99:$AF117) | AP118: =SUM(AP99:AP117)
B120: Year 6 | P120: =+$B120 | W120: =+$B120 | AD120: =+$B120 | AK120: =+$B120
B121: Unit Type | C121: AMI / S8 | D121: # of Units | E121: Avg. SF | F121: Avg. Utilities | G121: Avg. Max LITHC | H121: Net LIHTC | I121: Avg. Max FMR | J121: Net FMR | K121: =+K98 | L121: Gross Rent | M121: Avg. Current Rent | N121: Yrly. Gross Income (Net Rent) | P121: Unit Type | Q121: AMI / S8 | R121: # of Units | S121: Avg. SF | T121: Avg. Utilities | U121: Max Current Vouchers | W121: Unit Type | X121: AMI / S8 | Y121: # of Units | Z121: Avg. SF | AA121: Avg. Utilities | AB121: Max NET LIHTC | AD121: Unit Type | AE121: AMI / S8 | AF121: # of Units | AG121: Avg. SF | AH121: Avg. Utilities | AI121: Max Current Vouchers + NET LIHTC | AK121: Unit Type | AL121: AMI / S8 | AM121: # of Units | AN121: Avg. SF | AO121: Avg. Utilities | AP121: Max Current Vouchers + NET LIHTC
B122: =B99 | C122: =C99 | D122: =$D99 | E122: =E99 | F122: =F99*(1+Dashboard!$P$12) | G122: =G99*(1+Dashboard!$P$11) | H122: =+G122-F122 | I122: =I99*(1+Dashboard!$P$11) | J122: =I122-F122 | K122: =K99*(1+Dashboard!$P$11) | L122: =M122+F122 | M122: =M99*(1+Dashboard!$P$11) | N122: =((M122*D122)*12) | P122: =B122 | Q122: =C122 | R122: =D122 | S122: =E122 | T122: =F122 | U122: =((M122*R122)*12) | W122: =B122 | X122: =C122 | Y122: =D122 | Z122: =E122 | AA122: =F122 | AB122: =((H122*Y122)*12) | AD122: =B122 | AE122: =C122 | AF122: =D122 | AG122: =E122 | AH122: =F122 | AI122: =+MAX(U122,AB122) | AK122: =B122 | AL122: =C122 | AM122: =D122 | AN122: =E122 | AO122: =F122 | AP122: =IF(G122>0,MAX(U122,AB122),N122)
B123: =B100 | C123: =C100 | D123: =$D100 | E123: =E100 | F123: =F100*(1+Dashboard!$P$12) | G123: =G100*(1+Dashboard!$P$11) | H123: =+G123-F123 | I123: =I100*(1+Dashboard!$P$11) | J123: =I123-F123 | K123: =K100*(1+Dashboard!$P$11) | L123: =M123+F123 | M123: =M100*(1+Dashboard!$P$11) | N123: =((M123*D123)*12) | P123: =B123 | Q123: =C123 | R123: =D123 | S123: =E123 | T123: =F123 | U123: =((M123*R123)*12) | W123: =B123 | X123: =C123 | Y123: =D123 | Z123: =E123 | AA123: =F123 | AB123: =((H123*Y123)*12) | AD123: =B123 | AE123: =C123 | AF123: =D123 | AG123: =E123 | AH123: =F123 | AI123: =+MAX(U123,AB123) | AK123: =B123 | AL123: =C123 | AM123: =D123 | AN123: =E123 | AO123: =F123 | AP123: =IF(G123>0,MAX(U123,AB123),N123)
B124: =B101 | C124: =C101 | D124: =$D101 | E124: =E101 | F124: =F101*(1+Dashboard!$P$12) | G124: =G101*(1+Dashboard!$P$11) | H124: =+G124-F124 | I124: =I101*(1+Dashboard!$P$11) | J124: =I124-F124 | K124: =K101*(1+Dashboard!$P$11) | L124: =M124+F124 | M124: =M101*(1+Dashboard!$P$11) | N124: =((M124*D124)*12) | P124: =B124 | Q124: =C124 | R124: =D124 | S124: =E124 | T124: =F124 | U124: =((M124*R124)*12) | W124: =B124 | X124: =C124 | Y124: =D124 | Z124: =E124 | AA124: =F124 | AB124: =((H124*Y124)*12) | AD124: =B124 | AE124: =C124 | AF124: =D124 | AG124: =E124 | AH124: =F124 | AI124: =+MAX(U124,AB124) | AK124: =B124 | AL124: =C124 | AM124: =D124 | AN124: =E124 | AO124: =F124 | AP124: =IF(G124>0,MAX(U124,AB124),N124)
B125: =B102 | C125: =C102 | D125: =$D102 | E125: =E102 | F125: =F102*(1+Dashboard!$P$12) | G125: =G102*(1+Dashboard!$P$11) | H125: =+G125-F125 | I125: =I102*(1+Dashboard!$P$11) | J125: =I125-F125 | K125: =K102*(1+Dashboard!$P$11) | L125: =M125+F125 | M125: =M102*(1+Dashboard!$P$11) | N125: =((M125*D125)*12) | P125: =B125 | Q125: =C125 | R125: =D125 | S125: =E125 | T125: =F125 | U125: =((M125*R125)*12) | W125: =B125 | X125: =C125 | Y125: =D125 | Z125: =E125 | AA125: =F125 | AB125: =((H125*Y125)*12) | AD125: =B125 | AE125: =C125 | AF125: =D125 | AG125: =E125 | AH125: =F125 | AI125: =+MAX(U125,AB125) | AK125: =B125 | AL125: =C125 | AM125: =D125 | AN125: =E125 | AO125: =F125 | AP125: =IF(G125>0,MAX(U125,AB125),N125)
B126: =B103 | C126: =C103 | D126: =$D103 | E126: =E103 | F126: =F103*(1+Dashboard!$P$12) | G126: =G103*(1+Dashboard!$P$11) | H126: =+G126-F126 | I126: =I103*(1+Dashboard!$P$11) | J126: =I126-F126 | K126: =K103*(1+Dashboard!$P$11) | L126: =M126+F126 | M126: =M103*(1+Dashboard!$P$11) | N126: =((M126*D126)*12) | P126: =B126 | Q126: =C126 | R126: =D126 | S126: =E126 | T126: =F126 | U126: =((M126*R126)*12) | W126: =B126 | X126: =C126 | Y126: =D126 | Z126: =E126 | AA126: =F126 | AB126: =((H126*Y126)*12) | AD126: =B126 | AE126: =C126 | AF126: =D126 | AG126: =E126 | AH126: =F126 | AI126: =+MAX(U126,AB126) | AK126: =B126 | AL126: =C126 | AM126: =D126 | AN126: =E126 | AO126: =F126 | AP126: =IF(G126>0,MAX(U126,AB126),N126)
B127: =B104 | C127: =C104 | D127: =$D104 | E127: =E104 | F127: =F104*(1+Dashboard!$P$12) | G127: =G104*(1+Dashboard!$P$11) | H127: =+G127-F127 | I127: =I104*(1+Dashboard!$P$11) | J127: =I127-F127 | K127: =K104*(1+Dashboard!$P$11) | L127: =M127+F127 | M127: =M104*(1+Dashboard!$P$11) | N127: =((M127*D127)*12) | P127: =B127 | Q127: =C127 | R127: =D127 | S127: =E127 | T127: =F127 | U127: =((M127*R127)*12) | W127: =B127 | X127: =C127 | Y127: =D127 | Z127: =E127 | AA127: =F127 | AB127: =((H127*Y127)*12) | AD127: =B127 | AE127: =C127 | AF127: =D127 | AG127: =E127 | AH127: =F127 | AI127: =+MAX(U127,AB127) | AK127: =B127 | AL127: =C127 | AM127: =D127 | AN127: =E127 | AO127: =F127 | AP127: =IF(G127>0,MAX(U127,AB127),N127)
B128: =B105 | C128: =C105 | D128: =$D105 | E128: =E105 | F128: =F105*(1+Dashboard!$P$12) | G128: =G105*(1+Dashboard!$P$11) | H128: =+G128-F128 | I128: =I105*(1+Dashboard!$P$11) | J128: =I128-F128 | K128: =K105*(1+Dashboard!$P$11) | L128: =M128+F128 | M128: =M105*(1+Dashboard!$P$11) | N128: =((M128*D128)*12) | P128: =B128 | Q128: =C128 | R128: =D128 | S128: =E128 | T128: =F128 | U128: =((M128*R128)*12) | W128: =B128 | X128: =C128 | Y128: =D128 | Z128: =E128 | AA128: =F128 | AB128: =((H128*Y128)*12) | AD128: =B128 | AE128: =C128 | AF128: =D128 | AG128: =E128 | AH128: =F128 | AI128: =+MAX(U128,AB128) | AK128: =B128 | AL128: =C128 | AM128: =D128 | AN128: =E128 | AO128: =F128 | AP128: =IF(G128>0,MAX(U128,AB128),N128)
B129: =B106 | C129: =C106 | D129: =$D106 | E129: =E106 | F129: =F106*(1+Dashboard!$P$12) | G129: =G106*(1+Dashboard!$P$11) | H129: =+G129-F129 | I129: =I106*(1+Dashboard!$P$11) | J129: =I129-F129 | K129: =K106*(1+Dashboard!$P$11) | L129: =M129+F129 | M129: =M106*(1+Dashboard!$P$11) | N129: =((M129*D129)*12) | P129: =B129 | Q129: =C129 | R129: =D129 | S129: =E129 | T129: =F129 | U129: =((M129*R129)*12) | W129: =B129 | X129: =C129 | Y129: =D129 | Z129: =E129 | AA129: =F129 | AB129: =((H129*Y129)*12) | AD129: =B129 | AE129: =C129 | AF129: =D129 | AG129: =E129 | AH129: =F129 | AI129: =+MAX(U129,AB129) | AK129: =B129 | AL129: =C129 | AM129: =D129 | AN129: =E129 | AO129: =F129 | AP129: =IF(G129>0,MAX(U129,AB129),N129)
B130: =B107 | C130: =C107 | D130: =$D107 | E130: =E107 | F130: =F107*(1+Dashboard!$P$12) | G130: =G107*(1+Dashboard!$P$11) | H130: =+G130-F130 | I130: =I107*(1+Dashboard!$P$11) | J130: =I130-F130 | K130: =K107*(1+Dashboard!$P$11) | L130: =M130+F130 | M130: =M107*(1+Dashboard!$P$11) | N130: =((M130*D130)*12) | P130: =B130 | Q130: =C130 | R130: =D130 | S130: =E130 | T130: =F130 | U130: =((M130*R130)*12) | W130: =B130 | X130: =C130 | Y130: =D130 | Z130: =E130 | AA130: =F130 | AB130: =((H130*Y130)*12) | AD130: =B130 | AE130: =C130 | AF130: =D130 | AG130: =E130 | AH130: =F130 | AI130: =+MAX(U130,AB130) | AK130: =B130 | AL130: =C130 | AM130: =D130 | AN130: =E130 | AO130: =F130 | AP130: =IF(G130>0,MAX(U130,AB130),N130)
B131: =B108 | C131: =C108 | D131: =$D108 | E131: =E108 | F131: =F108*(1+Dashboard!$P$12) | G131: =G108*(1+Dashboard!$P$11) | H131: =+G131-F131 | I131: =I108*(1+Dashboard!$P$11) | J131: =I131-F131 | K131: =K108*(1+Dashboard!$P$11) | L131: =M131+F131 | M131: =M108*(1+Dashboard!$P$11) | N131: =((M131*D131)*12) | P131: =B131 | Q131: =C131 | R131: =D131 | S131: =E131 | T131: =F131 | U131: =((M131*R131)*12) | W131: =B131 | X131: =C131 | Y131: =D131 | Z131: =E131 | AA131: =F131 | AB131: =((H131*Y131)*12) | AD131: =B131 | AE131: =C131 | AF131: =D131 | AG131: =E131 | AH131: =F131 | AI131: =+MAX(U131,AB131) | AK131: =B131 | AL131: =C131 | AM131: =D131 | AN131: =E131 | AO131: =F131 | AP131: =IF(G131>0,MAX(U131,AB131),N131)
B132: =B109 | C132: =C109 | D132: =$D109 | E132: =E109 | F132: =F109*(1+Dashboard!$P$12) | G132: =G109*(1+Dashboard!$P$11) | H132: =+G132-F132 | I132: =I109*(1+Dashboard!$P$11) | J132: =I132-F132 | K132: =K109*(1+Dashboard!$P$11) | L132: =M132+F132 | M132: =M109*(1+Dashboard!$P$11) | N132: =((M132*D132)*12) | P132: =B132 | Q132: =C132 | R132: =D132 | S132: =E132 | T132: =F132 | U132: =((M132*R132)*12) | W132: =B132 | X132: =C132 | Y132: =D132 | Z132: =E132 | AA132: =F132 | AB132: =((H132*Y132)*12) | AD132: =B132 | AE132: =C132 | AF132: =D132 | AG132: =E132 | AH132: =F132 | AI132: =+MAX(U132,AB132) | AK132: =B132 | AL132: =C132 | AM132: =D132 | AN132: =E132 | AO132: =F132 | AP132: =IF(G132>0,MAX(U132,AB132),N132)
B133: =B110 | C133: =C110 | D133: =$D110 | E133: =E110 | F133: =F110*(1+Dashboard!$P$12) | G133: =G110*(1+Dashboard!$P$11) | H133: =+G133-F133 | I133: =I110*(1+Dashboard!$P$11) | J133: =I133-F133 | K133: =K110*(1+Dashboard!$P$11) | L133: =M133+F133 | M133: =M110*(1+Dashboard!$P$11) | N133: =((M133*D133)*12) | P133: =B133 | Q133: =C133 | R133: =D133 | S133: =E133 | T133: =F133 | U133: =((M133*R133)*12) | W133: =B133 | X133: =C133 | Y133: =D133 | Z133: =E133 | AA133: =F133 | AB133: =((H133*Y133)*12) | AD133: =B133 | AE133: =C133 | AF133: =D133 | AG133: =E133 | AH133: =F133 | AI133: =+MAX(U133,AB133) | AK133: =B133 | AL133: =C133 | AM133: =D133 | AN133: =E133 | AO133: =F133 | AP133: =IF(G133>0,MAX(U133,AB133),N133)
... B140: =B117 | C140: =C117 | D140: =$D117 | E140: =E117 | F140: =F117*(1+Dashboard!$P$12) | G140: =G117*(1+Dashboard!$P$11) | H140: =+G140-F140 | I140: =I117*(1+Dashboard!$P$11) | J140: =I140-F140 | K140: =K117*(1+Dashboard!$P$11) | L140: =M140+F140 | M140: =M117*(1+Dashboard!$P$11) | N140: =((M140*D140)*12) | P140: =B140 | Q140: =C140 | R140: =D140 | S140: =E140 | T140: =F140 | U140: =((M140*R140)*12) | W140: =B140 | X140: =C140 | Y140: =D140 | Z140: =E140 | AA140: =F140 | AB140: =((H140*Y140)*12) | AD140: =B140 | AE140: =C140 | AF140: =D140 | AG140: =E140 | AH140: =F140 | AI140: =+MAX(U140,AB140) | AK140: =B140 | AL140: =C140 | AM140: =D140 | AN140: =E140 | AO140: =F140 | AP140: =IF(G140>0,MAX(U140,AB140),N140)
B141: Total (Pre-Vacancy) | D141: =SUM(D122:D140) | E141: =+SUMPRODUCT(E122:E140,$D122:$D140) | F141: =+SUMPRODUCT(F122:F140,$D122:$D140) | G141: =+SUMPRODUCT(G122:G140,$D122:$D140) | H141: =+SUMPRODUCT(H122:H140,$D122:$D140) | I141: =+SUMPRODUCT(I122:I140,$D122:$D140) | J141: =+SUMPRODUCT(J122:J140,$D122:$D140) | K141: =+SUMPRODUCT(K122:K140,$D122:$D140) | L141: =+SUMPRODUCT(L122:L140,$D122:$D140) | M141: =+SUMPRODUCT(M122:M140,$D122:$D140) | N141: =SUM(N122:N140) | P141: Total (Pre-Vacancy) | R141: =SUM(R122:R140) | S141: =+SUMPRODUCT(S122:S140,$R122:$R140) | T141: =+SUMPRODUCT(T122:T140,$R122:$R140) | U141: =SUM(U122:U140) | W141: Total (Pre-Vacancy) | Y141: =SUM(Y122:Y140) | Z141: =+SUMPRODUCT(Z122:Z140,$Y122:$Y140) | AA141: =+SUMPRODUCT(AA122:AA140,$Y122:$Y140) | AB141: =SUM(AB122:AB140) | AD141: Total (Pre-Vacancy) | AF141: =SUM(AF122:AF140) | AG141: =+SUMPRODUCT(AG122:AG140,$AF122:$AF140) | AH141: =+SUMPRODUCT(AH122:AH140,$AF122:$AF140) | AI141: =SUM(AI122:AI140) | AK141: Total (Pre-Vacancy) | AM141: =SUM(AF122:AF140) | AN141: =+SUMPRODUCT(AG122:AG140,$AF122:$AF140) | AO141: =+SUMPRODUCT(AH122:AH140,$AF122:$AF140) | AP141: =SUM(AP122:AP140)
B143: Year 7 | P143: =+$B143 | W143: =+$B143 | AD143: =+$B143 | AK143: =+$B143
B144: Unit Type | C144: AMI / S8 | D144: # of Units | E144: Avg. SF | F144: Avg. Utilities | G144: Avg. Max LITHC | H144: Net LIHTC | I144: Avg. Max FMR | J144: Net FMR | K144: =+K121 | L144: Gross Rent | M144: Avg. Current Rent | N144: Yrly. Gross Income (Net Rent) | P144: Unit Type | Q144: AMI / S8 | R144: # of Units | S144: Avg. SF | T144: Avg. Utilities | U144: Max Current Vouchers | W144: Unit Type | X144: AMI / S8 | Y144: # of Units | Z144: Avg. SF | AA144: Avg. Utilities | AB144: Max NET LIHTC | AD144: Unit Type | AE144: AMI / S8 | AF144: # of Units | AG144: Avg. SF | AH144: Avg. Utilities | AI144: Max Current Vouchers + NET LIHTC | AK144: Unit Type | AL144: AMI / S8 | AM144: # of Units | AN144: Avg. SF | AO144: Avg. Utilities | AP144: Max Current Vouchers + NET LIHTC
B145: =B122 | C145: =C122 | D145: =$D122 | E145: =E122 | F145: =F122*(1+Dashboard!$P$12) | G145: =G122*(1+Dashboard!$P$11) | H145: =+G145-F145 | I145: =I122*(1+Dashboard!$P$11) | J145: =I145-F145 | K145: =K122*(1+Dashboard!$P$11) | L145: =M145+F145 | M145: =M122*(1+Dashboard!$P$11) | N145: =((M145*D145)*12) | P145: =B145 | Q145: =C145 | R145: =D145 | S145: =E145 | T145: =F145 | U145: =((M145*R145)*12) | W145: =B145 | X145: =C145 | Y145: =D145 | Z145: =E145 | AA145: =F145 | AB145: =((H145*Y145)*12) | AD145: =B145 | AE145: =C145 | AF145: =D145 | AG145: =E145 | AH145: =F145 | AI145: =+MAX(U145,AB145) | AK145: =B145 | AL145: =C145 | AM145: =D145 | AN145: =E145 | AO145: =F145 | AP145: =IF(G145>0,MAX(U145,AB145),N145)
...

Sheet Rent Roll
B3: Unit Statistics | F3: Unit Types | J3: AMI / S8 Breakdown | N3: Total SF | O3: Avg Gross Rent | P3: Avg Net Rent
B4: Occupied | C4: =C6-C5 | D4: =+C4/C6 | F4: =+C13 | G4: =SUMIF(C$13:E$32,F4,E$13:E$32) | H4: =G4/G$10 | J4: =+D17 | K4: =SUMIF(D$13:E$32,J4,E$13:E$32) | L4: =K4/K$10 | N4: =+SUMPRODUCT(E13:E31,F13:F31) | O4: =L33/C$6 | P4: =J33/C6
B5: Vacant | C5: =+ROUND(D5*$C$6,0) | D5: =+Dashboard!P10 | F5: =+C17 | G5: =SUMIF(C$13:E$32,F5,E$13:E$32) | H5: =G5/G$10 | J5: =+D13 | K5: =SUMIF(D$13:E$32,J5,E$13:E$32) | L5: =K5/K$10
B6: Total Units | C6: =+SUM(E13:E31) | D6: =SUM(D4:D5) | F6: =+C20 | G6: =SUMIF(C$13:E$32,F6,E$13:E$32) | H6: =G6/G$10 | J6: =+D14 | K6: =SUMIF(D$13:E$32,J6,E$13:E$32) | L6: =K6/K$10
F7: =+C23 | G7: =SUMIF(C$13:E$32,F7,E$13:E$32) | H7: =G7/G$10 | J7: =+D22 | K7: =SUMIF(D$13:E$32,J7,E$13:E$32) | L7: =K7/K$10
F8: =+C27 | G8: =SUMIF(C$13:E$32,F8,E$13:E$32) | H8: =G8/G$10 | J8: =+D27 | K8: =SUMIF(D$13:E$32,J8,E$13:E$32) | L8: =K8/K$10
F9: =+C28 | G9: =SUMIF(C$13:E$32,F9,E$13:E$32) | H9: =G9/G$10
F10: Total | G10: =SUM(G4:G9) | H10: =SUM(H4:H9) | J10: Total | K10: =SUM(K4:K9) | L10: =SUM(L4:L8)
B12: Unit Set # | C12: Unit Types | D12: AMI / S8 | E12: # of Units | F12: Avg. SF | G12: Avg. Market Rent | H12: Avg. Resident Rent | I12: Avg. Subsidy | J12: Avg. Current Rent | K12: Avg. Utilities | L12: Gross Rent | M12: Avg. Max LIHTC | N12: Net LIHTC | O12: Avg. Max FMR | P12: Net FMR
B13: 1 | C13: 1x1 | D13: 50% AMI | E13: 2 | F13: 701 | H13: 527 | J13: =+(I13+H13) | K13: 65 | L13: =J13+K13 | M13: 651 | N13: =M13-$K13 | O13: 683 | P13: =O13-$K13
B14: =+B13+1 | C14: 1x1 | D14: 60% AMI | E14: 0 | F14: 701 | H14: 0 | J14: =+(I14+H14) | K14: 65 | L14: =J14+K14 | M14: 781 | N14: =M14-$K14 | O14: 683 | P14: =O14-$K14
B15: =+B14+1 | C15: 1x1 | D15: Market | E15: 1 | F15: 701 | H15: 593 | J15: =+(I15+H15) | K15: 0 | L15: =J15+K15 | M15: 0 | N15: =M15-$K15 | O15: 683 | P15: =O15-$K15
B16: =+B15+1 | C16: 1x1 | D16: S8 Voucher | E16: 3 | F16: 701 | H16: 523 | J16: =+(I16+H16) | K16: 65 | L16: =J16+K16 | M16: 781 | N16: =M16-$K16 | O16: 683 | P16: =O16-$K16
B17: =+B16+1 | C17: 2x1.5 | D17: 40% AMI | E17: 1 | F17: 940 | H17: 465 | J17: =+(I17+H17) | K17: 86 | L17: =J17+K17 | M17: 539 | N17: =M17-$K17 | O17: 778 | P17: =O17-$K17
B18: =+B17+1 | C18: 2x1.5 | D18: =+D13 | E18: 3 | F18: 990 | H18: 580 | J18: =+(I18+H18) | K18: 86 | L18: =J18+K18 | M18: 695 | N18: =M18-$K18 | O18: 778 | P18: =O18-$K18
B19: =+B18+1 | C19: 2x1.5 | D19: =+D14 | E19: 2 | F19: 980 | H19: 642 | J19: =+(I19+H19) | K19: 86 | L19: =J19+K19 | M19: 851 | N19: =M19-$K19 | O19: 778 | P19: =O19-$K19
B20: =+B19+1 | C20: 2x2 | D20: =+D18 | E20: 1 | F20: 968 | H20: 610 | J20: =+(I20+H20) | K20: 86 | L20: =J20+K20 | M20: 695 | N20: =M20-$K20 | O20: 778 | P20: =O20-$K20
B21: =+B20+1 | C21: 2x2 | D21: =+D19 | E21: 2 | F21: 968 | H21: 635 | J21: =+(I21+H21) | K21: 86 | L21: =J21+K21 | M21: 851 | N21: =M21-$K21 | O21: 778 | P21: =O21-$K21
B22: =+B21+1 | C22: 2x2 | D22: =+D15 | E22: 0 | F22: 968 | H22: 0 | J22: =+(I22+H22) | K22: 0 | L22: =J22+K22 | M22: 0 | N22: =M22-$K22 | O22: 778 | P22: =O22-$K22
B23: =+B22+1 | C23: 2x2 (TH) | D23: =+D17 | E23: 1 | F23: 1058 | H23: 450 | J23: =+(I23+H23) | K23: 86 | L23: =J23+K23 | M23: 539 | N23: =M23-$K23 | O23: 778 | P23: =O23-$K23
B24: =+B23+1 | C24: 2x2 (TH) | D24: =+D18 | E24: 1 | F24: 1058 | H24: 60 | J24: =+(I24+H24) | K24: 86 | L24: =J24+K24 | M24: 695 | N24: =M24-$K24 | O24: 778 | P24: =O24-$K24
B25: =+B24+1 | C25: 2x2 (TH) | D25: =+D19 | E25: 16 | F25: 1058 | H25: 690 | J25: =+(I25+H25) | K25: 86 | L25: =J25+K25 | M25: 851 | N25: =M25-$K25 | O25: 778 | P25: =O25-$K25
B26: =+B25+1 | C26: 2x2 (TH) | D26: =+D15 | E26: 1 | F26: 1058 | H26: 750 | J26: =+(I26+H26) | K26: 0 | L26: =J26+K26 | M26: 0 | N26: =M26-$K26 | O26: 778 | P26: =O26-$K26
B27: =+B26+1 | C27: 2x1.5-2x2 | D27: =+D16 | E27: 18 | H27: 736 | J27: =+(I27+H27) | K27: 86 | L27: =J27+K27 | M27: 851 | N27: =M27-$K27 | O27: 778 | P27: =O27-$K27
B28: =+B27+1 | C28: 3x2 (TH) | D28: =+D24 | E28: 2 | F28: 1296 | H28: 680 | J28: =+(I28+H28) | K28: 107 | L28: =J28+K28 | M28: 795 | N28: =M28-$K28 | O28: 1023 | P28: =O28-$K28
B29: =+B28+1 | C29: 3x2 (TH) | D29: =+D25 | E29: 7 | F29: 1296 | H29: 696 | J29: =+(I29+H29) | K29: 107 | L29: =J29+K29 | M29: 976 | N29: =M29-$K29 | O29: 1023 | P29: =O29-$K29
B30: =+B29+1 | C30: 3x2 (TH) | D30: =+D26 | E30: 0 | F30: 1296 | H30: 0 | J30: =+(I30+H30) | K30: 0 | L30: =J30+K30 | M30: 0 | N30: =M30-$K30 | O30: 1023 | P30: =O30-$K30
B31: =+B30+1 | C31: 3x2 (TH) | D31: =+D27 | E31: 11 | F31: 1296 | H31: 828 | J31: =+(I31+H31) | K31: 107 | L31: =J31+K31 | M31: 976 | N31: =M31-$K31 | O31: 1023 | P31: =O31-$K31
B32: Add Rows by Inserting Row Above This Row
B33: Monthly Total | F33: --- | G33: =+SUMPRODUCT($E$13:$E$32,G13:G32) | H33: =+SUMPRODUCT($E$13:$E$32,H13:H32) | I33: =+SUMPRODUCT($E$13:$E$32,I13:I32) | J33: =+SUMPRODUCT($E$13:$E$32,J13:J32) | K33: =+SUMPRODUCT($E$13:$E$32,K13:K32) | L33: =+SUMPRODUCT($E$13:$E$32,L13:L32) | M33: =+SUMPRODUCT($E$13:$E$32,M13:M32) | N33: =+SUMPRODUCT($E$13:$E$32,N13:N32) | ... P33: =+SUMPRODUCT($E$13:$E$32,P13:P32)
B34: Yearly Total | F34: --- | G34: =G33*12 | H34: =H33*12 | I34: =I33*12 | J34: =J33*12 | K34: =K33*12 | L34: =L33*12 | M34: =M33*12 | N34: =N33*12 | ... P34: =P33*12
B36: Weighted Average | F36: =+SUMPRODUCT(F13:F32,$E$13:$E$32)/$C$6 | G36: =+SUMPRODUCT(G13:G32,$E$13:$E$32)/$C$6 | H36: =+SUMPRODUCT(H13:H32,$E$13:$E$32)/$C$6 | J36: =+SUMPRODUCT(J13:J32,$E$13:$E$32)/$C$6 | K36: =+SUMPRODUCT(K13:K32,$E$13:$E$32)/$C$6 | L36: =+SUMPRODUCT(L13:L32,$E$13:$E$32)/$C$6 | M36: =+SUMPRODUCT(M13:M32,$E$13:$E$32)/$C$6 | N36: =+SUMPRODUCT(N13:N32,$E$13:$E$32)/$C$6 | O36: =+SUMPRODUCT(O13:O32,$E$13:$E$32)/$C$6 | P36: =+SUMPRODUCT(P13:P32,$E$13:$E$32)/$C$6

Sheet Summary Outputs -->

Sheet Op Ex per Unit
B3: Total Operating Expenses | O3: Operating Expenses Cost Per Unit
B5: Income Statement | C5: T12 | D5: 1 | E5: =+D5+1 | F5: =+E5+1 | G5: =+F5+1 | H5: =+G5+1 | I5: =+H5+1 | J5: =+I5+1 | K5: =+J5+1 | L5: =+K5+1 | M5: =+L5+1 | O5: Income Statement | P5: T12 | Q5: 1 | R5: =+Q5+1 | S5: =+R5+1 | T5: =+S5+1 | U5: =+T5+1 | V5: =+U5+1 | W5: =+V5+1 | X5: =+W5+1 | Y5: =+X5+1 | Z5: =+Y5+1
B7: Bad Debt | C7: =+'Scenario 0'!E17 | D7: =+'Scenario 0'!F17 | E7: =+'Scenario 0'!G17 | F7: =+'Scenario 0'!H17 | G7: =+'Scenario 0'!I17 | H7: =+'Scenario 0'!J17 | I7: =+'Scenario 0'!K17 | J7: =+'Scenario 0'!L17 | ... M7: =+'Scenario 0'!O17 | O7: Bad Debt | P7: =+'Scenario 0'!E17/Dashboard!$E$16 | Q7: =+'Scenario 0'!F17/Dashboard!$E$16 | R7: =+'Scenario 0'!G17/Dashboard!$E$16 | S7: =+'Scenario 0'!H17/Dashboard!$E$16 | T7: =+'Scenario 0'!I17/Dashboard!$E$16 | U7: =+'Scenario 0'!J17/Dashboard!$E$16 | V7: =+'Scenario 0'!K17/Dashboard!$E$16 | W7: =+'Scenario 0'!L17/Dashboard!$E$16 | ... Z7: =+'Scenario 0'!O17/Dashboard!$E$16
B8: Total Bad Debt | C8: =+'Scenario 0'!E18 | D8: =+'Scenario 0'!F18 | E8: =+'Scenario 0'!G18 | F8: =+'Scenario 0'!H18 | G8: =+'Scenario 0'!I18 | H8: =+'Scenario 0'!J18 | I8: =+'Scenario 0'!K18 | J8: =+'Scenario 0'!L18 | ... M8: =+'Scenario 0'!O18 | O8: Total Bad Debt | P8: =+'Scenario 0'!E18/Dashboard!$E$16 | Q8: =+'Scenario 0'!F18/Dashboard!$E$16 | R8: =+'Scenario 0'!G18/Dashboard!$E$16 | S8: =+'Scenario 0'!H18/Dashboard!$E$16 | T8: =+'Scenario 0'!I18/Dashboard!$E$16 | U8: =+'Scenario 0'!J18/Dashboard!$E$16 | V8: =+'Scenario 0'!K18/Dashboard!$E$16 | W8: =+'Scenario 0'!L18/Dashboard!$E$16 | ... Z8: =+'Scenario 0'!O18/Dashboard!$E$16
B10: Replacement Reserves | C10: =+'Scenario 0'!E20 | D10: =+'Scenario 0'!F20 | E10: =+'Scenario 0'!G20 | F10: =+'Scenario 0'!H20 | G10: =+'Scenario 0'!I20 | H10: =+'Scenario 0'!J20 | I10: =+'Scenario 0'!K20 | J10: =+'Scenario 0'!L20 | ... M10: =+'Scenario 0'!O20 | O10: Replacement Reserves | P10: =+'Scenario 0'!E20/Dashboard!$E$16 | Q10: =+'Scenario 0'!F20/Dashboard!$E$16 | R10: =+'Scenario 0'!G20/Dashboard!$E$16 | S10: =+'Scenario 0'!H20/Dashboard!$E$16 | T10: =+'Scenario 0'!I20/Dashboard!$E$16 | U10: =+'Scenario 0'!J20/Dashboard!$E$16 | V10: =+'Scenario 0'!K20/Dashboard!$E$16 | W10: =+'Scenario 0'!L20/Dashboard!$E$16 | ... Z10: =+'Scenario 0'!O20/Dashboard!$E$16
B11: Compliance Fee | C11: =+'Scenario 0'!E21 | D11: =+'Scenario 0'!F21 | E11: =+'Scenario 0'!G21 | F11: =+'Scenario 0'!H21 | G11: =+'Scenario 0'!I21 | H11: =+'Scenario 0'!J21 | I11: =+'Scenario 0'!K21 | J11: =+'Scenario 0'!L21 | ... M11: =+'Scenario 0'!O21 | O11: Compliance Fee | P11: =+'Scenario 0'!E21/Dashboard!$E$16 | Q11: =+'Scenario 0'!F21/Dashboard!$E$16 | R11: =+'Scenario 0'!G21/Dashboard!$E$16 | S11: =+'Scenario 0'!H21/Dashboard!$E$16 | T11: =+'Scenario 0'!I21/Dashboard!$E$16 | U11: =+'Scenario 0'!J21/Dashboard!$E$16 | V11: =+'Scenario 0'!K21/Dashboard!$E$16 | W11: =+'Scenario 0'!L21/Dashboard!$E$16 | ... Z11: =+'Scenario 0'!O21/Dashboard!$E$16
B12: Total Replacement Reserves | C12: =+'Scenario 0'!E22 | D12: =+'Scenario 0'!F22 | E12: =+'Scenario 0'!G22 | F12: =+'Scenario 0'!H22 | G12: =+'Scenario 0'!I22 | H12: =+'Scenario 0'!J22 | I12: =+'Scenario 0'!K22 | J12: =+'Scenario 0'!L22 | ... M12: =+'Scenario 0'!O22 | O12: Total Replacement Reserves | P12: =+'Scenario 0'!E22/Dashboard!$E$16 | Q12: =+'Scenario 0'!F22/Dashboard!$E$16 | R12: =+'Scenario 0'!G22/Dashboard!$E$16 | S12: =+'Scenario 0'!H22/Dashboard!$E$16 | T12: =+'Scenario 0'!I22/Dashboard!$E$16 | U12: =+'Scenario 0'!J22/Dashboard!$E$16 | V12: =+'Scenario 0'!K22/Dashboard!$E$16 | W12: =+'Scenario 0'!L22/Dashboard!$E$16 | ... Z12: =+'Scenario 0'!O22/Dashboard!$E$16
B14: Property Manager Salary | C14: =+'Scenario 0'!E25 | D14: =+'Scenario 0'!F25 | E14: =+'Scenario 0'!G25 | F14: =+'Scenario 0'!H25 | G14: =+'Scenario 0'!I25 | H14: =+'Scenario 0'!J25 | I14: =+'Scenario 0'!K25 | J14: =+'Scenario 0'!L25 | ... M14: =+'Scenario 0'!O25 | O14: Property Manager Salary | P14: =+'Scenario 0'!E25/Dashboard!$E$16 | Q14: =+'Scenario 0'!F25/Dashboard!$E$16 | R14: =+'Scenario 0'!G25/Dashboard!$E$16 | S14: =+'Scenario 0'!H25/Dashboard!$E$16 | T14: =+'Scenario 0'!I25/Dashboard!$E$16 | U14: =+'Scenario 0'!J25/Dashboard!$E$16 | V14: =+'Scenario 0'!K25/Dashboard!$E$16 | W14: =+'Scenario 0'!L25/Dashboard!$E$16 | ... Z14: =+'Scenario 0'!O25/Dashboard!$E$16
B15: Assistant Manager (over 160 units) | C15: =+'Scenario 0'!E26 | D15: =+'Scenario 0'!F26 | E15: =+'Scenario 0'!G26 | F15: =+'Scenario 0'!H26 | G15: =+'Scenario 0'!I26 | H15: =+'Scenario 0'!J26 | I15: =+'Scenario 0'!K26 | J15: =+'Scenario 0'!L26 | ... M15: =+'Scenario 0'!O26 | O15: Assistant Manager (over 160 units) | P15: =+'Scenario 0'!E26/Dashboard!$E$16 | Q15: =+'Scenario 0'!F26/Dashboard!$E$16 | R15: =+'Scenario 0'!G26/Dashboard!$E$16 | S15: =+'Scenario 0'!H26/Dashboard!$E$16 | T15: =+'Scenario 0'!I26/Dashboard!$E$16 | U15: =+'Scenario 0'!J26/Dashboard!$E$16 | V15: =+'Scenario 0'!K26/Dashboard!$E$16 | W15: =+'Scenario 0'!L26/Dashboard!$E$16 | ... Z15: =+'Scenario 0'!O26/Dashboard!$E$16
B16: Commissions/Bonuses | C16: =+'Scenario 0'!E27 | D16: =+'Scenario 0'!F27 | E16: =+'Scenario 0'!G27 | F16: =+'Scenario 0'!H27 | G16: =+'Scenario 0'!I27 | H16: =+'Scenario 0'!J27 | I16: =+'Scenario 0'!K27 | J16: =+'Scenario 0'!L27 | ... M16: =+'Scenario 0'!O27 | O16: Commissions/Bonuses | P16: =+'Scenario 0'!E27/Dashboard!$E$16 | Q16: =+'Scenario 0'!F27/Dashboard!$E$16 | R16: =+'Scenario 0'!G27/Dashboard!$E$16 | S16: =+'Scenario 0'!H27/Dashboard!$E$16 | T16: =+'Scenario 0'!I27/Dashboard!$E$16 | U16: =+'Scenario 0'!J27/Dashboard!$E$16 | V16: =+'Scenario 0'!K27/Dashboard!$E$16 | W16: =+'Scenario 0'!L27/Dashboard!$E$16 | ... Z16: =+'Scenario 0'!O27/Dashboard!$E$16
B17: Maintenance Salary | C17: =+'Scenario 0'!E28 | D17: =+'Scenario 0'!F28 | E17: =+'Scenario 0'!G28 | F17: =+'Scenario 0'!H28 | G17: =+'Scenario 0'!I28 | H17: =+'Scenario 0'!J28 | I17: =+'Scenario 0'!K28 | J17: =+'Scenario 0'!L28 | ... M17: =+'Scenario 0'!O28 | O17: Maintenance Salary | P17: =+'Scenario 0'!E28/Dashboard!$E$16 | Q17: =+'Scenario 0'!F28/Dashboard!$E$16 | R17: =+'Scenario 0'!G28/Dashboard!$E$16 | S17: =+'Scenario 0'!H28/Dashboard!$E$16 | T17: =+'Scenario 0'!I28/Dashboard!$E$16 | U17: =+'Scenario 0'!J28/Dashboard!$E$16 | V17: =+'Scenario 0'!K28/Dashboard!$E$16 | W17: =+'Scenario 0'!L28/Dashboard!$E$16 | ... Z17: =+'Scenario 0'!O28/Dashboard!$E$16
B18: Total Payroll | C18: =+'Scenario 0'!E29 | D18: =+'Scenario 0'!F29 | E18: =+'Scenario 0'!G29 | F18: =+'Scenario 0'!H29 | G18: =+'Scenario 0'!I29 | H18: =+'Scenario 0'!J29 | I18: =+'Scenario 0'!K29 | J18: =+'Scenario 0'!L29 | ... M18: =+'Scenario 0'!O29 | O18: Total Payroll | P18: =+'Scenario 0'!E29/Dashboard!$E$16 | Q18: =+'Scenario 0'!F29/Dashboard!$E$16 | R18: =+'Scenario 0'!G29/Dashboard!$E$16 | S18: =+'Scenario 0'!H29/Dashboard!$E$16 | T18: =+'Scenario 0'!I29/Dashboard!$E$16 | U18: =+'Scenario 0'!J29/Dashboard!$E$16 | V18: =+'Scenario 0'!K29/Dashboard!$E$16 | W18: =+'Scenario 0'!L29/Dashboard!$E$16 | ... Z18: =+'Scenario 0'!O29/Dashboard!$E$16
B20: Management Fee | C20: =+'Scenario 0'!E31 | D20: =+'Scenario 0'!F31 | E20: =+'Scenario 0'!G31 | F20: =+'Scenario 0'!H31 | G20: =+'Scenario 0'!I31 | H20: =+'Scenario 0'!J31 | I20: =+'Scenario 0'!K31 | J20: =+'Scenario 0'!L31 | ... M20: =+'Scenario 0'!O31 | O20: Management Fee | P20: =+'Scenario 0'!E31/Dashboard!$E$16 | Q20: =+'Scenario 0'!F31/Dashboard!$E$16 | R20: =+'Scenario 0'!G31/Dashboard!$E$16 | S20: =+'Scenario 0'!H31/Dashboard!$E$16 | T20: =+'Scenario 0'!I31/Dashboard!$E$16 | U20: =+'Scenario 0'!J31/Dashboard!$E$16 | V20: =+'Scenario 0'!K31/Dashboard!$E$16 | W20: =+'Scenario 0'!L31/Dashboard!$E$16 | ... Z20: =+'Scenario 0'!O31/Dashboard!$E$16
B21: Legal Expense | C21: =+'Scenario 0'!E32 | D21: =+'Scenario 0'!F32 | E21: =+'Scenario 0'!G32 | F21: =+'Scenario 0'!H32 | G21: =+'Scenario 0'!I32 | H21: =+'Scenario 0'!J32 | I21: =+'Scenario 0'!K32 | J21: =+'Scenario 0'!L32 | ... M21: =+'Scenario 0'!O32 | O21: Legal Expense | P21: =+'Scenario 0'!E32/Dashboard!$E$16 | Q21: =+'Scenario 0'!F32/Dashboard!$E$16 | R21: =+'Scenario 0'!G32/Dashboard!$E$16 | S21: =+'Scenario 0'!H32/Dashboard!$E$16 | T21: =+'Scenario 0'!I32/Dashboard!$E$16 | U21: =+'Scenario 0'!J32/Dashboard!$E$16 | V21: =+'Scenario 0'!K32/Dashboard!$E$16 | W21: =+'Scenario 0'!L32/Dashboard!$E$16 | ... Z21: =+'Scenario 0'!O32/Dashboard!$E$16
B22: Office Expense | C22: =+'Scenario 0'!E33 | D22: =+'Scenario 0'!F33 | E22: =+'Scenario 0'!G33 | F22: =+'Scenario 0'!H33 | G22: =+'Scenario 0'!I33 | H22: =+'Scenario 0'!J33 | I22: =+'Scenario 0'!K33 | J22: =+'Scenario 0'!L33 | ... M22: =+'Scenario 0'!O33 | O22: Office Expense | P22: =+'Scenario 0'!E33/Dashboard!$E$16 | Q22: =+'Scenario 0'!F33/Dashboard!$E$16 | R22: =+'Scenario 0'!G33/Dashboard!$E$16 | S22: =+'Scenario 0'!H33/Dashboard!$E$16 | T22: =+'Scenario 0'!I33/Dashboard!$E$16 | U22: =+'Scenario 0'!J33/Dashboard!$E$16 | V22: =+'Scenario 0'!K33/Dashboard!$E$16 | W22: =+'Scenario 0'!L33/Dashboard!$E$16 | ... Z22: =+'Scenario 0'!O33/Dashboard!$E$16
B23: Travel Cost | C23: =+'Scenario 0'!E34 | D23: =+'Scenario 0'!F34 | E23: =+'Scenario 0'!G34 | F23: =+'Scenario 0'!H34 | G23: =+'Scenario 0'!I34 | H23: =+'Scenario 0'!J34 | I23: =+'Scenario 0'!K34 | J23: =+'Scenario 0'!L34 | ... M23: =+'Scenario 0'!O34 | O23: Travel Cost | P23: =+'Scenario 0'!E34/Dashboard!$E$16 | Q23: =+'Scenario 0'!F34/Dashboard!$E$16 | R23: =+'Scenario 0'!G34/Dashboard!$E$16 | S23: =+'Scenario 0'!H34/Dashboard!$E$16 | T23: =+'Scenario 0'!I34/Dashboard!$E$16 | U23: =+'Scenario 0'!J34/Dashboard!$E$16 | V23: =+'Scenario 0'!K34/Dashboard!$E$16 | W23: =+'Scenario 0'!L34/Dashboard!$E$16 | ... Z23: =+'Scenario 0'!O34/Dashboard!$E$16
B24: Audit Expense | C24: =+'Scenario 0'!E35 | D24: =+'Scenario 0'!F35 | E24: =+'Scenario 0'!G35 | F24: =+'Scenario 0'!H35 | G24: =+'Scenario 0'!I35 | H24: =+'Scenario 0'!J35 | I24: =+'Scenario 0'!K35 | J24: =+'Scenario 0'!L35 | ... M24: =+'Scenario 0'!O35 | O24: Audit Expense | P24: =+'Scenario 0'!E35/Dashboard!$E$16 | Q24: =+'Scenario 0'!F35/Dashboard!$E$16 | R24: =+'Scenario 0'!G35/Dashboard!$E$16 | S24: =+'Scenario 0'!H35/Dashboard!$E$16 | T24: =+'Scenario 0'!I35/Dashboard!$E$16 | U24: =+'Scenario 0'!J35/Dashboard!$E$16 | V24: =+'Scenario 0'!K35/Dashboard!$E$16 | W24: =+'Scenario 0'!L35/Dashboard!$E$16 | ... Z24: =+'Scenario 0'!O35/Dashboard!$E$16
B25: Advertising | C25: =+'Scenario 0'!E36 | D25: =+'Scenario 0'!F36 | E25: =+'Scenario 0'!G36 | F25: =+'Scenario 0'!H36 | G25: =+'Scenario 0'!I36 | H25: =+'Scenario 0'!J36 | I25: =+'Scenario 0'!K36 | J25: =+'Scenario 0'!L36 | ... M25: =+'Scenario 0'!O36 | O25: Advertising | P25: =+'Scenario 0'!E36/Dashboard!$E$16 | Q25: =+'Scenario 0'!F36/Dashboard!$E$16 | R25: =+'Scenario 0'!G36/Dashboard!$E$16 | S25: =+'Scenario 0'!H36/Dashboard!$E$16 | T25: =+'Scenario 0'!I36/Dashboard!$E$16 | U25: =+'Scenario 0'!J36/Dashboard!$E$16 | V25: =+'Scenario 0'!K36/Dashboard!$E$16 | W25: =+'Scenario 0'!L36/Dashboard!$E$16 | ... Z25: =+'Scenario 0'!O36/Dashboard!$E$16
B26: Training Charge | C26: =+'Scenario 0'!E37 | D26: =+'Scenario 0'!F37 | E26: =+'Scenario 0'!G37 | F26: =+'Scenario 0'!H37 | G26: =+'Scenario 0'!I37 | H26: =+'Scenario 0'!J37 | I26: =+'Scenario 0'!K37 | J26: =+'Scenario 0'!L37 | ... M26: =+'Scenario 0'!O37 | O26: Training Charge | P26: =+'Scenario 0'!E37/Dashboard!$E$16 | Q26: =+'Scenario 0'!F37/Dashboard!$E$16 | R26: =+'Scenario 0'!G37/Dashboard!$E$16 | S26: =+'Scenario 0'!H37/Dashboard!$E$16 | T26: =+'Scenario 0'!I37/Dashboard!$E$16 | U26: =+'Scenario 0'!J37/Dashboard!$E$16 | V26: =+'Scenario 0'!K37/Dashboard!$E$16 | W26: =+'Scenario 0'!L37/Dashboard!$E$16 | ... Z26: =+'Scenario 0'!O37/Dashboard!$E$16
... B48: Total Operating and Maint. | C48: =+'Scenario 0'!E59 | D48: =+'Scenario 0'!F59 | E48: =+'Scenario 0'!G59 | F48: =+'Scenario 0'!H59 | G48: =+'Scenario 0'!I59 | H48: =+'Scenario 0'!J59 | I48: =+'Scenario 0'!K59 | J48: =+'Scenario 0'!L59 | ... M48: =+'Scenario 0'!O59 | O48: Total Operating and Maint. | P48: =+'Scenario 0'!E59/Dashboard!$E$16 | Q48: =+'Scenario 0'!F59/Dashboard!$E$16 | R48: =+'Scenario 0'!G59/Dashboard!$E$16 | S48: =+'Scenario 0'!H59/Dashboard!$E$16 | T48: =+'Scenario 0'!I59/Dashboard!$E$16 | U48: =+'Scenario 0'!J59/Dashboard!$E$16 | V48: =+'Scenario 0'!K59/Dashboard!$E$16 | W48: =+'Scenario 0'!L59/Dashboard!$E$16 | ... Z48: =+'Scenario 0'!O59/Dashboard!$E$16
C49: =+'Scenario 0'!R60/Dashboard!$E$16 | D49: =+'Scenario 0'!S60/Dashboard!$E$16 | E49: =+'Scenario 0'!T60/Dashboard!$E$16 | F49: =+'Scenario 0'!U60/Dashboard!$E$16 | G49: =+'Scenario 0'!V60/Dashboard!$E$16 | H49: =+'Scenario 0'!W60/Dashboard!$E$16 | I49: =+'Scenario 0'!X60/Dashboard!$E$16 | J49: =+'Scenario 0'!Y60/Dashboard!$E$16 | ... M49: =+'Scenario 0'!AB60/Dashboard!$E$16 | P49: =+'Scenario 0'!E60/Dashboard!$E$16 | Q49: =+'Scenario 0'!F60/Dashboard!$E$16 | R49: =+'Scenario 0'!G60/Dashboard!$E$16 | S49: =+'Scenario 0'!H60/Dashboard!$E$16 | T49: =+'Scenario 0'!I60/Dashboard!$E$16 | U49: =+'Scenario 0'!J60/Dashboard!$E$16 | V49: =+'Scenario 0'!K60/Dashboard!$E$16 | W49: =+'Scenario 0'!L60/Dashboard!$E$16 | ... Z49: =+'Scenario 0'!O60/Dashboard!$E$16
B50: Landscaping/Grounds Contract | C50: =+'Scenario 0'!E61 | D50: =+'Scenario 0'!F61 | E50: =+'Scenario 0'!G61 | F50: =+'Scenario 0'!H61 | G50: =+'Scenario 0'!I61 | H50: =+'Scenario 0'!J61 | I50: =+'Scenario 0'!K61 | J50: =+'Scenario 0'!L61 | ... M50: =+'Scenario 0'!O61 | O50: Landscaping/Grounds Contract | P50: =+'Scenario 0'!E61/Dashboard!$E$16 | Q50: =+'Scenario 0'!F61/Dashboard!$E$16 | R50: =+'Scenario 0'!G61/Dashboard!$E$16 | S50: =+'Scenario 0'!H61/Dashboard!$E$16 | T50: =+'Scenario 0'!I61/Dashboard!$E$16 | U50: =+'Scenario 0'!J61/Dashboard!$E$16 | V50: =+'Scenario 0'!K61/Dashboard!$E$16 | W50: =+'Scenario 0'!L61/Dashboard!$E$16 | ... Z50: =+'Scenario 0'!O61/Dashboard!$E$16
B51: Fire & Safety System | C51: =+'Scenario 0'!E62 | D51: =+'Scenario 0'!F62 | E51: =+'Scenario 0'!G62 | F51: =+'Scenario 0'!H62 | G51: =+'Scenario 0'!I62 | H51: =+'Scenario 0'!J62 | I51: =+'Scenario 0'!K62 | J51: =+'Scenario 0'!L62 | ... M51: =+'Scenario 0'!O62 | O51: Fire & Safety System | P51: =+'Scenario 0'!E62/Dashboard!$E$16 | Q51: =+'Scenario 0'!F62/Dashboard!$E$16 | R51: =+'Scenario 0'!G62/Dashboard!$E$16 | S51: =+'Scenario 0'!H62/Dashboard!$E$16 | T51: =+'Scenario 0'!I62/Dashboard!$E$16 | U51: =+'Scenario 0'!J62/Dashboard!$E$16 | V51: =+'Scenario 0'!K62/Dashboard!$E$16 | W51: =+'Scenario 0'!L62/Dashboard!$E$16 | ... Z51: =+'Scenario 0'!O62/Dashboard!$E$16
B52: Security | C52: =+'Scenario 0'!E63 | D52: =+'Scenario 0'!F63 | E52: =+'Scenario 0'!G63 | F52: =+'Scenario 0'!H63 | G52: =+'Scenario 0'!I63 | H52: =+'Scenario 0'!J63 | I52: =+'Scenario 0'!K63 | J52: =+'Scenario 0'!L63 | ... M52: =+'Scenario 0'!O63 | O52: Security | P52: =+'Scenario 0'!E63/Dashboard!$E$16 | Q52: =+'Scenario 0'!F63/Dashboard!$E$16 | R52: =+'Scenario 0'!G63/Dashboard!$E$16 | S52: =+'Scenario 0'!H63/Dashboard!$E$16 | T52: =+'Scenario 0'!I63/Dashboard!$E$16 | U52: =+'Scenario 0'!J63/Dashboard!$E$16 | V52: =+'Scenario 0'!K63/Dashboard!$E$16 | W52: =+'Scenario 0'!L63/Dashboard!$E$16 | ... Z52: =+'Scenario 0'!O63/Dashboard!$E$16
B53: Pest Control | C53: =+'Scenario 0'!E64 | D53: =+'Scenario 0'!F64 | E53: =+'Scenario 0'!G64 | F53: =+'Scenario 0'!H64 | G53: =+'Scenario 0'!I64 | H53: =+'Scenario 0'!J64 | I53: =+'Scenario 0'!K64 | J53: =+'Scenario 0'!L64 | ... M53: =+'Scenario 0'!O64 | O53: Pest Control | P53: =+'Scenario 0'!E64/Dashboard!$E$16 | Q53: =+'Scenario 0'!F64/Dashboard!$E$16 | R53: =+'Scenario 0'!G64/Dashboard!$E$16 | S53: =+'Scenario 0'!H64/Dashboard!$E$16 | T53: =+'Scenario 0'!I64/Dashboard!$E$16 | U53: =+'Scenario 0'!J64/Dashboard!$E$16 | V53: =+'Scenario 0'!K64/Dashboard!$E$16 | W53: =+'Scenario 0'!L64/Dashboard!$E$16 | ... Z53: =+'Scenario 0'!O64/Dashboard!$E$16
B54: Misc. Contracts | C54: =+'Scenario 0'!E65 | D54: =+'Scenario 0'!F65 | E54: =+'Scenario 0'!G65 | F54: =+'Scenario 0'!H65 | G54: =+'Scenario 0'!I65 | H54: =+'Scenario 0'!J65 | I54: =+'Scenario 0'!K65 | J54: =+'Scenario 0'!L65 | ... M54: =+'Scenario 0'!O65 | O54: Misc. Contracts | P54: =+'Scenario 0'!E65/Dashboard!$E$16 | Q54: =+'Scenario 0'!F65/Dashboard!$E$16 | R54: =+'Scenario 0'!G65/Dashboard!$E$16 | S54: =+'Scenario 0'!H65/Dashboard!$E$16 | T54: =+'Scenario 0'!I65/Dashboard!$E$16 | U54: =+'Scenario 0'!J65/Dashboard!$E$16 | V54: =+'Scenario 0'!K65/Dashboard!$E$16 | W54: =+'Scenario 0'!L65/Dashboard!$E$16 | ... Z54: =+'Scenario 0'!O65/Dashboard!$E$16
B55: Elevator Costs | C55: =+'Scenario 0'!E66 | D55: =+'Scenario 0'!F66 | E55: =+'Scenario 0'!G66 | F55: =+'Scenario 0'!H66 | G55: =+'Scenario 0'!I66 | H55: =+'Scenario 0'!J66 | I55: =+'Scenario 0'!K66 | J55: =+'Scenario 0'!L66 | ... M55: =+'Scenario 0'!O66 | O55: Elevator Costs | P55: =+'Scenario 0'!E66/Dashboard!$E$16 | Q55: =+'Scenario 0'!F66/Dashboard!$E$16 | R55: =+'Scenario 0'!G66/Dashboard!$E$16 | S55: =+'Scenario 0'!H66/Dashboard!$E$16 | T55: =+'Scenario 0'!I66/Dashboard!$E$16 | U55: =+'Scenario 0'!J66/Dashboard!$E$16 | V55: =+'Scenario 0'!K66/Dashboard!$E$16 | W55: =+'Scenario 0'!L66/Dashboard!$E$16 | ... Z55: =+'Scenario 0'!O66/Dashboard!$E$16
B56: Snow | C56: =+'Scenario 0'!E67 | D56: =+'Scenario 0'!F67 | E56: =+'Scenario 0'!G67 | F56: =+'Scenario 0'!H67 | G56: =+'Scenario 0'!I67 | H56: =+'Scenario 0'!J67 | I56: =+'Scenario 0'!K67 | J56: =+'Scenario 0'!L67 | ... M56: =+'Scenario 0'!O67 | O56: Snow | P56: =+'Scenario 0'!E67/Dashboard!$E$16 | Q56: =+'Scenario 0'!F67/Dashboard!$E$16 | R56: =+'Scenario 0'!G67/Dashboard!$E$16 | S56: =+'Scenario 0'!H67/Dashboard!$E$16 | T56: =+'Scenario 0'!I67/Dashboard!$E$16 | U56: =+'Scenario 0'!J67/Dashboard!$E$16 | V56: =+'Scenario 0'!K67/Dashboard!$E$16 | W56: =+'Scenario 0'!L67/Dashboard!$E$16 | ... Z56: =+'Scenario 0'!O67/Dashboard!$E$16
B57: Misc. Operating & Maint. | C57: =+'Scenario 0'!E68 | D57: =+'Scenario 0'!F68 | E57: =+'Scenario 0'!G68 | F57: =+'Scenario 0'!H68 | G57: =+'Scenario 0'!I68 | H57: =+'Scenario 0'!J68 | I57: =+'Scenario 0'!K68 | J57: =+'Scenario 0'!L68 | ... M57: =+'Scenario 0'!O68 | O57: Misc. Operating & Maint. | P57: =+'Scenario 0'!E68/Dashboard!$E$16 | Q57: =+'Scenario 0'!F68/Dashboard!$E$16 | R57: =+'Scenario 0'!G68/Dashboard!$E$16 | S57: =+'Scenario 0'!H68/Dashboard!$E$16 | T57: =+'Scenario 0'!I68/Dashboard!$E$16 | U57: =+'Scenario 0'!J68/Dashboard!$E$16 | V57: =+'Scenario 0'!K68/Dashboard!$E$16 | W57: =+'Scenario 0'!L68/Dashboard!$E$16 | ... Z57: =+'Scenario 0'!O68/Dashboard!$E$16
B58: Total Contract Expenses | C58: =+'Scenario 0'!E69 | D58: =+'Scenario 0'!F69 | E58: =+'Scenario 0'!G69 | F58: =+'Scenario 0'!H69 | G58: =+'Scenario 0'!I69 | H58: =+'Scenario 0'!J69 | I58: =+'Scenario 0'!K69 | J58: =+'Scenario 0'!L69 | ... M58: =+'Scenario 0'!O69 | O58: Total Contract Expenses | P58: =+'Scenario 0'!E69/Dashboard!$E$16 | Q58: =+'Scenario 0'!F69/Dashboard!$E$16 | R58: =+'Scenario 0'!G69/Dashboard!$E$16 | S58: =+'Scenario 0'!H69/Dashboard!$E$16 | T58: =+'Scenario 0'!I69/Dashboard!$E$16 | U58: =+'Scenario 0'!J69/Dashboard!$E$16 | V58: =+'Scenario 0'!K69/Dashboard!$E$16 | W58: =+'Scenario 0'!L69/Dashboard!$E$16 | ... Z58: =+'Scenario 0'!O69/Dashboard!$E$16
B60: Real Estate Taxes | C60: =+'Scenario 0'!E71 | D60: =+'Scenario 0'!F71 | E60: =+'Scenario 0'!G71 | F60: =+'Scenario 0'!H71 | G60: =+'Scenario 0'!I71 | H60: =+'Scenario 0'!J71 | I60: =+'Scenario 0'!K71 | J60: =+'Scenario 0'!L71 | ... M60: =+'Scenario 0'!O71 | O60: Real Estate Taxes | P60: =+'Scenario 0'!E71/Dashboard!$E$16 | Q60: =+'Scenario 0'!F71/Dashboard!$E$16 | R60: =+'Scenario 0'!G71/Dashboard!$E$16 | S60: =+'Scenario 0'!H71/Dashboard!$E$16 | T60: =+'Scenario 0'!I71/Dashboard!$E$16 | U60: =+'Scenario 0'!J71/Dashboard!$E$16 | V60: =+'Scenario 0'!K71/Dashboard!$E$16 | W60: =+'Scenario 0'!L71/Dashboard!$E$16 | ... Z60: =+'Scenario 0'!O71/Dashboard!$E$16
B61: Property & Liability Insurance | C61: =+'Scenario 0'!E72 | D61: =+'Scenario 0'!F72 | E61: =+'Scenario 0'!G72 | F61: =+'Scenario 0'!H72 | G61: =+'Scenario 0'!I72 | H61: =+'Scenario 0'!J72 | I61: =+'Scenario 0'!K72 | J61: =+'Scenario 0'!L72 | ... M61: =+'Scenario 0'!O72 | O61: Property & Liability Insurance | P61: =+'Scenario 0'!E72/Dashboard!$E$16 | Q61: =+'Scenario 0'!F72/Dashboard!$E$16 | R61: =+'Scenario 0'!G72/Dashboard!$E$16 | S61: =+'Scenario 0'!H72/Dashboard!$E$16 | T61: =+'Scenario 0'!I72/Dashboard!$E$16 | U61: =+'Scenario 0'!J72/Dashboard!$E$16 | V61: =+'Scenario 0'!K72/Dashboard!$E$16 | W61: =+'Scenario 0'!L72/Dashboard!$E$16 | ... Z61: =+'Scenario 0'!O72/Dashboard!$E$16
B62: Workmens Comp | C62: =+'Scenario 0'!E73 | D62: =+'Scenario 0'!F73 | E62: =+'Scenario 0'!G73 | F62: =+'Scenario 0'!H73 | G62: =+'Scenario 0'!I73 | H62: =+'Scenario 0'!J73 | I62: =+'Scenario 0'!K73 | J62: =+'Scenario 0'!L73 | ... M62: =+'Scenario 0'!O73 | O62: Workmens Comp | P62: =+'Scenario 0'!E73/Dashboard!$E$16 | Q62: =+'Scenario 0'!F73/Dashboard!$E$16 | R62: =+'Scenario 0'!G73/Dashboard!$E$16 | S62: =+'Scenario 0'!H73/Dashboard!$E$16 | T62: =+'Scenario 0'!I73/Dashboard!$E$16 | U62: =+'Scenario 0'!J73/Dashboard!$E$16 | V62: =+'Scenario 0'!K73/Dashboard!$E$16 | W62: =+'Scenario 0'!L73/Dashboard!$E$16 | ... Z62: =+'Scenario 0'!O73/Dashboard!$E$16
... B68: Total Operating Expenses | C68: =+'Scenario 0'!E79 | D68: =+'Scenario 0'!F79 | E68: =+'Scenario 0'!G79 | F68: =+'Scenario 0'!H79 | G68: =+'Scenario 0'!I79 | H68: =+'Scenario 0'!J79 | I68: =+'Scenario 0'!K79 | J68: =+'Scenario 0'!L79 | ... M68: =+'Scenario 0'!O79 | O68: Total Operating Expenses | P68: =+'Scenario 0'!E79/Dashboard!$E$16 | Q68: =+'Scenario 0'!F79/Dashboard!$E$16 | R68: =+'Scenario 0'!G79/Dashboard!$E$16 | S68: =+'Scenario 0'!H79/Dashboard!$E$16 | T68: =+'Scenario 0'!I79/Dashboard!$E$16 | U68: =+'Scenario 0'!J79/Dashboard!$E$16 | V68: =+'Scenario 0'!K79/Dashboard!$E$16 | W68: =+'Scenario 0'!L79/Dashboard!$E$16 | ... Z68: =+'Scenario 0'!O79/Dashboard!$E$16

Sheet Return Summary
B2: Return Summary (Gross)
B3: Scenario 1
D4: Unlevered | E4: Levered
B5: IRR | D5: =+'Scenario 1'!$E$122 | E5: =+'Scenario 1'!$E$134
B6: MOIC | D6: =+'Scenario 1'!$E$123 | E6: =+'Scenario 1'!$E$135
B7: Profit ($m) | D7: =+('Scenario 1'!$J$119+'Scenario 1'!$E$119)/1000000 | E7: =+('Scenario 1'!$J$131+'Scenario 1'!$E$131)/1000000
B9: Return Summary (Gross)
B10: Scenario 2
D11: Unlevered | E11: Levered
B12: IRR | D12: =+'Scenario 2'!$E$122 | E12: =+'Scenario 2'!$E$134
B13: MOIC | D13: =+'Scenario 2'!$E$123 | E13: =+'Scenario 2'!$E$135
B14: Profit ($m) | D14: =+('Scenario 2'!$J$119+'Scenario 2'!$E$119)/1000000 | E14: =+('Scenario 2'!$J$131+'Scenario 2'!$E$131)/1000000

Sheet Waterfall -->

Sheet Partnership Terms + Fees
B2: Granite Park | G2: =TODAY()
B3: Partnership Assumptions / Return Summary
B5: Partnership Assumptions
C6: Hurdle | F6: Cash Flow Distribution
B7: Quarterly | C7: Preferred Return | D7: Equity Multiple | E7: Promote | F7: LP | G7: Granite Park
B8: Tier I | C8: 0.08 | D8: 0 | E8: Pari-Passu | F8: 0.75 | G8: 0.25
B9: Tier II | C9: 0.15 | D9: 1.7 | E9: 0.2 | F9: 0.72 | G9: 0.28
B10: Tier III | C10: 0.2 | D10: 2 | E10: 0.25 | F10: 0.675 | G10: 0.325
B11: Tier IV | C11: 1.5 | D11: 0 | E11: 0.3 | F11: 0.63 | G11: 0.37
B12: Thereafter | E12: 0.35 | F12: 0.585 | G12: 0.415
B14: Return Summary
C15: Deal-Level | D15: =F7 | E15: =G7
B16: IRR | C16: ='Promote Cash Flow'!D23 | D16: ='Promote Cash Flow'!D53 | E16: ='Promote Cash Flow'!D72
B17: MOIC | C17: ='Promote Cash Flow'!D24 | D17: ='Promote Cash Flow'!D55 | E17: ='Promote Cash Flow'!D74
B18: Profit | C18: ='Promote Cash Flow'!D25 | D18: ='Promote Cash Flow'!D54 | E18: ='Promote Cash Flow'!D73
B19: % of Profit | C19: N/A | D19: ='Promote Cash Flow'!D56 | E19: ='Promote Cash Flow'!D75
B20: $ Value of Promote | C20: N/A | D20: N/A | E20: =SUM('Promote Cash Flow'!D62,'Promote Cash Flow'!D64,'Promote Cash Flow'!D66,'Promote Cash Flow'!D68)

Sheet Promote Cash Flow
DW1: x
C2: ='Partnership Terms + Fees'!B2 | DW2: x
C3: Waterfall | DW3: x
C5: Sale Month | D5: =MAX('Scenario 2'!E110:J110)*12 | DW5: x
C7: Analysis Year | F7: 0 | G7: =ROUNDUP(G8/12,) | H7: =ROUNDUP(H8/12,) | I7: =ROUNDUP(I8/12,) | J7: =ROUNDUP(J8/12,) | K7: =ROUNDUP(K8/12,) | L7: =ROUNDUP(L8/12,) | M7: =ROUNDUP(M8/12,) | N7: =ROUNDUP(N8/12,) | ... DV7: =ROUNDUP(DV8/12,) | DW7: x
C8: Analysis Month | F8: 0 | G8: =F8+1 | H8: =G8+1 | I8: =H8+1 | J8: =I8+1 | K8: =J8+1 | L8: =K8+1 | M8: =L8+1 | N8: =M8+1 | ... DV8: =DU8+1 | DW8: x
C9: Date | F9: =EOMONTH(TODAY(),1) | G9: =EOMONTH(F9,1) | H9: =EOMONTH(G9,1) | I9: =EOMONTH(H9,1) | J9: =EOMONTH(I9,1) | K9: =EOMONTH(J9,1) | L9: =EOMONTH(K9,1) | M9: =EOMONTH(L9,1) | N9: =EOMONTH(M9,1) | ... DV9: =EOMONTH(DU9,1) | DW9: x
DW10: x
C11: Unlevered Cash Flow Pre-Fees | F11: =IF(F8>$D$5,0,'Scenario 2'!E119) | G11: =IF(G8>$D$5,0,IFERROR(INDEX('Scenario 2'!$F$120:$J$120,MATCH(G7,'Scenario 2'!$F$110:$J$110,0))/12,0)) | H11: =IF(H8>$D$5,0,IFERROR(INDEX('Scenario 2'!$F$120:$J$120,MATCH(H7,'Scenario 2'!$F$110:$J$110,0))/12,0)) | I11: =IF(I8>$D$5,0,IFERROR(INDEX('Scenario 2'!$F$120:$J$120,MATCH(I7,'Scenario 2'!$F$110:$J$110,0))/12,0)) | J11: =IF(J8>$D$5,0,IFERROR(INDEX('Scenario 2'!$F$120:$J$120,MATCH(J7,'Scenario 2'!$F$110:$J$110,0))/12,0)) | K11: =IF(K8>$D$5,0,IFERROR(INDEX('Scenario 2'!$F$120:$J$120,MATCH(K7,'Scenario 2'!$F$110:$J$110,0))/12,0)) | L11: =IF(L8>$D$5,0,IFERROR(INDEX('Scenario 2'!$F$120:$J$120,MATCH(L7,'Scenario 2'!$F$110:$J$110,0))/12,0)) | M11: =IF(M8>$D$5,0,IFERROR(INDEX('Scenario 2'!$F$120:$J$120,MATCH(M7,'Scenario 2'!$F$110:$J$110,0))/12,0)) | N11: =IF(N8>$D$5,0,IFERROR(INDEX('Scenario 2'!$F$120:$J$120,MATCH(N7,'Scenario 2'!$F$110:$J$110,0))/12,0)) | ... DV11: =IF(DV8>$D$5,0,IFERROR(INDEX('Scenario 2'!$F$120:$J$120,MATCH(DV7,'Scenario 2'!$F$110:$J$110,0))/12,0)) | DW11: x
C12: Sale Proceeds | G12: =IF(G8=$D$5,SUM('Scenario 2'!$F$126:$J$126),0) | H12: =IF(H8=$D$5,SUM('Scenario 2'!$F$126:$J$126),0) | I12: =IF(I8=$D$5,SUM('Scenario 2'!$F$126:$J$126),0) | J12: =IF(J8=$D$5,SUM('Scenario 2'!$F$126:$J$126),0) | K12: =IF(K8=$D$5,SUM('Scenario 2'!$F$126:$J$126),0) | L12: =IF(L8=$D$5,SUM('Scenario 2'!$F$126:$J$126),0) | M12: =IF(M8=$D$5,SUM('Scenario 2'!$F$126:$J$126),0) | N12: =IF(N8=$D$5,SUM('Scenario 2'!$F$126:$J$126),0) | ... DV12: =IF(DV8=$D$5,SUM('Scenario 2'!$F$126:$J$126),0) | DW12: x
C13: Unlevered Cash Flows | F13: =SUM(F11:F12) | G13: =SUM(G11:G12) | H13: =SUM(H11:H12) | I13: =SUM(I11:I12) | J13: =SUM(J11:J12) | K13: =SUM(K11:K12) | L13: =SUM(L11:L12) | M13: =SUM(M11:M12) | ... DV13: =SUM(DV11:DV12) | DW13: x
DW14: x
C15: Unlevered Deal-Level Returns | DW15: x
C16: IRR | D16: =XIRR(F13:DV13,$F$9:$DV$9) | DW16: x
C17: MOIC | D17: {=SUMPRODUCT(--(F13:DV13>0),F13:DV13)/-SUMPRODUCT(--(F13:DV13<0),F13:DV13)} | DW17: x
C18: Profit | D18: =SUM(F13:DV13) | DW18: x
DW19: x
C20: Levered Cash Flow | F20: =+'Scenario 2'!E131 | G20: =IFERROR(INDEX('Scenario 2'!$F$132:$J$132,MATCH(G7,'Scenario 2'!$F$110:$J$110,0))/12,0)+IF($D$5=G$8,SUM('Scenario 2'!$F$126:$J$126,'Scenario 2'!$F$129:$J$129)) | H20: =IFERROR(INDEX('Scenario 2'!$F$132:$J$132,MATCH(H7,'Scenario 2'!$F$110:$J$110,0))/12,0)+IF($D$5=H$8,SUM('Scenario 2'!$F$126:$J$126,'Scenario 2'!$F$129:$J$129)) | I20: =IFERROR(INDEX('Scenario 2'!$F$132:$J$132,MATCH(I7,'Scenario 2'!$F$110:$J$110,0))/12,0)+IF($D$5=I$8,SUM('Scenario 2'!$F$126:$J$126,'Scenario 2'!$F$129:$J$129)) | J20: =IFERROR(INDEX('Scenario 2'!$F$132:$J$132,MATCH(J7,'Scenario 2'!$F$110:$J$110,0))/12,0)+IF($D$5=J$8,SUM('Scenario 2'!$F$126:$J$126,'Scenario 2'!$F$129:$J$129)) | K20: =IFERROR(INDEX('Scenario 2'!$F$132:$J$132,MATCH(K7,'Scenario 2'!$F$110:$J$110,0))/12,0)+IF($D$5=K$8,SUM('Scenario 2'!$F$126:$J$126,'Scenario 2'!$F$129:$J$129)) | L20: =IFERROR(INDEX('Scenario 2'!$F$132:$J$132,MATCH(L7,'Scenario 2'!$F$110:$J$110,0))/12,0)+IF($D$5=L$8,SUM('Scenario 2'!$F$126:$J$126,'Scenario 2'!$F$129:$J$129)) | M20: =IFERROR(INDEX('Scenario 2'!$F$132:$J$132,MATCH(M7,'Scenario 2'!$F$110:$J$110,0))/12,0)+IF($D$5=M$8,SUM('Scenario 2'!$F$126:$J$126,'Scenario 2'!$F$129:$J$129)) | N20: =IFERROR(INDEX('Scenario 2'!$F$132:$J$132,MATCH(N7,'Scenario 2'!$F$110:$J$110,0))/12,0)+IF($D$5=N$8,SUM('Scenario 2'!$F$126:$J$126,'Scenario 2'!$F$129:$J$129)) | ... DV20: =IFERROR(INDEX('Scenario 2'!$F$132:$J$132,MATCH(DV7,'Scenario 2'!$F$110:$J$110,0))/12,0)+IF($D$5=DV$8,SUM('Scenario 2'!$F$126:$J$126,'Scenario 2'!$F$129:$J$129)) | DW20: x
F21: =SUM($F20:F20) | G21: =SUM($F20:G20) | H21: =SUM($F20:H20) | I21: =SUM($F20:I20) | J21: =SUM($F20:J20) | K21: =SUM($F20:K20) | L21: =SUM($F20:L20) | M21: =SUM($F20:M20) | ... DV21: =SUM($F20:DV20) | DW21: x
C22: Levered Deal-Level Returns | DW22: x
C23: IRR | D23: =XIRR(F20:DV20,$F$9:$DV$9) | DW23: x
C24: MOIC | D24: {=SUMPRODUCT(--(F20:DV20>0),F20:DV20)/-SUMPRODUCT(--(F20:DV20<0),F20:DV20)} | DW24: x
C25: Profit | D25: =SUM(F20:DV20) | DW25: x
DW26: x
C27: 1 | DW27: x
DW28: x
C29: Equity Contribution Summary
C30: Member | D30: % | DW30: x
C31: ='Partnership Terms + Fees'!F7 | D31: ='Partnership Terms + Fees'!F8 | DW31: x
C32: ='Partnership Terms + Fees'!G7 | D32: ='Partnership Terms + Fees'!G8 | DW32: x
C33: Total | D33: =SUM(D31:D32) | DW33: x
DW34: x
C35: Waterfall Summary
D36: Hurdle | H36: CF Distribution | K36: Compound Interval | DW36: x
C37: Tier | D37: Pref. Return | F37: MOIC | G37: Promote | H37: ='Partnership Terms + Fees'!F7 | I37: ='Partnership Terms + Fees'!G7 | K37: ='Partnership Terms + Fees'!B7 | DW37: x
C38: Tier I | D38: ='Partnership Terms + Fees'!C8 | F38: ='Partnership Terms + Fees'!D8 | G38: Pari-Passu | H38: ='Partnership Terms + Fees'!F8 | I38: ='Partnership Terms + Fees'!G8 | K38: =IF(K37="Monthly",12,4) | DW38: x
C39: Tier II | D39: ='Partnership Terms + Fees'!C9 | F39: ='Partnership Terms + Fees'!D9 | G39: ='Partnership Terms + Fees'!E9 | H39: ='Partnership Terms + Fees'!F9 | I39: ='Partnership Terms + Fees'!G9 | DW39: x
C40: Tier III | D40: ='Partnership Terms + Fees'!C10 | F40: ='Partnership Terms + Fees'!D10 | G40: ='Partnership Terms + Fees'!E10 | H40: ='Partnership Terms + Fees'!F10 | I40: ='Partnership Terms + Fees'!G10 | DW40: x
C41: Tier IV | D41: ='Partnership Terms + Fees'!C11 | F41: ='Partnership Terms + Fees'!D11 | G41: ='Partnership Terms + Fees'!E11 | H41: ='Partnership Terms + Fees'!F11 | I41: ='Partnership Terms + Fees'!G11 | DW41: x
C42: Tier V | G42: ='Partnership Terms + Fees'!E12 | H42: ='Partnership Terms + Fees'!F12 | I42: ='Partnership Terms + Fees'!G12 | DW42: x
DW43: x
C44: =H37&" Cash Flow Summary" | DW44: x
C45: Tier I | D45: =SUM(F45:DV45) | F45: =F126 | G45: =G126 | H45: =H126 | I45: =I126 | J45: =J126 | K45: =K126 | L45: =L126 | M45: =M126 | ... DV45: =DV126 | DW45: x
C46: Tier II | D46: =SUM(F46:DV46) | F46: =F157 | G46: =G157 | H46: =H157 | I46: =I157 | J46: =J157 | K46: =K157 | L46: =L157 | M46: =M157 | ... DV46: =DV157 | DW46: x
C47: Tier III | D47: =SUM(F47:DV47) | F47: =F190 | G47: =G190 | H47: =H190 | I47: =I190 | J47: =J190 | K47: =K190 | L47: =L190 | M47: =M190 | ... DV47: =DV190 | DW47: x
C48: Tier IV | D48: =SUM(F48:DV48) | F48: =F208 | G48: =G208 | H48: =H208 | I48: =I208 | J48: =J208 | K48: =K208 | L48: =L208 | M48: =M208 | ... DV48: =DV208 | DW48: x
C49: Tier V | D49: =SUM(F49:DV49) | F49: =F217 | G49: =G217 | H49: =H217 | I49: =I217 | J49: =J217 | K49: =K217 | L49: =L217 | M49: =M217 | ... DV49: =DV217 | DW49: x
C50: Total | D50: =SUM(D45:D49) | F50: =SUM(F45:F49) | G50: =SUM(G45:G49) | H50: =SUM(H45:H49) | I50: =SUM(I45:I49) | J50: =SUM(J45:J49) | K50: =SUM(K45:K49) | L50: =SUM(L45:L49) | M50: =SUM(M45:M49) | ... DV50: =SUM(DV45:DV49) | DW50: x
DW51: x
C52: =H37&" Returns" | H52: 0 | I52: 1 | DW52: x
C53: IRR | D53: =XIRR(F50:DV50,$F$9:$DV$9) | G53: =D53 | I53: 0.21018254 | DW53: x
C54: Profit | D54: =SUM(F50:DV50) | G54: =D55 | H54: 1.8503289 | I54: 2.3015413 | DW54: x
C55: Equity Multiple | D55: {=SUMPRODUCT(--($F$50:$DV$50>0),$F$50:$DV$50)/-SUMPRODUCT(--($F$50:$DV$50<0),$F$50:$DV$50)} | G55: =D54 | H55: 2742310.7 | I55: 1779532.3 | DW55: x
C56: Profit % | D56: =D54/SUM(D81,D77) | DW56: x
DW57: x
DW58: x
C59: =I37&" Cash Flow Summary" | DW59: x
C60: Tier I | D60: =SUM(F60:DV60) | F60: =F127 | G60: =G127 | H60: =H127 | I60: =I127 | J60: =J127 | K60: =K127 | L60: =L127 | M60: =M127 | ... DV60: =DV127 | DW60: x
C61: Tier II | D61: =SUM(F61:DV61) | F61: =F158 | G61: =G158 | H61: =H158 | I61: =I158 | J61: =J158 | K61: =K158 | L61: =L158 | M61: =M158 | ... DV61: =DV158 | DW61: x
C62: Tier II Promote | D62: =SUM(F62:DV62) | F62: =F159 | G62: =G159 | H62: =H159 | I62: =I159 | J62: =J159 | K62: =K159 | L62: =L159 | M62: =M159 | ... DV62: =DV159 | DW62: x
C63: Tier III | D63: =SUM(F63:DV63) | F63: =F191 | G63: =G191 | H63: =H191 | I63: =I191 | J63: =J191 | K63: =K191 | L63: =L191 | M63: =M191 | ... DV63: =DV191 | DW63: x
C64: Tier III Promote | D64: =SUM(F64:DV64) | F64: =F192 | G64: =G192 | H64: =H192 | I64: =I192 | J64: =J192 | K64: =K192 | L64: =L192 | M64: =M192 | ... DV64: =DV192 | DW64: x
C65: Tier IV | D65: =SUM(F65:DV65) | F65: =F209 | G65: =G209 | H65: =H209 | I65: =I209 | J65: =J209 | K65: =K209 | L65: =L209 | M65: =M209 | ... DV65: =DV209 | DW65: x
C66: Tier IV Promote | D66: =SUM(F66:DV66) | F66: =F210 | G66: =G210 | H66: =H210 | I66: =I210 | J66: =J210 | K66: =K210 | L66: =L210 | M66: =M210 | ... DV66: =DV210 | DW66: x
C67: Tier V | D67: =SUM(F67:DV67) | F67: =F218 | G67: =G218 | H67: =H218 | I67: =I218 | J67: =J218 | K67: =K218 | L67: =L218 | M67: =M218 | ... DV67: =DV218 | DW67: x
C68: Tier V Promote | D68: =SUM(F68:DV68) | F68: =F219 | G68: =G219 | H68: =H219 | I68: =I219 | J68: =J219 | K68: =K219 | L68: =L219 | M68: =M219 | ... DV68: =DV219 | DW68: x
C69: Total | D69: =SUM(D60:D68) | F69: =SUM(F60:F68) | G69: =SUM(G60:G68) | H69: =SUM(H60:H68) | I69: =SUM(I60:I68) | J69: =SUM(J60:J68) | K69: =SUM(K60:K68) | L69: =SUM(L60:L68) | M69: =SUM(M60:M68) | ... DV69: =SUM(DV60:DV68) | DW69: x
DW70: x
C71: =I37&" Returns" | DW71: x
C72: IRR | D72: =XIRR(F69:DV69,$F$9:$DV$9) | DW72: x
C73: Profit | D73: =SUM(F69:DV69) | DW73: x
C74: Equity Multiple | D74: {=SUMPRODUCT(--($F$69:$DV$69>0),$F$69:$DV$69)/-SUMPRODUCT(--($F$69:$DV$69<0),$F$69:$DV$69)} | DW74: x
C75: Profit % | D75: =D73/SUM(D81,D77) | DW75: x
C77: Deal-Level | D77: =SUM(F77:DV77) | F77: =IF($C$27=1,IF(F20<0,F20,0),IF(F13<0,F13,0)) | G77: =IF($C$27=1,IF(G20<0,G20,0),IF(G13<0,G13,0)) | H77: =IF($C$27=1,IF(H20<0,H20,0),IF(H13<0,H13,0)) | I77: =IF($C$27=1,IF(I20<0,I20,0),IF(I13<0,I13,0)) | J77: =IF($C$27=1,IF(J20<0,J20,0),IF(J13<0,J13,0)) | K77: =IF($C$27=1,IF(K20<0,K20,0),IF(K13<0,K13,0)) | L77: =IF($C$27=1,IF(L20<0,L20,0),IF(L13<0,L13,0)) | M77: =IF($C$27=1,IF(M20<0,M20,0),IF(M13<0,M13,0)) | ... DV77: =IF($C$27=1,IF(DV20<0,DV20,0),IF(DV13<0,DV13,0)) | DW77: x
C78: =H37 | D78: =SUM(F78:DV78) | F78: =F77*$D$31 | G78: =G77*$D$31 | H78: =H77*$D$31 | I78: =I77*$D$31 | J78: =J77*$D$31 | K78: =K77*$D$31 | L78: =L77*$D$31 | M78: =M77*$D$31 | ... DV78: =DV77*$D$31 | DW78: x
C79: =I37 | D79: =SUM(F79:DV79) | F79: =F77*$D$32 | G79: =G77*$D$32 | H79: =H77*$D$32 | I79: =I77*$D$32 | J79: =J77*$D$32 | K79: =K77*$D$32 | L79: =L77*$D$32 | M79: =M77*$D$32 | ... DV79: =DV77*$D$32 | DW79: x
DW80: x
C81: Positive Cash Flow | D81: =SUM(F81:DV81) | F81: =IF($C$27=1,IF(F20>0,F20,0),IF(F13>0,F13,0)) | G81: =IF($C$27=1,IF(G20>0,G20,0),IF(G13>0,G13,0)) | H81: =IF($C$27=1,IF(H20>0,H20,0),IF(H13>0,H13,0)) | I81: =IF($C$27=1,IF(I20>0,I20,0),IF(I13>0,I13,0)) | J81: =IF($C$27=1,IF(J20>0,J20,0),IF(J13>0,J13,0)) | K81: =IF($C$27=1,IF(K20>0,K20,0),IF(K13>0,K13,0)) | L81: =IF($C$27=1,IF(L20>0,L20,0),IF(L13>0,L13,0)) | M81: =IF($C$27=1,IF(M20>0,M20,0),IF(M13>0,M13,0)) | ... DV81: =IF($C$27=1,IF(DV20>0,DV20,0),IF(DV13>0,DV13,0)) | DW81: x
DW82: x
C83: Tier 1 | DW83: x
DW84: x
C85: Tier I IRR Hurdle | F85: Compound? | G85: =IF($K$38=12,1,IF(INT(G86)=G86,1,0)) | H85: =IF($K$38=12,1,IF(INT(H86)=H86,1,0)) | I85: =IF($K$38=12,1,IF(INT(I86)=I86,1,0)) | J85: =IF($K$38=12,1,IF(INT(J86)=J86,1,0)) | K85: =IF($K$38=12,1,IF(INT(K86)=K86,1,0)) | L85: =IF($K$38=12,1,IF(INT(L86)=L86,1,0)) | M85: =IF($K$38=12,1,IF(INT(M86)=M86,1,0)) | N85: =IF($K$38=12,1,IF(INT(N86)=N86,1,0)) | ... DV85: =IF($K$38=12,1,IF(INT(DV86)=DV86,1,0)) | DW85: x
C86: =H37 | G86: =1/3 | H86: =G86+1/3 | I86: =H86+1/3 | J86: =I86+1/3 | K86: =J86+1/3 | L86: =K86+1/3 | M86: =L86+1/3 | N86: =M86+1/3 | O86: =N86+1/3 | ... DV86: =DU86+1/3 | DW86: x
C87: Beginning Balance | F87: 0 | G87: =F91 | H87: =G91 | I87: =H91 | J87: =I91 | K87: =J91 | L87: =K91 | M87: =L91 | N87: =M91 | ... DV87: =DU91 | DW87: x
C88: Injections | E88: =SUM(F88:DV88) | F88: =-F78 | G88: =-G78 | H88: =-H78 | I88: =-I78 | J88: =-J78 | K88: =-K78 | L88: =-L78 | M88: =-M78 | ... DV88: =-DV78 | DW88: x
C89: Investor Accruals | E89: =SUM(F89:DV89) | F89: 0 | G89: =G87*(((1+$D$38)^(1/$K$38)-1)*G85) | H89: =H87*(((1+$D$38)^(1/$K$38)-1)*H85) | I89: =I87*(((1+$D$38)^(1/$K$38)-1)*I85) | J89: =J87*(((1+$D$38)^(1/$K$38)-1)*J85) | K89: =K87*(((1+$D$38)^(1/$K$38)-1)*K85) | L89: =L87*(((1+$D$38)^(1/$K$38)-1)*L85) | M89: =M87*(((1+$D$38)^(1/$K$38)-1)*M85) | N89: =N87*(((1+$D$38)^(1/$K$38)-1)*N85) | ... DV89: =DV87*(((1+$D$38)^(1/$K$38)-1)*DV85) | DW89: x
C90: =TEXT(D38,"0.00%")&" Accrual Distribution" | E90: =SUM(F90:DV90) | F90: 0 | G90: =-MIN(G81*$D$126,SUM(G87:G89)) | H90: =-MIN(H81*$D$126,SUM(H87:H89)) | I90: =-MIN(I81*$D$126,SUM(I87:I89)) | J90: =-MIN(J81*$D$126,SUM(J87:J89)) | K90: =-MIN(K81*$D$126,SUM(K87:K89)) | L90: =-MIN(L81*$D$126,SUM(L87:L89)) | M90: =-MIN(M81*$D$126,SUM(M87:M89)) | N90: =-MIN(N81*$D$126,SUM(N87:N89)) | ... DV90: =-MIN(DV81*$D$126,SUM(DV87:DV89)) | DW90: x
C91: Ending Balance | E91: =SUM(E88:E90) | F91: =SUM(F87:F90) | G91: =SUM(G87:G90) | H91: =SUM(H87:H90) | I91: =SUM(I87:I90) | J91: =SUM(J87:J90) | K91: =SUM(K87:K90) | L91: =SUM(L87:L90) | M91: =SUM(M87:M90) | ... DV91: =SUM(DV87:DV90) | DW91: x
DW92: x
C93: Tier I - Levered Multiple Hurdle | AV93: x | DW93: x
C94: Injections | E94: =SUM(F94:BN94) | F94: =F88 | G94: =G88 | H94: =H88 | I94: =I88 | J94: =J88 | K94: =K88 | L94: =L88 | M94: =M88 | ... DV94: =DV88 | DW94: x
C95: Beginning Balance | E95: =SUM(F95:BN95) | F95: 0 | G95: =F98 | H95: =G98 | I95: =H98 | J95: =I98 | K95: =J98 | L95: =K98 | M95: =L98 | N95: =M98 | ... DV95: =DU98 | DW95: x
C96: Investor Accrual | D96: =F38 | E96: =SUM(F96:BN96) | F96: =F94*$D$96 | G96: =G94*$D$96 | H96: =H94*$D$96 | I96: =I94*$D$96 | J96: =J94*$D$96 | K96: =K94*$D$96 | L96: =L94*$D$96 | M96: =M94*$D$96 | ... DV96: =DV94*$D$96 | DW96: x
C97: =C90 | E97: =SUM(F97:BN97) | F97: =F90 | G97: =G90 | H97: =H90 | I97: =I90 | J97: =J90 | K97: =K90 | L97: =L90 | M97: =M90 | ... DV97: =DV90 | DW97: x
C98: Ending Balance | E98: 0 | F98: =SUM(F95:F97) | G98: =SUM(G95:G97) | H98: =SUM(H95:H97) | I98: =SUM(I95:I97) | J98: =SUM(J95:J97) | K98: =SUM(K95:K97) | L98: =SUM(L95:L97) | M98: =SUM(M95:M97) | ... DV98: =SUM(DV95:DV97) | DW98: x
DW99: x
C100: Amount Required to Satisfy greater of | DW100: x
C101: ="IRR and Equity Multiple Test for "&C86 | F101: =MAX(SUM(F87:F89),SUM(F95:F96)) | G101: =MAX(SUM(G87:G89),SUM(G95:G96)) | H101: =MAX(SUM(H87:H89),SUM(H95:H96)) | I101: =MAX(SUM(I87:I89),SUM(I95:I96)) | J101: =MAX(SUM(J87:J89),SUM(J95:J96)) | K101: =MAX(SUM(K87:K89),SUM(K95:K96)) | L101: =MAX(SUM(L87:L89),SUM(L95:L96)) | M101: =MAX(SUM(M87:M89),SUM(M95:M96)) | ... DV101: =MAX(SUM(DV87:DV89),SUM(DV95:DV96)) | DW101: x
DW102: x
C103: ="Total Distribution Per Tier I to "&C86 | E103: -2077334.4 | F103: =-MAX(MIN(F101,F81*$D$126),0) | G103: =-MAX(MIN(G101,G81*$D$126),0) | H103: =-MAX(MIN(H101,H81*$D$126),0) | I103: =-MAX(MIN(I101,I81*$D$126),0) | J103: =-MAX(MIN(J101,J81*$D$126),0) | K103: =-MAX(MIN(K101,K81*$D$126),0) | L103: =-MAX(MIN(L101,L81*$D$126),0) | M103: =-MAX(MIN(M101,M81*$D$126),0) | ... DV103: =-MAX(MIN(DV101,DV81*$D$126),0) | DW103: x
...

Sheet Waterfall Summary
U1: x
B2: ='Promote Cash Flow'!C2 | U2: x
B3: Waterfall Summary | T3: =TODAY() | U3: x
U4: x
B5: Equity Contribution Summary | U5: x
B6: Member | C6: Percentage | U6: x
B7: ='Promote Cash Flow'!C31 | C7: ='Promote Cash Flow'!D31 | U7: x
B8: ='Promote Cash Flow'!C32 | C8: ='Promote Cash Flow'!D32 | U8: x
B9: Total | C9: =SUM(C7:C8) | U9: x
U10: x
B11: Cash Flow Waterfall | U11: x
F12: Cash Flow Distribution | U12: x
B13: Tier | C13: Hurdle | D13: MOIC | E13: Promote | F13: ='Partnership Terms + Fees'!F7 | G13: ='Partnership Terms + Fees'!G7 | U13: x
B14: ='Promote Cash Flow'!C38 | C14: ='Promote Cash Flow'!D38 | D14: ='Promote Cash Flow'!F38 | E14: ='Promote Cash Flow'!G38 | F14: ='Promote Cash Flow'!H38 | G14: ='Promote Cash Flow'!I38 | U14: x
B15: Tier II | C15: ='Promote Cash Flow'!D39 | D15: ='Promote Cash Flow'!F39 | E15: ='Promote Cash Flow'!G39 | F15: ='Promote Cash Flow'!H39 | G15: ='Promote Cash Flow'!I39 | U15: x
B16: Tier III | C16: ='Promote Cash Flow'!D40 | D16: ='Promote Cash Flow'!F40 | E16: ='Promote Cash Flow'!G40 | F16: ='Promote Cash Flow'!H40 | G16: ='Promote Cash Flow'!I40 | U16: x
B17: Tier IV | C17: ='Promote Cash Flow'!D41 | D17: ='Promote Cash Flow'!F41 | E17: ='Promote Cash Flow'!G41 | F17: ='Promote Cash Flow'!H41 | G17: ='Promote Cash Flow'!I41 | U17: x
B18: Thereafter | D18: ='Promote Cash Flow'!F42 | E18: ='Promote Cash Flow'!G41 | F18: ='Promote Cash Flow'!H42 | G18: ='Promote Cash Flow'!I42 | U18: x
U19: x
B20: ='Promote Cash Flow'!C44 | D20: Closing | E20: 1 | F20: =E20+1 | G20: =F20+1 | H20: =G20+1 | I20: =H20+1 | J20: =I20+1 | K20: =J20+1 | L20: =K20+1 | M20: =L20+1 | ... S20: =R20+1 | T20: Total | U20: x
B21: Tier I | C21: =SUM(D21:M21) | D21: ='Promote Cash Flow'!F45 | E21: =SUMIF('Promote Cash Flow'!$G$7:$DV$7,E$20,'Promote Cash Flow'!$G45:$DV45) | F21: =SUMIF('Promote Cash Flow'!$G$7:$DV$7,F$20,'Promote Cash Flow'!$G45:$DV45) | G21: =SUMIF('Promote Cash Flow'!$G$7:$DV$7,G$20,'Promote Cash Flow'!$G45:$DV45) | H21: =SUMIF('Promote Cash Flow'!$G$7:$DV$7,H$20,'Promote Cash Flow'!$G45:$DV45) | I21: =SUMIF('Promote Cash Flow'!$G$7:$DV$7,I$20,'Promote Cash Flow'!$G45:$DV45) | J21: =SUMIF('Promote Cash Flow'!$G$7:$DV$7,J$20,'Promote Cash Flow'!$G45:$DV45) | K21: =SUMIF('Promote Cash Flow'!$G$7:$DV$7,K$20,'Promote Cash Flow'!$G45:$DV45) | L21: =SUMIF('Promote Cash Flow'!$G$7:$DV$7,L$20,'Promote Cash Flow'!$G45:$DV45) | ... S21: =SUMIF('Promote Cash Flow'!$G$7:$DV$7,S$20,'Promote Cash Flow'!$G45:$DV45) | T21: =SUM(D21:S21) | U21: x
B22: Tier II | C22: =SUM(D22:M22) | D22: ='Promote Cash Flow'!F46 | E22: =SUMIF('Promote Cash Flow'!$G$7:$DV$7,E$20,'Promote Cash Flow'!$G46:$DV46) | F22: =SUMIF('Promote Cash Flow'!$G$7:$DV$7,F$20,'Promote Cash Flow'!$G46:$DV46) | G22: =SUMIF('Promote Cash Flow'!$G$7:$DV$7,G$20,'Promote Cash Flow'!$G46:$DV46) | H22: =SUMIF('Promote Cash Flow'!$G$7:$DV$7,H$20,'Promote Cash Flow'!$G46:$DV46) | I22: =SUMIF('Promote Cash Flow'!$G$7:$DV$7,I$20,'Promote Cash Flow'!$G46:$DV46) | J22: =SUMIF('Promote Cash Flow'!$G$7:$DV$7,J$20,'Promote Cash Flow'!$G46:$DV46) | K22: =SUMIF('Promote Cash Flow'!$G$7:$DV$7,K$20,'Promote Cash Flow'!$G46:$DV46) | L22: =SUMIF('Promote Cash Flow'!$G$7:$DV$7,L$20,'Promote Cash Flow'!$G46:$DV46) | ... S22: =SUMIF('Promote Cash Flow'!$G$7:$DV$7,S$20,'Promote Cash Flow'!$G46:$DV46) | T22: =SUM(D22:S22) | U22: x
B23: Tier III | C23: =SUM(D23:M23) | D23: ='Promote Cash Flow'!F47 | E23: =SUMIF('Promote Cash Flow'!$G$7:$DV$7,E$20,'Promote Cash Flow'!$G47:$DV47) | F23: =SUMIF('Promote Cash Flow'!$G$7:$DV$7,F$20,'Promote Cash Flow'!$G47:$DV47) | G23: =SUMIF('Promote Cash Flow'!$G$7:$DV$7,G$20,'Promote Cash Flow'!$G47:$DV47) | H23: =SUMIF('Promote Cash Flow'!$G$7:$DV$7,H$20,'Promote Cash Flow'!$G47:$DV47) | I23: =SUMIF('Promote Cash Flow'!$G$7:$DV$7,I$20,'Promote Cash Flow'!$G47:$DV47) | J23: =SUMIF('Promote Cash Flow'!$G$7:$DV$7,J$20,'Promote Cash Flow'!$G47:$DV47) | K23: =SUMIF('Promote Cash Flow'!$G$7:$DV$7,K$20,'Promote Cash Flow'!$G47:$DV47) | L23: =SUMIF('Promote Cash Flow'!$G$7:$DV$7,L$20,'Promote Cash Flow'!$G47:$DV47) | ... S23: =SUMIF('Promote Cash Flow'!$G$7:$DV$7,S$20,'Promote Cash Flow'!$G47:$DV47) | T23: =SUM(D23:S23) | U23: x
B24: Tier IV | C24: =SUM(D24:M24) | D24: ='Promote Cash Flow'!F48 | E24: =SUMIF('Promote Cash Flow'!$G$7:$DV$7,E$20,'Promote Cash Flow'!$G48:$DV48) | F24: =SUMIF('Promote Cash Flow'!$G$7:$DV$7,F$20,'Promote Cash Flow'!$G48:$DV48) | G24: =SUMIF('Promote Cash Flow'!$G$7:$DV$7,G$20,'Promote Cash Flow'!$G48:$DV48) | H24: =SUMIF('Promote Cash Flow'!$G$7:$DV$7,H$20,'Promote Cash Flow'!$G48:$DV48) | I24: =SUMIF('Promote Cash Flow'!$G$7:$DV$7,I$20,'Promote Cash Flow'!$G48:$DV48) | J24: =SUMIF('Promote Cash Flow'!$G$7:$DV$7,J$20,'Promote Cash Flow'!$G48:$DV48) | K24: =SUMIF('Promote Cash Flow'!$G$7:$DV$7,K$20,'Promote Cash Flow'!$G48:$DV48) | L24: =SUMIF('Promote Cash Flow'!$G$7:$DV$7,L$20,'Promote Cash Flow'!$G48:$DV48) | ... S24: =SUMIF('Promote Cash Flow'!$G$7:$DV$7,S$20,'Promote Cash Flow'!$G48:$DV48) | T24: =SUM(D24:S24) | U24: x
B25: Thereafter | C25: =SUM(D25:M25) | D25: ='Promote Cash Flow'!F49 | E25: =SUMIF('Promote Cash Flow'!$G$7:$DV$7,E$20,'Promote Cash Flow'!$G49:$DV49) | F25: =SUMIF('Promote Cash Flow'!$G$7:$DV$7,F$20,'Promote Cash Flow'!$G49:$DV49) | G25: =SUMIF('Promote Cash Flow'!$G$7:$DV$7,G$20,'Promote Cash Flow'!$G49:$DV49) | H25: =SUMIF('Promote Cash Flow'!$G$7:$DV$7,H$20,'Promote Cash Flow'!$G49:$DV49) | I25: =SUMIF('Promote Cash Flow'!$G$7:$DV$7,I$20,'Promote Cash Flow'!$G49:$DV49) | J25: =SUMIF('Promote Cash Flow'!$G$7:$DV$7,J$20,'Promote Cash Flow'!$G49:$DV49) | K25: =SUMIF('Promote Cash Flow'!$G$7:$DV$7,K$20,'Promote Cash Flow'!$G49:$DV49) | L25: =SUMIF('Promote Cash Flow'!$G$7:$DV$7,L$20,'Promote Cash Flow'!$G49:$DV49) | ... S25: =SUMIF('Promote Cash Flow'!$G$7:$DV$7,S$20,'Promote Cash Flow'!$G49:$DV49) | T25: =SUM(D25:S25) | U25: x
B26: Total | C26: =SUM(C21:C25) | D26: =SUM(D21:D25) | E26: =SUM(E21:E25) | F26: =SUM(F21:F25) | G26: =SUM(G21:G25) | H26: =SUM(H21:H25) | I26: =SUM(I21:I25) | J26: =SUM(J21:J25) | ... S26: =SUM(S21:S25) | T26: =SUM(D26:S26) | U26: x
U27: x
B28: =B7&" Returns" | U28: x
B29: IRR | C29: ='Promote Cash Flow'!D53 | U29: x
B30: Profit | C30: ='Promote Cash Flow'!D54 | U30: x
B31: ='Promote Cash Flow'!C55 | C31: ='Promote Cash Flow'!D55 | U31: x
B32: ='Promote Cash Flow'!C56 | C32: ='Promote Cash Flow'!D56 | U32: x
U33: x
U34: x
